Workbook
Name UPDATE: 'Data Sheet'!$E$1

Sheet One-Page
B2: UltraTech Cement - One Page Profile
C4: UltraTech Cement Limited is the cement flagship company of the Aditya Birla Group. A USD 8.9 billion building solutions powerhouse, UltraTech is the largest manufacturer of grey cement and ready-mix concrete (RMC) and one of the largest manufacturers of white cement in India. It is the second largest cement company globally by capacity and the largest by sales volume (excluding China).
B6: Key Financial Metrics | C6: =Historical_FS!H10 -> 44286 | D6: =Historical_FS!I10 -> 44651 | E6: =Historical_FS!J10 -> 45016 | F6: =Historical_FS!K10 -> 45382 | G6: =Historical_FS!L10 -> 45747 | I6: Share Price - 5Y
B8: Total Sales | C8: =Historical_FS!H12 -> 44725.8 | D8: =Historical_FS!I12 -> 52598.83 | E8: =Historical_FS!J12 -> 63239.98 | F8: =Historical_FS!K12 -> 70908.14 | G8: =Historical_FS!L12 -> 75955.13
B9: Sales Growth | C9: =Historical_FS!H13 -> 0.054110675 | D9: =Historical_FS!I13 -> 0.17602882 | E9: =Historical_FS!J13 -> 0.20230773 | F9: =Historical_FS!K13 -> 0.12125494 | G9: =Historical_FS!L13 -> 0.071176454
B10: Gross Profit Margin (%) | C10: =Historical_FS!H22 -> 0.54770669 | D10: =Historical_FS!I22 -> 0.50821168 | E10: =Historical_FS!J22 -> 0.44979711 | F10: =Historical_FS!K22 -> 0.47002643 | G10: =Historical_FS!L22 -> 0.46257745
B11: EBITDA Margin (%) | C11: =Historical_FS!H28 -> 0.2724698 | D11: =Historical_FS!I28 -> 0.23163595 | E11: =Historical_FS!J28 -> 0.17594819 | F11: =Historical_FS!K28 -> 0.1908881 | G11: =Historical_FS!L28 -> 0.17370282
B12: EBIT Margin (%) | C12: =Historical_FS!H34 -> 0.21209682 | D12: =Historical_FS!I34 -> 0.18002359 | E12: =Historical_FS!J34 -> 0.13028103 | F12: =Historical_FS!K34 -> 0.14653071 | G12: =Historical_FS!L34 -> 0.12084332
B13: Net Profit Margin (%) | C13: =Historical_FS!H46 -> 0.12211855 | D13: =Historical_FS!I46 -> 0.1394377 | E13: =Historical_FS!J46 -> 0.080224567 | F13: =Historical_FS!K46 -> 0.098775119 | G13: =Historical_FS!L46 -> 0.079515893
B14: Earnings Per Share (In Rs.) | C14: =Historical_FS!H50 -> 189.18774 | D14: =Historical_FS!I50 -> 254.04434 | E14: =Historical_FS!J50 -> 175.73259 | F14: =Historical_FS!K50 -> 242.60339 | G14: =Historical_FS!L50 -> 204.94197
B15: EPS Growth | C15: =Historical_FS!H51 -> -0.050587367 | D15: =Historical_FS!I51 -> 0.34281608 | E15: =Historical_FS!J51 -> -0.30826014 | F15: =Historical_FS!K51 -> 0.38052588 | G15: =Historical_FS!L51 -> -0.15523863
B16: Dividend Per Share (In Rs.) | C16: =Historical_FS!H54 -> 36.993419 | D16: =Historical_FS!I54 -> 37.99619 | E16: =Historical_FS!J54 -> 37.998614 | F16: =Historical_FS!K54 -> 69.997575 | G16: =Historical_FS!L54 -> 77.49474
B17: DPS Growth | C17: =Historical_FS!H55 -> 1.8453442 | D17: =Historical_FS!I55 -> 0.027106742 | E17: =Historical_FS!J55 -> 6.3813301e-05 | F17: =Historical_FS!K55 -> 0.84210862 | G17: =Historical_FS!L55 -> 0.10710607
B19: Key Financial Ratios | C19: =C6 -> 44286 | D19: =D6 -> 44651 | E19: =E6 -> 45016 | F19: =F6 -> 45382 | G19: =G6 -> 45747 | I19: Volume - 5Y
B21: Price to Earnings | C21: 35.58 | D21: 25.93 | E21: 43.4 | F21: 40.96 | G21: ='Relative_Val.'!P16 -> 47.50985
B22: EV/EBITDA | C22: 17.66 | D22: 16.7 | E22: 22.6 | F22: 24.2 | G22: ='Relative_Val.'!O16 -> 23.578018
B23: EV/Sales | C23: 4.82 | D23: 3.93 | E23: 3.75 | F23: 4.2 | G23: ='Relative_Val.'!N16 -> 4.530178
B24: Price to Book Value | C24: 4.8 | D24: 4.1 | E24: 4.3 | F24: 5 | G24: 5.4
B25: Return on Equity (%) | C25: =Ratios!H28 -> 0.1236421 | D25: =Ratios!I28 -> 0.14541927 | E25: =Ratios!J28 -> 0.093390574 | F25: =Ratios!K28 -> 0.11629177 | G25: =Ratios!L28 -> 0.085418129
B26: Return on Capital Employed (%) | C26: =Ratios!H26 -> 0.14396136 | D26: =Ratios!I26 -> 0.15338418 | E26: =Ratios!J26 -> 0.12601228 | F26: =Ratios!K26 -> 0.14505316 | G26: =Ratios!L26 -> 0.096812274
B28: Top 10 Shareholders | C28: No. of Shares (In Cr.) | E28: % Holding | F28: Market Value (In Cr.) | I28: Latest Shareholding
B30: ='Comps Rel.'!Q3 -> Grasim Industries Limited | C30: ='Comps Rel.'!R3 -> 16.533515 | E30: ='Comps Rel.'!S3 -> 0.5611 | F30: ='Comps Rel.'!T3 -> 197360.57
B31: ='Comps Rel.'!Q4 -> LIFE INSURANCE CORPORATION OF INDIA | C31: ='Comps Rel.'!R4 -> 0.6104355 | E31: ='Comps Rel.'!S4 -> 0.0207 | F31: ='Comps Rel.'!T4 -> 7286.7686
B32: ='Comps Rel.'!Q5 -> ICICI PRUDENTIAL NIFTY INFRASTRUCTURE ETF | C32: ='Comps Rel.'!R5 -> 0.6038328 | E32: ='Comps Rel.'!S5 -> 0.0205 | F32: ='Comps Rel.'!T5 -> 7207.9521
B33: ='Comps Rel.'!Q6 -> NPS TRUST-A/C TATA PENSION FUND MANAGEMENT PRIVATE | C33: ='Comps Rel.'!R6 -> 0.5769186 | E33: ='Comps Rel.'!S6 -> 0.0196 | F33: ='Comps Rel.'!T6 -> 6886.6773
B34: ='Comps Rel.'!Q7 -> Pilani Investment and Industries Corporation Limited | C34: ='Comps Rel.'!R7 -> 0.4405944 | E34: ='Comps Rel.'!S7 -> 0.015 | F34: ='Comps Rel.'!T7 -> 5259.3754
B35: ='Comps Rel.'!Q8 -> SBI NIFTY 50 EQUAL WEIGHT INDEX FUND | C35: ='Comps Rel.'!R8 -> 0.4310567 | E35: ='Comps Rel.'!S8 -> 0.0146 | F35: ='Comps Rel.'!T8 -> 5145.5238
B36: ='Comps Rel.'!Q9 -> Government of Singapore - E | C36: ='Comps Rel.'!R9 -> 0.3937328 | E36: ='Comps Rel.'!S9 -> 0.0134 | F36: ='Comps Rel.'!T9 -> 4699.9884
B37: ='Comps Rel.'!Q10 -> KOTAK AGGRESSIVE HYBRID FUND | C37: ='Comps Rel.'!R10 -> 0.3256356 | E37: ='Comps Rel.'!S10 -> 0.0111 | F37: ='Comps Rel.'!T10 -> 3887.1122
B38: ='Comps Rel.'!Q11 -> PT. Indo Bharat Rayon | C38: ='Comps Rel.'!R11 -> 0.2286172 | E38: ='Comps Rel.'!S11 -> 0.0078 | F38: ='Comps Rel.'!T11 -> 2729.0035
B39: ='Comps Rel.'!Q12 -> Hindalco Industries Limited | C39: ='Comps Rel.'!R12 -> 0.1258515 | E39: ='Comps Rel.'!S12 -> 0.0043 | F39: ='Comps Rel.'!T12 -> 1502.2894
B41: Managerial Remuneration (In Cr.) | C41: Designation | E41: Remuneration | F41: X of Median Salary | I41: Capital Structure
B43: Kumar Mangalam Birla | C43: Chairman | E43: 0.043 | F43: - | I43: Share Price as on 10-01-25 | K43: =DCF!E49 -> 11937
B44: K. K. Maheshwari | C44: Vice Chairman | E44: 0.45 | F44: - | I44: Number of Shares o/s | K44: =DCF!E45 -> 29.490848
B45: Mrs. Rajashree Birla | C45: Non-Executive Director | E45: 6.727 | F45: 88.8 | I45: Market Capitalization | K45: =K43*K44 -> 352032.26
B46: K. C. Jhanwar | C46: Managing Director | E46: =13.42+5.26 -> 18.68 | F46: 247.5 | I46: Less: Cash & Equivalents | K46: =DCF!E42 -> 1673.32
B47: Atul Daga | C47: Whole Time Director & CFO | E47: =6.6+2.56 -> 9.16 | F47: 121.4 | I47: Add: Total Debt | K47: =DCF!E43 -> 23031
I48: Add: Minority Interest | K48: 55.94
I49: Enterprise Value | K49: =K45+K47+K48-K46 -> 373445.88
B51: Recent Updates

Sheet Historical_FS
B9: ="Financial Statements"&" - "&'Data Sheet'!B1 -> Financial Statements - ULTRATECH CEMENT LTD
B10: Years | C10: ='Data Sheet'!B16 -> 42460 | D10: ='Data Sheet'!C16 -> 42825 | E10: ='Data Sheet'!D16 -> 43190 | F10: ='Data Sheet'!E16 -> 43555 | G10: ='Data Sheet'!F16 -> 43921 | H10: ='Data Sheet'!G16 -> 44286 | I10: ='Data Sheet'!H16 -> 44651 | J10: ='Data Sheet'!I16 -> 45016 | ... L10: ='Data Sheet'!K16 -> 45747
A11: # | B11: Income Statement
B12: Sales | C12: =IFERROR('Data Sheet'!B17,0) -> 25153.24 | D12: =IFERROR('Data Sheet'!C17,0) -> 25374.94 | E12: =IFERROR('Data Sheet'!D17,0) -> 30978.62 | F12: =IFERROR('Data Sheet'!E17,0) -> 41462.26 | G12: =IFERROR('Data Sheet'!F17,0) -> 42429.89 | H12: =IFERROR('Data Sheet'!G17,0) -> 44725.8 | I12: =IFERROR('Data Sheet'!H17,0) -> 52598.83 | J12: =IFERROR('Data Sheet'!I17,0) -> 63239.98 | ... L12: =IFERROR('Data Sheet'!K17,0) -> 75955.13
B13: =B12&" Growth" -> Sales Growth | C13: =IFERROR((C12/B12)-1,"-") -> - | D13: =IFERROR((D12/C12)-1,"-") -> 0.0088139739 | E13: =IFERROR((E12/D12)-1,"-") -> 0.2208352 | F13: =IFERROR((F12/E12)-1,"-") -> 0.33841533 | G13: =IFERROR((G12/F12)-1,"-") -> 0.023337609 | H13: =IFERROR((H12/G12)-1,"-") -> 0.054110675 | I13: =IFERROR((I12/H12)-1,"-") -> 0.17602882 | J13: =IFERROR((J12/I12)-1,"-") -> 0.20230773 | ... L13: =IFERROR((L12/K12)-1,"-") -> 0.071176454
B15: Other Income | C15: =IFERROR('Data Sheet'!B25,0) -> 463.81 | D15: =IFERROR('Data Sheet'!C25,0) -> 648.12 | E15: =IFERROR('Data Sheet'!D25,0) -> 241.97 | F15: =IFERROR('Data Sheet'!E25,0) -> 350.1 | G15: =IFERROR('Data Sheet'!F25,0) -> 651.06 | H15: =IFERROR('Data Sheet'!G25,0) -> 618.52 | I15: =IFERROR('Data Sheet'!H25,0) -> 669.43 | J15: =IFERROR('Data Sheet'!I25,0) -> 507.11 | ... L15: =IFERROR('Data Sheet'!K25,0) -> 396.74
B16: =B15&" % Sales" -> Other Income % Sales | C16: =IFERROR(C15/C$12,0) -> 0.018439374 | D16: =IFERROR(D15/D$12,0) -> 0.025541735 | E16: =IFERROR(E15/E$12,0) -> 0.0078108709 | F16: =IFERROR(F15/F$12,0) -> 0.0084438234 | G16: =IFERROR(G15/G$12,0) -> 0.015344372 | H16: =IFERROR(H15/H$12,0) -> 0.013829155 | I16: =IFERROR(I15/I$12,0) -> 0.012727089 | J16: =IFERROR(J15/J$12,0) -> 0.0080188197 | ... L16: =IFERROR(L15/L$12,0) -> 0.005223347
B18: COGS | C18: =IFERROR(SUM('Data Sheet'!B18,'Data Sheet'!B20:B22)-1*('Data Sheet'!B19),0) -> 12397.13 | D18: =IFERROR(SUM('Data Sheet'!C18,'Data Sheet'!C20:C22)-1*('Data Sheet'!C19),0) -> 12303.62 | E18: =IFERROR(SUM('Data Sheet'!D18,'Data Sheet'!D20:D22)-1*('Data Sheet'!D19),0) -> 15744.19 | F18: =IFERROR(SUM('Data Sheet'!E18,'Data Sheet'!E20:E22)-1*('Data Sheet'!E19),0) -> 21729.72 | G18: =IFERROR(SUM('Data Sheet'!F18,'Data Sheet'!F20:F22)-1*('Data Sheet'!F19),0) -> 20600.87 | H18: =IFERROR(SUM('Data Sheet'!G18,'Data Sheet'!G20:G22)-1*('Data Sheet'!G19),0) -> 20847.7 | I18: =IFERROR(SUM('Data Sheet'!H18,'Data Sheet'!H20:H22)-1*('Data Sheet'!H19),0) -> 26536.92 | J18: =IFERROR(SUM('Data Sheet'!I18,'Data Sheet'!I20:I22)-1*('Data Sheet'!I19),0) -> 35301.93 | ... L18: =IFERROR(SUM('Data Sheet'!K18,'Data Sheet'!K20:K22)-1*('Data Sheet'!K19),0) -> 41216.74
B19: =B18&" % Sales" -> COGS % Sales | C19: =IFERROR(C18/C12,0) -> 0.49286414 | D19: =IFERROR(D18/D12,0) -> 0.48487287 | E19: =IFERROR(E18/E12,0) -> 0.50822761 | F19: =IFERROR(F18/F12,0) -> 0.52408431 | G19: =IFERROR(G18/G12,0) -> 0.4855273 | H19: =IFERROR(H18/H12,0) -> 0.46612246 | I19: =IFERROR(I18/I12,0) -> 0.5045154 | J19: =IFERROR(J18/J12,0) -> 0.55822171 | ... L19: =IFERROR(L18/L12,0) -> 0.5426459
B21: Gross Profit | C21: =IFERROR(C12+C15-C18,0) -> 13219.92 | D21: =IFERROR(D12+D15-D18,0) -> 13719.44 | E21: =IFERROR(E12+E15-E18,0) -> 15476.4 | F21: =IFERROR(F12+F15-F18,0) -> 20082.64 | G21: =IFERROR(G12+G15-G18,0) -> 22480.08 | H21: =IFERROR(H12+H15-H18,0) -> 24496.62 | I21: =IFERROR(I12+I15-I18,0) -> 26731.34 | J21: =IFERROR(J12+J15-J18,0) -> 28445.16 | ... L21: =IFERROR(L12+L15-L18,0) -> 35135.13
B22: =B21&" % Sales" -> Gross Profit % Sales | C22: =IFERROR(C21/C12,0) -> 0.52557523 | D22: =IFERROR(D21/D12,0) -> 0.54066886 | E22: =IFERROR(E21/E12,0) -> 0.49958326 | F22: =IFERROR(F21/F12,0) -> 0.48435951 | G22: =IFERROR(G21/G12,0) -> 0.52981707 | H22: =IFERROR(H21/H12,0) -> 0.54770669 | I22: =IFERROR(I21/I12,0) -> 0.50821168 | J22: =IFERROR(J21/J12,0) -> 0.44979711 | ... L22: =IFERROR(L21/L12,0) -> 0.46257745
B24: Selling & Other Exp. | C24: =IFERROR(SUM('Data Sheet'!B23:B24),0) -> 7855.14 | D24: =IFERROR(SUM('Data Sheet'!C23:C24),0) -> 7858.88 | E24: =IFERROR(SUM('Data Sheet'!D23:D24),0) -> 9089.4 | F24: =IFERROR(SUM('Data Sheet'!E23:E24),0) -> 12385.6 | G24: =IFERROR(SUM('Data Sheet'!F23:F24),0) -> 12583.05 | H24: =IFERROR(SUM('Data Sheet'!G23:G24),0) -> 12310.19 | I24: =IFERROR(SUM('Data Sheet'!H23:H24),0) -> 14547.56 | J24: =IFERROR(SUM('Data Sheet'!I23:I24),0) -> 17318.2 | ... L24: =IFERROR(SUM('Data Sheet'!K23:K24),0) -> 21941.51
B25: =B24&" % Sales" -> Selling & Other Exp. % Sales | C25: =IFERROR(C24/C12,0) -> 0.31229138 | D25: =IFERROR(D24/D12,0) -> 0.30971029 | E25: =IFERROR(E24/E12,0) -> 0.29340881 | F25: =IFERROR(F24/F12,0) -> 0.29871985 | G25: =IFERROR(G24/G12,0) -> 0.29656099 | H25: =IFERROR(H24/H12,0) -> 0.27523689 | I25: =IFERROR(I24/I12,0) -> 0.27657573 | J25: =IFERROR(J24/J12,0) -> 0.27384892 | ... L25: =IFERROR(L24/L12,0) -> 0.28887463
B27: EBITDA | C27: =IFERROR(C21-C24,0) -> 5364.78 | D27: =IFERROR(D21-D24,0) -> 5860.56 | E27: =IFERROR(E21-E24,0) -> 6387 | F27: =IFERROR(F21-F24,0) -> 7697.04 | G27: =IFERROR(G21-G24,0) -> 9897.03 | H27: =IFERROR(H21-H24,0) -> 12186.43 | I27: =IFERROR(I21-I24,0) -> 12183.78 | J27: =IFERROR(J21-J24,0) -> 11126.96 | ... L27: =IFERROR(L21-L24,0) -> 13193.62
B28: =B27&" % Sales" -> EBITDA % Sales | C28: =IFERROR(C27/C12,0) -> 0.21328386 | D28: =IFERROR(D27/D12,0) -> 0.23095858 | E28: =IFERROR(E27/E12,0) -> 0.20617445 | F28: =IFERROR(F27/F12,0) -> 0.18563966 | G28: =IFERROR(G27/G12,0) -> 0.23325608 | H28: =IFERROR(H27/H12,0) -> 0.2724698 | I28: =IFERROR(I27/I12,0) -> 0.23163595 | J28: =IFERROR(J27/J12,0) -> 0.17594819 | ... L28: =IFERROR(L27/L12,0) -> 0.17370282
B30: Depreciation | C30: =IFERROR('Data Sheet'!B26,0) -> 1377.17 | D30: =IFERROR('Data Sheet'!C26,0) -> 1348.41 | E30: =IFERROR('Data Sheet'!D26,0) -> 1847.93 | F30: =IFERROR('Data Sheet'!E26,0) -> 2450.73 | G30: =IFERROR('Data Sheet'!F26,0) -> 2722.66 | H30: =IFERROR('Data Sheet'!G26,0) -> 2700.23 | I30: =IFERROR('Data Sheet'!H26,0) -> 2714.75 | J30: =IFERROR('Data Sheet'!I26,0) -> 2887.99 | ... L30: =IFERROR('Data Sheet'!K26,0) -> 4014.95
B31: =B30&" % Sales" -> Depreciation % Sales | C31: =IFERROR(C30/C12,0) -> 0.054751197 | D31: =IFERROR(D30/D12,0) -> 0.053139436 | E31: =IFERROR(E30/E12,0) -> 0.059651786 | F31: =IFERROR(F30/F12,0) -> 0.059107487 | G31: =IFERROR(G30/G12,0) -> 0.064168444 | H31: =IFERROR(H30/H12,0) -> 0.060372984 | I31: =IFERROR(I30/I12,0) -> 0.051612365 | J31: =IFERROR(J30/J12,0) -> 0.045667155 | ... L31: =IFERROR(L30/L12,0) -> 0.052859497
B33: EBIT | C33: =IFERROR(C27-C30,0) -> 3987.61 | D33: =IFERROR(D27-D30,0) -> 4512.15 | E33: =IFERROR(E27-E30,0) -> 4539.07 | F33: =IFERROR(F27-F30,0) -> 5246.31 | G33: =IFERROR(G27-G30,0) -> 7174.37 | H33: =IFERROR(H27-H30,0) -> 9486.2 | I33: =IFERROR(I27-I30,0) -> 9469.03 | J33: =IFERROR(J27-J30,0) -> 8238.97 | ... L33: =IFERROR(L27-L30,0) -> 9178.67
B34: =B33&" % Sales" -> EBIT % Sales | C34: =IFERROR(C33/C12,0) -> 0.15853266 | D34: =IFERROR(D33/D12,0) -> 0.17781914 | E34: =IFERROR(E33/E12,0) -> 0.14652267 | F34: =IFERROR(F33/F12,0) -> 0.12653218 | G34: =IFERROR(G33/G12,0) -> 0.16908764 | H34: =IFERROR(H33/H12,0) -> 0.21209682 | I34: =IFERROR(I33/I12,0) -> 0.18002359 | J34: =IFERROR(J33/J12,0) -> 0.13028103 | ... L34: =IFERROR(L33/L12,0) -> 0.12084332
B36: Interest | C36: =IFERROR('Data Sheet'!B27,0) -> 566.3 | D36: =IFERROR('Data Sheet'!C27,0) -> 640.1 | E36: =IFERROR('Data Sheet'!D27,0) -> 1237.6 | F36: =IFERROR('Data Sheet'!E27,0) -> 1777.86 | G36: =IFERROR('Data Sheet'!F27,0) -> 1991.65 | H36: =IFERROR('Data Sheet'!G27,0) -> 1485.65 | I36: =IFERROR('Data Sheet'!H27,0) -> 944.71 | J36: =IFERROR('Data Sheet'!I27,0) -> 822.72 | ... L36: =IFERROR('Data Sheet'!K27,0) -> 1650.54
B37: =B36&" % Sales" -> Interest % Sales | C37: =IFERROR(C36/C12,0) -> 0.022513998 | D37: =IFERROR(D36/D12,0) -> 0.025225675 | E37: =IFERROR(E36/E12,0) -> 0.039950133 | F37: =IFERROR(F36/F12,0) -> 0.042878994 | G37: =IFERROR(G36/G12,0) -> 0.046939787 | H37: =IFERROR(H36/H12,0) -> 0.033216846 | I37: =IFERROR(I36/I12,0) -> 0.017960666 | J37: =IFERROR(J36/J12,0) -> 0.013009492 | ... L37: =IFERROR(L36/L12,0) -> 0.021730461
B39: EBT | C39: =IFERROR(C33-C36,0) -> 3421.31 | D39: =IFERROR(D33-D36,0) -> 3872.05 | E39: =IFERROR(E33-E36,0) -> 3301.47 | F39: =IFERROR(F33-F36,0) -> 3468.45 | G39: =IFERROR(G33-G36,0) -> 5182.72 | H39: =IFERROR(H33-H36,0) -> 8000.55 | I39: =IFERROR(I33-I36,0) -> 8524.32 | J39: =IFERROR(J33-J36,0) -> 7416.25 | ... L39: =IFERROR(L33-L36,0) -> 7528.13
B40: =B39&" % Sales" -> EBT % Sales | C40: =IFERROR(C39/C12,0) -> 0.13601866 | D40: =IFERROR(D39/D12,0) -> 0.15259346 | E40: =IFERROR(E39/E12,0) -> 0.10657253 | F40: =IFERROR(F39/F12,0) -> 0.083653182 | G40: =IFERROR(G39/G12,0) -> 0.12214785 | H40: =IFERROR(H39/H12,0) -> 0.17887998 | I40: =IFERROR(I39/I12,0) -> 0.16206292 | J40: =IFERROR(J39/J12,0) -> 0.11727154 | ... L40: =IFERROR(L39/L12,0) -> 0.099112858
B42: Tax | C42: =IFERROR('Data Sheet'!B29,0) -> 941.69 | D42: =IFERROR('Data Sheet'!C29,0) -> 1158.54 | E42: =IFERROR('Data Sheet'!D29,0) -> 1077.01 | F42: =IFERROR('Data Sheet'!E29,0) -> 1068.07 | G42: =IFERROR('Data Sheet'!F29,0) -> -568.16 | H42: =IFERROR('Data Sheet'!G29,0) -> 2538.7 | I42: =IFERROR('Data Sheet'!H29,0) -> 1190.06 | J42: =IFERROR('Data Sheet'!I29,0) -> 2342.85 | ... L42: =IFERROR('Data Sheet'!K29,0) -> 1488.49
B43: Effective Tax Rate | C43: =IFERROR(C42/C39,0) -> 0.27524252 | D43: =IFERROR(D42/D39,0) -> 0.29920585 | E43: =IFERROR(E42/E39,0) -> 0.32622135 | F43: =IFERROR(F42/F39,0) -> 0.3079387 | G43: =IFERROR(G42/G39,0) -> -0.10962583 | H43: =IFERROR(H42/H39,0) -> 0.31731568 | I43: =IFERROR(I42/I39,0) -> 0.13960762 | J43: =IFERROR(J42/J39,0) -> 0.31590764 | ... L43: =IFERROR(L42/L39,0) -> 0.19772374
B45: Net Profit | C45: =IFERROR(C39-C42,0) -> 2479.62 | D45: =IFERROR(D39-D42,0) -> 2713.51 | E45: =IFERROR(E39-E42,0) -> 2224.46 | F45: =IFERROR(F39-F42,0) -> 2400.38 | G45: =IFERROR(G39-G42,0) -> 5750.88 | H45: =IFERROR(H39-H42,0) -> 5461.85 | I45: =IFERROR(I39-I42,0) -> 7334.26 | J45: =IFERROR(J39-J42,0) -> 5073.4 | ... L45: =IFERROR(L39-L42,0) -> 6039.64
B46: =B45&" % Sales" -> Net Profit % Sales | C46: =IFERROR(C45/C12,0) -> 0.098580541 | D46: =IFERROR(D45/D12,0) -> 0.10693661 | E46: =IFERROR(E45/E12,0) -> 0.071806297 | F46: =IFERROR(F45/F12,0) -> 0.05789313 | G46: =IFERROR(G45/G12,0) -> 0.13553841 | H46: =IFERROR(H45/H12,0) -> 0.12211855 | I46: =IFERROR(I45/I12,0) -> 0.1394377 | J46: =IFERROR(J45/J12,0) -> 0.080224567 | ... L46: =IFERROR(L45/L12,0) -> 0.079515893
B48: No. of Equity Shares | C48: =IFERROR('Data Sheet'!B93,0) -> 27.44 | D48: =IFERROR('Data Sheet'!C93,0) -> 27.45 | E48: =IFERROR('Data Sheet'!D93,0) -> 27.46 | F48: =IFERROR('Data Sheet'!E93,0) -> 27.46 | G48: =IFERROR('Data Sheet'!F93,0) -> 28.86 | H48: =IFERROR('Data Sheet'!G93,0) -> 28.87 | I48: =IFERROR('Data Sheet'!H93,0) -> 28.87 | J48: =IFERROR('Data Sheet'!I93,0) -> 28.87 | ... L48: =IFERROR('Data Sheet'!K93,0) -> 29.47
B50: Earnings Per Share | C50: =IFERROR(C45/C48,0) -> 90.36516 | D50: =IFERROR(D45/D48,0) -> 98.852823 | E50: =IFERROR(E45/E48,0) -> 81.007283 | F50: =IFERROR(F45/F48,0) -> 87.413693 | G50: =IFERROR(G45/G48,0) -> 199.26819 | H50: =IFERROR(H45/H48,0) -> 189.18774 | I50: =IFERROR(I45/I48,0) -> 254.04434 | J50: =IFERROR(J45/J48,0) -> 175.73259 | ... L50: =IFERROR(L45/L48,0) -> 204.94197
B51: =B50&" Growth" -> Earnings Per Share Growth | C51: =IFERROR(C50/ABS(B50)-1,"-") -> - | D51: =IFERROR(D50/ABS(C50)-1,"-") -> 0.093926276 | E51: =IFERROR(E50/ABS(D50)-1,"-") -> -0.18052636 | F51: =IFERROR(F50/ABS(E50)-1,"-") -> 0.079084362 | G51: =IFERROR(G50/ABS(F50)-1,"-") -> 1.2795993 | H51: =IFERROR(H50/ABS(G50)-1,"-") -> -0.050587367 | I51: =IFERROR(I50/ABS(H50)-1,"-") -> 0.34281608 | J51: =IFERROR(J50/ABS(I50)-1,"-") -> -0.30826014 | ... L51: =IFERROR(L50/ABS(K50)-1,"-") -> -0.15523863
D52: =IFERROR(IF(AND(C50<0,D50>0),"Profit Swing",IF(AND(C50>0,D50<0),"Loss-Making",IF(C50=0,"-","-"))),0) -> - | E52: =IFERROR(IF(AND(D50<0,E50>0),"Profit Swing",IF(AND(D50>0,E50<0),"Loss-Making",IF(D50=0,"-","-"))),0) -> - | F52: =IFERROR(IF(AND(E50<0,F50>0),"Profit Swing",IF(AND(E50>0,F50<0),"Loss-Making",IF(E50=0,"-","-"))),0) -> - | G52: =IFERROR(IF(AND(F50<0,G50>0),"Profit Swing",IF(AND(F50>0,G50<0),"Loss-Making",IF(F50=0,"-","-"))),0) -> - | H52: =IFERROR(IF(AND(G50<0,H50>0),"Profit Swing",IF(AND(G50>0,H50<0),"Loss-Making",IF(G50=0,"-","-"))),0) -> - | I52: =IFERROR(IF(AND(H50<0,I50>0),"Profit Swing",IF(AND(H50>0,I50<0),"Loss-Making",IF(H50=0,"-","-"))),0) -> - | J52: =IFERROR(IF(AND(I50<0,J50>0),"Profit Swing",IF(AND(I50>0,J50<0),"Loss-Making",IF(I50=0,"-","-"))),0) -> - | K52: =IFERROR(IF(AND(J50<0,K50>0),"Profit Swing",IF(AND(J50>0,K50<0),"Loss-Making",IF(J50=0,"-","-"))),0) -> - | L52: =IFERROR(IF(AND(K50<0,L50>0),"Profit Swing",IF(AND(K50>0,L50<0),"Loss-Making",IF(K50=0,"-","-"))),0) -> -
B54: Dividend Per Share | C54: =IFERROR('Data Sheet'!B31/Historical_FS!C48,0) -> 9.5010933 | D54: =IFERROR('Data Sheet'!C31/Historical_FS!D48,0) -> 10.000364 | E54: =IFERROR('Data Sheet'!D31/Historical_FS!E48,0) -> 10.500364 | F54: =IFERROR('Data Sheet'!E31/Historical_FS!F48,0) -> 11.501821 | G54: =IFERROR('Data Sheet'!F31/Historical_FS!G48,0) -> 13.001386 | H54: =IFERROR('Data Sheet'!G31/Historical_FS!H48,0) -> 36.993419 | I54: =IFERROR('Data Sheet'!H31/Historical_FS!I48,0) -> 37.99619 | J54: =IFERROR('Data Sheet'!I31/Historical_FS!J48,0) -> 37.998614 | ... L54: =IFERROR('Data Sheet'!K31/Historical_FS!L48,0) -> 77.49474
B55: DPS Growth | C55: =IFERROR(C54/ABS(B54)-1,"-") -> - | D55: =IFERROR(D54/ABS(C54)-1,"-") -> 0.052548795 | E55: =IFERROR(E54/ABS(D54)-1,"-") -> 0.049998165 | F55: =IFERROR(F54/ABS(E54)-1,"-") -> 0.095373517 | G55: =IFERROR(G54/ABS(F54)-1,"-") -> 0.13037633 | H55: =IFERROR(H54/ABS(G54)-1,"-") -> 1.8453442 | I55: =IFERROR(I54/ABS(H54)-1,"-") -> 0.027106742 | J55: =IFERROR(J54/ABS(I54)-1,"-") -> 6.3813301e-05 | ... L55: =IFERROR(L54/ABS(K54)-1,"-") -> 0.10710607
B56: Dividend Payout Ratio | C56: =IFERROR(C54/C50,0) -> 0.10514111 | D56: =IFERROR(D54/D50,0) -> 0.10116417 | E56: =IFERROR(E54/E50,0) -> 0.12962247 | F56: =IFERROR(F54/F50,0) -> 0.13157917 | G56: =IFERROR(G54/G50,0) -> 0.065245667 | H56: =IFERROR(H54/H50,0) -> 0.19553814 | I56: =IFERROR(I54/I50,0) -> 0.14956519 | J56: =IFERROR(J54/J50,0) -> 0.21622975 | ... L56: =IFERROR(L54/L50,0) -> 0.37813015
B57: Retained Earnings | C57: =IFERROR(IF(C50>C54,1-C56,0),0) -> 0.89485889 | D57: =IFERROR(IF(D50>D54,1-D56,0),0) -> 0.89883583 | E57: =IFERROR(IF(E50>E54,1-E56,0),0) -> 0.87037753 | F57: =IFERROR(IF(F50>F54,1-F56,0),0) -> 0.86842083 | G57: =IFERROR(IF(G50>G54,1-G56,0),0) -> 0.93475433 | H57: =IFERROR(IF(H50>H54,1-H56,0),0) -> 0.80446186 | I57: =IFERROR(IF(I50>I54,1-I56,0),0) -> 0.85043481 | J57: =IFERROR(IF(J50>J54,1-J56,0),0) -> 0.78377025 | ... L57: =IFERROR(IF(L50>L54,1-L56,0),0) -> 0.62186985
A59: # | B59: Balance Sheet
B60: Equity & Liabilities
B61: Equity Share Capital | C61: =IFERROR('Data Sheet'!B57,0) -> 274.43 | D61: =IFERROR('Data Sheet'!C57,0) -> 274.51 | E61: =IFERROR('Data Sheet'!D57,0) -> 274.61 | F61: =IFERROR('Data Sheet'!E57,0) -> 274.64 | G61: =IFERROR('Data Sheet'!F57,0) -> 288.63 | H61: =IFERROR('Data Sheet'!G57,0) -> 288.65 | I61: =IFERROR('Data Sheet'!H57,0) -> 288.67 | J61: =IFERROR('Data Sheet'!I57,0) -> 288.69 | ... L61: =IFERROR('Data Sheet'!K57,0) -> 294.68
B62: Reserves | C62: =IFERROR('Data Sheet'!B58,0) -> 21671.2 | D62: =IFERROR('Data Sheet'!C58,0) -> 24117.38 | E62: =IFERROR('Data Sheet'!D58,0) -> 26106.55 | F62: =IFERROR('Data Sheet'!E58,0) -> 33476.01 | G62: =IFERROR('Data Sheet'!F58,0) -> 38755.13 | H62: =IFERROR('Data Sheet'!G58,0) -> 43886.03 | I62: =IFERROR('Data Sheet'!H58,0) -> 50146.6 | J62: =IFERROR('Data Sheet'!I58,0) -> 54035.85 | ... L62: =IFERROR('Data Sheet'!K58,0) -> 70412.09
B63: Borrowings | C63: =IFERROR('Data Sheet'!B59,0) -> 10615.99 | D63: =IFERROR('Data Sheet'!C59,0) -> 8474.49 | E63: =IFERROR('Data Sheet'!D59,0) -> 19480.22 | F63: =IFERROR('Data Sheet'!E59,0) -> 25337 | G63: =IFERROR('Data Sheet'!F59,0) -> 23018.96 | H63: =IFERROR('Data Sheet'!G59,0) -> 21719.39 | I63: =IFERROR('Data Sheet'!H59,0) -> 11298.8 | J63: =IFERROR('Data Sheet'!I59,0) -> 11057.74 | ... L63: =IFERROR('Data Sheet'!K59,0) -> 24102.18
B64: Other Liabilities | C64: =IFERROR('Data Sheet'!B60,0) -> 8631.49 | D64: =IFERROR('Data Sheet'!C60,0) -> 9342.73 | E64: =IFERROR('Data Sheet'!D60,0) -> 11279.71 | F64: =IFERROR('Data Sheet'!E60,0) -> 17437.72 | G64: =IFERROR('Data Sheet'!F60,0) -> 17151.09 | H64: =IFERROR('Data Sheet'!G60,0) -> 20282.28 | I64: =IFERROR('Data Sheet'!H60,0) -> 22077.37 | J64: =IFERROR('Data Sheet'!I60,0) -> 25998.12 | ... L64: =IFERROR('Data Sheet'!K60,0) -> 38823.11
B65: Total Equity & Liabilities | C65: =IFERROR(SUM(C61:C64),0) -> 41193.11 | D65: =IFERROR(SUM(D61:D64),0) -> 42209.11 | E65: =IFERROR(SUM(E61:E64),0) -> 57141.09 | F65: =IFERROR(SUM(F61:F64),0) -> 76525.37 | G65: =IFERROR(SUM(G61:G64),0) -> 79213.81 | H65: =IFERROR(SUM(H61:H64),0) -> 86176.35 | I65: =IFERROR(SUM(I61:I64),0) -> 83811.44 | J65: =IFERROR(SUM(J61:J64),0) -> 91380.4 | ... L65: =IFERROR(SUM(L61:L64),0) -> 133632.06
B67: Non Current Assets
B68: Net Block | C68: =IFERROR('Data Sheet'!B62,0) -> 25309.42 | D68: =IFERROR('Data Sheet'!C62,0) -> 25903.75 | E68: =IFERROR('Data Sheet'!D62,0) -> 39715.3 | F68: =IFERROR('Data Sheet'!E62,0) -> 56644.62 | G68: =IFERROR('Data Sheet'!F62,0) -> 57150.96 | H68: =IFERROR('Data Sheet'!G62,0) -> 55411.61 | I68: =IFERROR('Data Sheet'!H62,0) -> 55487.57 | J68: =IFERROR('Data Sheet'!I62,0) -> 59579 | ... L68: =IFERROR('Data Sheet'!K62,0) -> 94564.22
B69: Capital Work in Progress | C69: =IFERROR('Data Sheet'!B63,0) -> 1469.09 | D69: =IFERROR('Data Sheet'!C63,0) -> 921.48 | E69: =IFERROR('Data Sheet'!D63,0) -> 1511.21 | F69: =IFERROR('Data Sheet'!E63,0) -> 1153.32 | G69: =IFERROR('Data Sheet'!F63,0) -> 919.59 | H69: =IFERROR('Data Sheet'!G63,0) -> 1686.68 | I69: =IFERROR('Data Sheet'!H63,0) -> 4784.67 | J69: =IFERROR('Data Sheet'!I63,0) -> 4040.39 | ... L69: =IFERROR('Data Sheet'!K63,0) -> 6234.19
B70: Investments | C70: =IFERROR('Data Sheet'!B64,0) -> 5095.18 | D70: =IFERROR('Data Sheet'!C64,0) -> 6690.51 | E70: =IFERROR('Data Sheet'!D64,0) -> 5446.9 | F70: =IFERROR('Data Sheet'!E64,0) -> 2921.33 | G70: =IFERROR('Data Sheet'!F64,0) -> 5928.69 | H70: =IFERROR('Data Sheet'!G64,0) -> 12178.11 | I70: =IFERROR('Data Sheet'!H64,0) -> 6335.77 | J70: =IFERROR('Data Sheet'!I64,0) -> 7296.95 | ... L70: =IFERROR('Data Sheet'!K64,0) -> 5156.47
B71: Other Assets | C71: =IFERROR('Data Sheet'!B65-SUM('Data Sheet'!B67:B69),0) -> 2669.67 | D71: =IFERROR('Data Sheet'!C65-SUM('Data Sheet'!C67:C69),0) -> 2286.86 | E71: =IFERROR('Data Sheet'!D65-SUM('Data Sheet'!D67:D69),0) -> 4760.39 | F71: =IFERROR('Data Sheet'!E65-SUM('Data Sheet'!E67:E69),0) -> 8180.43 | G71: =IFERROR('Data Sheet'!F65-SUM('Data Sheet'!F67:F69),0) -> 8108.09 | H71: =IFERROR('Data Sheet'!G65-SUM('Data Sheet'!G67:G69),0) -> 8302.7 | I71: =IFERROR('Data Sheet'!H65-SUM('Data Sheet'!H67:H69),0) -> 8177.06 | J71: =IFERROR('Data Sheet'!I65-SUM('Data Sheet'!I67:I69),0) -> 8835.62 | ... L71: =IFERROR('Data Sheet'!K65-SUM('Data Sheet'!K67:K69),0) -> 10550.63
B72: Total Non Current Assets | C72: =IFERROR(SUM(C68:C71),0) -> 34543.36 | D72: =IFERROR(SUM(D68:D71),0) -> 35802.6 | E72: =IFERROR(SUM(E68:E71),0) -> 51433.8 | F72: =IFERROR(SUM(F68:F71),0) -> 68899.7 | G72: =IFERROR(SUM(G68:G71),0) -> 72107.33 | H72: =IFERROR(SUM(H68:H71),0) -> 77579.1 | I72: =IFERROR(SUM(I68:I71),0) -> 74785.07 | J72: =IFERROR(SUM(J68:J71),0) -> 79751.96 | ... L72: =IFERROR(SUM(L68:L71),0) -> 116505.51
B74: Current Assets
B75: Receivables | C75: =IFERROR('Data Sheet'!B67,0) -> 1928.21 | D75: =IFERROR('Data Sheet'!C67,0) -> 1757.09 | E75: =IFERROR('Data Sheet'!D67,0) -> 2220.63 | F75: =IFERROR('Data Sheet'!E67,0) -> 2787.03 | G75: =IFERROR('Data Sheet'!F67,0) -> 2383.22 | H75: =IFERROR('Data Sheet'!G67,0) -> 2571.73 | I75: =IFERROR('Data Sheet'!H67,0) -> 3071.61 | J75: =IFERROR('Data Sheet'!I67,0) -> 3867.02 | ... L75: =IFERROR('Data Sheet'!K67,0) -> 5890.25
B76: Inventory | C76: =IFERROR('Data Sheet'!B68,0) -> 2454.58 | D76: =IFERROR('Data Sheet'!C68,0) -> 2400.64 | E76: =IFERROR('Data Sheet'!D68,0) -> 3267.59 | F76: =IFERROR('Data Sheet'!E68,0) -> 4098.96 | G76: =IFERROR('Data Sheet'!F68,0) -> 4183.35 | H76: =IFERROR('Data Sheet'!G68,0) -> 4017.97 | I76: =IFERROR('Data Sheet'!H68,0) -> 5595.58 | J76: =IFERROR('Data Sheet'!I68,0) -> 6611.83 | ... L76: =IFERROR('Data Sheet'!K68,0) -> 9562.98
B77: Cash & Bank | C77: =IFERROR('Data Sheet'!B69,0) -> 2266.96 | D77: =IFERROR('Data Sheet'!C69,0) -> 2248.78 | E77: =IFERROR('Data Sheet'!D69,0) -> 219.07 | F77: =IFERROR('Data Sheet'!E69,0) -> 739.68 | G77: =IFERROR('Data Sheet'!F69,0) -> 539.91 | H77: =IFERROR('Data Sheet'!G69,0) -> 2007.55 | I77: =IFERROR('Data Sheet'!H69,0) -> 359.18 | J77: =IFERROR('Data Sheet'!I69,0) -> 1149.59 | ... L77: =IFERROR('Data Sheet'!K69,0) -> 1673.32
B78: Total Current Assets | C78: =IFERROR(SUM(C75:C77),0) -> 6649.75 | D78: =IFERROR(SUM(D75:D77),0) -> 6406.51 | E78: =IFERROR(SUM(E75:E77),0) -> 5707.29 | F78: =IFERROR(SUM(F75:F77),0) -> 7625.67 | G78: =IFERROR(SUM(G75:G77),0) -> 7106.48 | H78: =IFERROR(SUM(H75:H77),0) -> 8597.25 | I78: =IFERROR(SUM(I75:I77),0) -> 9026.37 | J78: =IFERROR(SUM(J75:J77),0) -> 11628.44 | ... L78: =IFERROR(SUM(L75:L77),0) -> 17126.55
B80: Total Assets | C80: =IFERROR(C72+C78,0) -> 41193.11 | D80: =IFERROR(D72+D78,0) -> 42209.11 | E80: =IFERROR(E72+E78,0) -> 57141.09 | F80: =IFERROR(F72+F78,0) -> 76525.37 | G80: =IFERROR(G72+G78,0) -> 79213.81 | H80: =IFERROR(H72+H78,0) -> 86176.35 | I80: =IFERROR(I72+I78,0) -> 83811.44 | J80: =IFERROR(J72+J78,0) -> 91380.4 | ... L80: =IFERROR(L72+L78,0) -> 133632.06
B82: Check | C82: =C65=C80 -> TRUE | D82: =D65=D80 -> TRUE | E82: =E65=E80 -> TRUE | F82: =F65=F80 -> TRUE | G82: =G65=G80 -> TRUE | H82: =H65=H80 -> TRUE | I82: =I65=I80 -> TRUE | J82: =J65=J80 -> TRUE | ... L82: =L65=L80 -> TRUE
A84: # | B84: Cash Flow Statement
B86: Cash from Operating Activity | C86: =C87+C93+C94 -> 4525 | D86: =D87+D93+D94 -> 5005 | E86: =E87+E93+E94 -> 3888 | F86: =F87+F93+F94 -> 5956 | G86: =G87+G93+G94 -> 8973 | H86: =H87+H93+H94 -> 12500 | I86: =I87+I93+I94 -> 9283 | J86: =J87+J93+J94 -> 9069 | ... L86: =L87+L93+L94 -> 10673
B87: Profit from operations | C87: ='Raw FS'!C57 -> 4948 | D87: ='Raw FS'!D57 -> 5220 | E87: ='Raw FS'!E57 -> 5986 | F87: ='Raw FS'!F57 -> 7362 | G87: ='Raw FS'!G57 -> 9348 | H87: ='Raw FS'!H57 -> 11465 | I87: ='Raw FS'!I57 -> 11311 | J87: ='Raw FS'!J57 -> 10530 | ... L87: ='Raw FS'!L57 -> 12645
B88: Receivables | C88: ='Raw FS'!C58 -> -287 | D88: ='Raw FS'!D58 -> 156 | E88: ='Raw FS'!E58 -> -454 | F88: ='Raw FS'!F58 -> -279 | G88: ='Raw FS'!G58 -> 473 | H88: ='Raw FS'!H58 -> -201 | I88: ='Raw FS'!I58 -> -495 | J88: ='Raw FS'!J58 -> -752 | ... L88: ='Raw FS'!L58 -> -608
B89: Inventory | C89: ='Raw FS'!C59 -> 374 | D89: ='Raw FS'!D59 -> 54 | E89: ='Raw FS'!E59 -> -623 | F89: ='Raw FS'!F59 -> -15 | G89: ='Raw FS'!G59 -> -64 | H89: ='Raw FS'!H59 -> 165 | I89: ='Raw FS'!I59 -> -1579 | J89: ='Raw FS'!J59 -> -992 | ... L89: ='Raw FS'!L59 -> -317
B90: Payables | C90: ='Raw FS'!C60 -> 310 | D90: ='Raw FS'!D60 -> 482 | E90: ='Raw FS'!E60 -> 346 | F90: ='Raw FS'!F60 -> 766 | G90: ='Raw FS'!G60 -> 279 | H90: ='Raw FS'!H60 -> 2868 | I90: ='Raw FS'!I60 -> 2077 | J90: ='Raw FS'!J60 -> 1869 | ... L90: ='Raw FS'!L60 -> -476
B91: Loans Advances | C91: ='Raw FS'!C61 -> 0 | D91: ='Raw FS'!D61 -> 0 | E91: ='Raw FS'!E61 -> 0 | F91: ='Raw FS'!F61 -> 0 | G91: ='Raw FS'!G61 -> 0 | H91: ='Raw FS'!H61 -> 0 | I91: ='Raw FS'!I61 -> 0 | J91: ='Raw FS'!J61 -> 0 | ... L91: ='Raw FS'!L61 -> 0
B92: Other WC items | C92: ='Raw FS'!C62 -> 32 | D92: ='Raw FS'!D62 -> -162 | E92: ='Raw FS'!E62 -> -525 | F92: ='Raw FS'!F62 -> -1167 | G92: ='Raw FS'!G62 -> -172 | H92: ='Raw FS'!H62 -> -505 | I92: ='Raw FS'!I62 -> -476 | J92: ='Raw FS'!J62 -> -461 | ... L92: ='Raw FS'!L62 -> 729
B93: Working capital changes | C93: ='Raw FS'!C63 -> 429 | D93: ='Raw FS'!D63 -> 529 | E93: ='Raw FS'!E63 -> -1255 | F93: ='Raw FS'!F63 -> -696 | G93: ='Raw FS'!G63 -> 516 | H93: ='Raw FS'!H63 -> 2326 | I93: ='Raw FS'!I63 -> -473 | J93: ='Raw FS'!J63 -> -337 | ... L93: ='Raw FS'!L63 -> -671
B94: Direct taxes | C94: ='Raw FS'!C64 -> -852 | D94: ='Raw FS'!D64 -> -744 | E94: ='Raw FS'!E64 -> -843 | F94: ='Raw FS'!F64 -> -710 | G94: ='Raw FS'!G64 -> -891 | H94: ='Raw FS'!H64 -> -1291 | I94: ='Raw FS'!I64 -> -1555 | J94: ='Raw FS'!J64 -> -1124 | ... L94: ='Raw FS'!L64 -> -1301
B95: Other operating items | C95: ='Raw FS'!C65 -> 0 | D95: ='Raw FS'!D65 -> 0 | E95: ='Raw FS'!E65 -> 0 | F95: ='Raw FS'!F65 -> 0 | G95: ='Raw FS'!G65 -> 0 | H95: ='Raw FS'!H65 -> 0 | I95: ='Raw FS'!I65 -> 0 | J95: ='Raw FS'!J65 -> 0 | ... L95: ='Raw FS'!L65 -> 0
B97: Cash from Investing Activity | C97: =SUM(C98:C108) -> -3675 | D97: =SUM(D98:D108) -> -2501 | E97: =SUM(E98:E108) -> 1866 | F97: =SUM(F98:F108) -> 1164 | G97: =SUM(G98:G108) -> -4193 | H97: =SUM(H98:H108) -> -8856 | I97: =SUM(I98:I108) -> 2322 | J97: =SUM(J98:J108) -> -7187 | ... L97: =SUM(L98:L108) -> -15835
B98: Fixed assets purchased | C98: ='Raw FS'!C67 -> -2150 | D98: ='Raw FS'!D67 -> -1402 | E98: ='Raw FS'!E67 -> -2103 | F98: ='Raw FS'!F67 -> -1808 | G98: ='Raw FS'!G67 -> -1766 | H98: ='Raw FS'!H67 -> -1925 | I98: ='Raw FS'!I67 -> -5613 | J98: ='Raw FS'!J67 -> -6200 | ... L98: ='Raw FS'!L67 -> -9129
B99: Fixed assets sold | C99: ='Raw FS'!C68 -> 18 | D99: ='Raw FS'!D68 -> 35 | E99: ='Raw FS'!E68 -> 220 | F99: ='Raw FS'!F68 -> 160 | G99: ='Raw FS'!G68 -> 79 | H99: ='Raw FS'!H68 -> 86 | I99: ='Raw FS'!I68 -> 73 | J99: ='Raw FS'!J68 -> 95 | ... L99: ='Raw FS'!L68 -> 179
B100: Investments purchased | C100: ='Raw FS'!C69 -> -2698 | D100: ='Raw FS'!D69 -> -3377 | E100: ='Raw FS'!E69 -> -3960 | F100: ='Raw FS'!F69 -> -1700 | G100: ='Raw FS'!G69 -> -6086 | H100: ='Raw FS'!H69 -> -12689 | I100: ='Raw FS'!I69 -> -7795 | J100: ='Raw FS'!J69 -> -7260 | ... L100: ='Raw FS'!L69 -> -15885
B101: Investments sold | C101: ='Raw FS'!C70 -> 2948 | D101: ='Raw FS'!D70 -> 2228 | E101: ='Raw FS'!E70 -> 5588 | F101: ='Raw FS'!F70 -> 4478 | G101: ='Raw FS'!G70 -> 3443 | H101: ='Raw FS'!H70 -> 7101 | I101: ='Raw FS'!I70 -> 13965 | J101: ='Raw FS'!J70 -> 7156 | ... L101: ='Raw FS'!L70 -> 19115
B102: Interest received | C102: ='Raw FS'!C71 -> 59 | D102: ='Raw FS'!D71 -> 47 | E102: ='Raw FS'!E71 -> 67 | F102: ='Raw FS'!F71 -> 78 | G102: ='Raw FS'!G71 -> 89 | H102: ='Raw FS'!H71 -> 77 | I102: ='Raw FS'!I71 -> 174 | J102: ='Raw FS'!J71 -> 283 | ... L102: ='Raw FS'!L71 -> 342
B103: Dividends received | C103: ='Raw FS'!C72 -> 0 | D103: ='Raw FS'!D72 -> 0 | E103: ='Raw FS'!E72 -> 0 | F103: ='Raw FS'!F72 -> 22 | G103: ='Raw FS'!G72 -> 32 | H103: ='Raw FS'!H72 -> 0 | I103: ='Raw FS'!I72 -> 0 | J103: ='Raw FS'!J72 -> 0 | ... L103: ='Raw FS'!L72 -> 1
B104: Invest in subsidiaries | C104: ='Raw FS'!C73 -> -13 | D104: ='Raw FS'!D73 -> 0 | E104: ='Raw FS'!E73 -> 0 | F104: ='Raw FS'!F73 -> 0 | G104: ='Raw FS'!G73 -> 0 | H104: ='Raw FS'!H73 -> 0 | I104: ='Raw FS'!I73 -> 0 | J104: ='Raw FS'!J73 -> 0 | ... L104: ='Raw FS'!L73 -> 0
B105: Investment in group cos | C105: ='Raw FS'!C74 -> 0 | D105: ='Raw FS'!D74 -> 0 | E105: ='Raw FS'!E74 -> -1 | F105: ='Raw FS'!F74 -> -8 | G105: ='Raw FS'!G74 -> -6 | H105: ='Raw FS'!H74 -> -3 | I105: ='Raw FS'!I74 -> 0 | J105: ='Raw FS'!J74 -> 0 | ... L105: ='Raw FS'!L74 -> 0
B106: Redemp n Canc of Shares | C106: ='Raw FS'!C75 -> 0 | D106: ='Raw FS'!D75 -> 0 | E106: ='Raw FS'!E75 -> 0 | F106: ='Raw FS'!F75 -> 0 | G106: ='Raw FS'!G75 -> 0 | H106: ='Raw FS'!H75 -> 0 | I106: ='Raw FS'!I75 -> 0 | J106: ='Raw FS'!J75 -> 3 | ... L106: ='Raw FS'!L75 -> 36
B107: Acquisition of companies | C107: ='Raw FS'!C76 -> 0 | D107: ='Raw FS'!D76 -> 0 | E107: ='Raw FS'!E76 -> 0 | F107: ='Raw FS'!F76 -> 0 | G107: ='Raw FS'!G76 -> 0 | H107: ='Raw FS'!H76 -> 0 | I107: ='Raw FS'!I76 -> 0 | J107: ='Raw FS'!J76 -> -847 | ... L107: ='Raw FS'!L76 -> -10262
B108: Other investing items | C108: ='Raw FS'!C77 -> -1839 | D108: ='Raw FS'!D77 -> -32 | E108: ='Raw FS'!E77 -> 2055 | F108: ='Raw FS'!F77 -> -58 | G108: ='Raw FS'!G77 -> 22 | H108: ='Raw FS'!H77 -> -1503 | I108: ='Raw FS'!I77 -> 1518 | J108: ='Raw FS'!J77 -> -417 | ... L108: ='Raw FS'!L77 -> -232
B110: Cash from Financing Activity | C110: =SUM(C111:C117) -> -843 | D110: =SUM(D111:D117) -> -2535 | E110: =SUM(E111:E117) -> -5735 | F110: =SUM(F111:F117) -> -6757 | G110: =SUM(G111:G117) -> -5076 | H110: =SUM(H111:H117) -> -4356 | I110: =SUM(I111:I117) -> -12497 | J110: =SUM(J111:J117) -> -1631 | ... L110: =SUM(L111:L117) -> 5076
B111: Proceeds from shares | C111: ='Raw FS'!C79 -> 3 | D111: ='Raw FS'!D79 -> 7 | E111: ='Raw FS'!E79 -> 16 | F111: ='Raw FS'!F79 -> 5 | G111: ='Raw FS'!G79 -> 3 | H111: ='Raw FS'!H79 -> 14 | I111: ='Raw FS'!I79 -> 13 | J111: ='Raw FS'!J79 -> 13 | ... L111: ='Raw FS'!L79 -> 33
B112: Proceeds from borrowings | C112: ='Raw FS'!C80 -> 2821 | D112: ='Raw FS'!D80 -> 3656 | E112: ='Raw FS'!E80 -> 15775 | F112: ='Raw FS'!F80 -> 9772 | G112: ='Raw FS'!G80 -> 1510 | H112: ='Raw FS'!H80 -> 4103 | I112: ='Raw FS'!I80 -> 175 | J112: ='Raw FS'!J80 -> 1032 | ... L112: ='Raw FS'!L80 -> 9410
B113: Repayment of borrowings | C113: ='Raw FS'!C81 -> -2775 | D113: ='Raw FS'!D81 -> -5272 | E113: ='Raw FS'!E81 -> -19982 | F113: ='Raw FS'!F81 -> -14420 | G113: ='Raw FS'!G81 -> -4154 | H113: ='Raw FS'!H81 -> -6499 | I113: ='Raw FS'!I81 -> -10346 | J113: ='Raw FS'!J81 -> -579 | ... L113: ='Raw FS'!L81 -> -550
B114: Interest paid fin | C114: ='Raw FS'!C82 -> -596 | D114: ='Raw FS'!D82 -> -614 | E114: ='Raw FS'!E82 -> -1210 | F114: ='Raw FS'!F82 -> -1685 | G114: ='Raw FS'!G82 -> -1950 | H114: ='Raw FS'!H82 -> -1481 | I114: ='Raw FS'!I82 -> -1026 | J114: ='Raw FS'!J82 -> -765 | ... L114: ='Raw FS'!L82 -> -1540
B115: Dividends paid | C115: ='Raw FS'!C83 -> -297 | D115: ='Raw FS'!D83 -> -312 | E115: ='Raw FS'!E83 -> -334 | F115: ='Raw FS'!F83 -> -346 | G115: ='Raw FS'!G83 -> -380 | H115: ='Raw FS'!H83 -> -375 | I115: ='Raw FS'!I83 -> -1065 | J115: ='Raw FS'!J83 -> -1091 | ... L115: ='Raw FS'!L83 -> -2012
B116: Financial liabilities | C116: ='Raw FS'!C84 -> 0 | D116: ='Raw FS'!D84 -> 0 | E116: ='Raw FS'!E84 -> 0 | F116: ='Raw FS'!F84 -> 0 | G116: ='Raw FS'!G84 -> -101 | H116: ='Raw FS'!H84 -> -118 | I116: ='Raw FS'!I84 -> -157 | J116: ='Raw FS'!J84 -> -126 | ... L116: ='Raw FS'!L84 -> -165
B117: Other financing items | C117: ='Raw FS'!C85 -> 1 | D117: ='Raw FS'!D85 -> 0 | E117: ='Raw FS'!E85 -> 0 | F117: ='Raw FS'!F85 -> -83 | G117: ='Raw FS'!G85 -> -4 | H117: ='Raw FS'!H85 -> 0 | I117: ='Raw FS'!I85 -> -91 | J117: ='Raw FS'!J85 -> -115 | ... L117: ='Raw FS'!L85 -> -100
B119: Net Cash Flow | C119: =C110+C97+C86 -> 7 | D119: =D110+D97+D86 -> -31 | E119: =E110+E97+E86 -> 19 | F119: =F110+F97+F86 -> 363 | G119: =G110+G97+G86 -> -296 | H119: =H110+H97+H86 -> -712 | I119: =I110+I97+I86 -> -892 | J119: =J110+J97+J86 -> 251 | ... L119: =L110+L97+L86 -> -86

Sheet Ratios
B9: ="Ratio Analysis"&" - "&'Data Sheet'!B1 -> Ratio Analysis - ULTRATECH CEMENT LTD
B10: Years | C10: ='Data Sheet'!B16 -> 42460 | D10: ='Data Sheet'!C16 -> 42825 | E10: ='Data Sheet'!D16 -> 43190 | F10: ='Data Sheet'!E16 -> 43555 | G10: ='Data Sheet'!F16 -> 43921 | H10: ='Data Sheet'!G16 -> 44286 | I10: ='Data Sheet'!H16 -> 44651 | J10: ='Data Sheet'!I16 -> 45016 | ... L10: ='Data Sheet'!K16 -> 45747 | M10: Trend
B12: Gross Profit Margin | C12: =IFERROR(Historical_FS!C22,0) -> 0.52557523 | D12: =IFERROR(Historical_FS!D22,0) -> 0.54066886 | E12: =IFERROR(Historical_FS!E22,0) -> 0.49958326 | F12: =IFERROR(Historical_FS!F22,0) -> 0.48435951 | G12: =IFERROR(Historical_FS!G22,0) -> 0.52981707 | H12: =IFERROR(Historical_FS!H22,0) -> 0.54770669 | I12: =IFERROR(Historical_FS!I22,0) -> 0.50821168 | J12: =IFERROR(Historical_FS!J22,0) -> 0.44979711 | ... L12: =IFERROR(Historical_FS!L22,0) -> 0.46257745
B13: EBITDA Margin | C13: =IFERROR(Historical_FS!C28,0) -> 0.21328386 | D13: =IFERROR(Historical_FS!D28,0) -> 0.23095858 | E13: =IFERROR(Historical_FS!E28,0) -> 0.20617445 | F13: =IFERROR(Historical_FS!F28,0) -> 0.18563966 | G13: =IFERROR(Historical_FS!G28,0) -> 0.23325608 | H13: =IFERROR(Historical_FS!H28,0) -> 0.2724698 | I13: =IFERROR(Historical_FS!I28,0) -> 0.23163595 | J13: =IFERROR(Historical_FS!J28,0) -> 0.17594819 | ... L13: =IFERROR(Historical_FS!L28,0) -> 0.17370282
B14: EBIT Margin | C14: =IFERROR(Historical_FS!C34,) -> 0.15853266 | D14: =IFERROR(Historical_FS!D34,) -> 0.17781914 | E14: =IFERROR(Historical_FS!E34,) -> 0.14652267 | F14: =IFERROR(Historical_FS!F34,) -> 0.12653218 | G14: =IFERROR(Historical_FS!G34,) -> 0.16908764 | H14: =IFERROR(Historical_FS!H34,) -> 0.21209682 | I14: =IFERROR(Historical_FS!I34,) -> 0.18002359 | J14: =IFERROR(Historical_FS!J34,) -> 0.13028103 | ... L14: =IFERROR(Historical_FS!L34,) -> 0.12084332
B15: EBT Margin | C15: =IFERROR(Historical_FS!C40,0) -> 0.13601866 | D15: =IFERROR(Historical_FS!D40,0) -> 0.15259346 | E15: =IFERROR(Historical_FS!E40,0) -> 0.10657253 | F15: =IFERROR(Historical_FS!F40,0) -> 0.083653182 | G15: =IFERROR(Historical_FS!G40,0) -> 0.12214785 | H15: =IFERROR(Historical_FS!H40,0) -> 0.17887998 | I15: =IFERROR(Historical_FS!I40,0) -> 0.16206292 | J15: =IFERROR(Historical_FS!J40,0) -> 0.11727154 | ... L15: =IFERROR(Historical_FS!L40,0) -> 0.099112858
B16: Net Profit Margin | C16: =IFERROR(Historical_FS!C46,) -> 0.098580541 | D16: =IFERROR(Historical_FS!D46,) -> 0.10693661 | E16: =IFERROR(Historical_FS!E46,) -> 0.071806297 | F16: =IFERROR(Historical_FS!F46,) -> 0.05789313 | G16: =IFERROR(Historical_FS!G46,) -> 0.13553841 | H16: =IFERROR(Historical_FS!H46,) -> 0.12211855 | I16: =IFERROR(Historical_FS!I46,) -> 0.1394377 | J16: =IFERROR(Historical_FS!J46,) -> 0.080224567 | ... L16: =IFERROR(Historical_FS!L46,) -> 0.079515893
B18: Current Ratio | C18: =IFERROR(Historical_FS!C78/Historical_FS!C64,0) -> 0.7704058 | D18: =IFERROR(Historical_FS!D78/Historical_FS!D64,0) -> 0.68572141 | E18: =IFERROR(Historical_FS!E78/Historical_FS!E64,0) -> 0.50597843 | F18: =IFERROR(Historical_FS!F78/Historical_FS!F64,0) -> 0.43730889 | G18: =IFERROR(Historical_FS!G78/Historical_FS!G64,0) -> 0.41434568 | H18: =IFERROR(Historical_FS!H78/Historical_FS!H64,0) -> 0.42387986 | I18: =IFERROR(Historical_FS!I78/Historical_FS!I64,0) -> 0.40885169 | J18: =IFERROR(Historical_FS!J78/Historical_FS!J64,0) -> 0.44728003 | ... L18: =IFERROR(Historical_FS!L78/Historical_FS!L64,0) -> 0.44114317
B19: Quick Ratio | C19: =IFERROR((Historical_FS!C78-Historical_FS!C76)/Historical_FS!C64,0) -> 0.4860308 | D19: =IFERROR((Historical_FS!D78-Historical_FS!D76)/Historical_FS!D64,0) -> 0.42876868 | E19: =IFERROR((Historical_FS!E78-Historical_FS!E76)/Historical_FS!E64,0) -> 0.21629102 | F19: =IFERROR((Historical_FS!F78-Historical_FS!F76)/Historical_FS!F64,0) -> 0.20224605 | G19: =IFERROR((Historical_FS!G78-Historical_FS!G76)/Historical_FS!G64,0) -> 0.17043407 | H19: =IFERROR((Historical_FS!H78-Historical_FS!H76)/Historical_FS!H64,0) -> 0.22577738 | I19: =IFERROR((Historical_FS!I78-Historical_FS!I76)/Historical_FS!I64,0) -> 0.15539849 | J19: =IFERROR((Historical_FS!J78-Historical_FS!J76)/Historical_FS!J64,0) -> 0.19296049 | ... L19: =IFERROR((Historical_FS!L78-Historical_FS!L76)/Historical_FS!L64,0) -> 0.19482133
B20: Cash Ratio | C20: =IFERROR(Historical_FS!C77/Historical_FS!C64,0) -> 0.26263832 | D20: =IFERROR(Historical_FS!D77/Historical_FS!D64,0) -> 0.24069838 | E20: =IFERROR(Historical_FS!E77/Historical_FS!E64,0) -> 0.019421599 | F20: =IFERROR(Historical_FS!F77/Historical_FS!F64,0) -> 0.04241839 | G20: =IFERROR(Historical_FS!G77/Historical_FS!G64,0) -> 0.031479632 | H20: =IFERROR(Historical_FS!H77/Historical_FS!H64,0) -> 0.098980489 | I20: =IFERROR(Historical_FS!I77/Historical_FS!I64,0) -> 0.016269148 | J20: =IFERROR(Historical_FS!J77/Historical_FS!J64,0) -> 0.044218197 | ... L20: =IFERROR(Historical_FS!L77/Historical_FS!L64,0) -> 0.043101132
B22: Debt to Equity Ratio | C22: =IFERROR(SUM(Historical_FS!C63:C64)/SUM(Historical_FS!C61:C62),0) -> 0.87705297 | D22: =IFERROR(SUM(Historical_FS!D63:D64)/SUM(Historical_FS!D61:D62),0) -> 0.73045672 | E22: =IFERROR(SUM(Historical_FS!E63:E64)/SUM(Historical_FS!E61:E62),0) -> 1.165981 | F22: =IFERROR(SUM(Historical_FS!F63:F64)/SUM(Historical_FS!F61:F62),0) -> 1.2673747 | G22: =IFERROR(SUM(Historical_FS!G63:G64)/SUM(Historical_FS!G61:G62),0) -> 1.0288469 | H22: =IFERROR(SUM(Historical_FS!H63:H64)/SUM(Historical_FS!H61:H62),0) -> 0.9508087 | I22: =IFERROR(SUM(Historical_FS!I63:I64)/SUM(Historical_FS!I61:I62),0) -> 0.66176249 | J22: =IFERROR(SUM(Historical_FS!J63:J64)/SUM(Historical_FS!J61:J62),0) -> 0.68212009 | ... L22: =IFERROR(SUM(Historical_FS!L63:L64)/SUM(Historical_FS!L61:L62),0) -> 0.88994717
B23: Debt to Assets Ratio | C23: =IFERROR(SUM(Historical_FS!C63:C64)/Historical_FS!C80,0) -> 0.46724998 | D23: =IFERROR(SUM(Historical_FS!D63:D64)/Historical_FS!D80,0) -> 0.42211788 | E23: =IFERROR(SUM(Historical_FS!E63:E64)/Historical_FS!E80,0) -> 0.53831542 | F23: =IFERROR(SUM(Historical_FS!F63:F64)/Historical_FS!F80,0) -> 0.5589613 | G23: =IFERROR(SUM(Historical_FS!G63:G64)/Historical_FS!G80,0) -> 0.50710918 | H23: =IFERROR(SUM(Historical_FS!H63:H64)/Historical_FS!H80,0) -> 0.48739207 | I23: =IFERROR(SUM(Historical_FS!I63:I64)/Historical_FS!I80,0) -> 0.39822929 | J23: =IFERROR(SUM(Historical_FS!J63:J64)/Historical_FS!J80,0) -> 0.40551212 | ... L23: =IFERROR(SUM(Historical_FS!L63:L64)/Historical_FS!L80,0) -> 0.47088468
B24: Interest Coverage Ratio | C24: =IFERROR(Historical_FS!C33/Historical_FS!C36,0) -> 7.0415151 | D24: =IFERROR(Historical_FS!D33/Historical_FS!D36,0) -> 7.0491329 | E24: =IFERROR(Historical_FS!E33/Historical_FS!E36,0) -> 3.667639 | F24: =IFERROR(Historical_FS!F33/Historical_FS!F36,0) -> 2.9509129 | G24: =IFERROR(Historical_FS!G33/Historical_FS!G36,0) -> 3.6022243 | H24: =IFERROR(Historical_FS!H33/Historical_FS!H36,0) -> 6.3852186 | I24: =IFERROR(Historical_FS!I33/Historical_FS!I36,0) -> 10.023213 | J24: =IFERROR(Historical_FS!J33/Historical_FS!J36,0) -> 10.014306 | ... L24: =IFERROR(Historical_FS!L33/Historical_FS!L36,0) -> 5.5610103
B26: Return on Capital Employed | C26: =IFERROR(Historical_FS!C33/SUM(Historical_FS!C61:C63),0) -> 0.1224635 | D26: =IFERROR(Historical_FS!D33/SUM(Historical_FS!D61:D63),0) -> 0.13728771 | E26: =IFERROR(Historical_FS!E33/SUM(Historical_FS!E61:E63),0) -> 0.09897369 | F26: =IFERROR(Historical_FS!F33/SUM(Historical_FS!F61:F63),0) -> 0.088788605 | G26: =IFERROR(Historical_FS!G33/SUM(Historical_FS!G61:G63),0) -> 0.1155987 | H26: =IFERROR(Historical_FS!H33/SUM(Historical_FS!H61:H63),0) -> 0.14396136 | I26: =IFERROR(Historical_FS!I33/SUM(Historical_FS!I61:I63),0) -> 0.15338418 | J26: =IFERROR(Historical_FS!J33/SUM(Historical_FS!J61:J63),0) -> 0.12601228 | ... L26: =IFERROR(Historical_FS!L33/SUM(Historical_FS!L61:L63),0) -> 0.096812274
B27: Retained Earnings % | C27: =IFERROR(Historical_FS!C57,0) -> 0.89485889 | D27: =IFERROR(Historical_FS!D57,0) -> 0.89883583 | E27: =IFERROR(Historical_FS!E57,0) -> 0.87037753 | F27: =IFERROR(Historical_FS!F57,0) -> 0.86842083 | G27: =IFERROR(Historical_FS!G57,0) -> 0.93475433 | H27: =IFERROR(Historical_FS!H57,0) -> 0.80446186 | I27: =IFERROR(Historical_FS!I57,0) -> 0.85043481 | J27: =IFERROR(Historical_FS!J57,0) -> 0.78377025 | ... L27: =IFERROR(Historical_FS!L57,0) -> 0.62186985
B28: Return on Equity % | C28: =IFERROR(Historical_FS!C45/SUM(Historical_FS!C61:C62),0) -> 0.11298924 | D28: =IFERROR(Historical_FS!D45/SUM(Historical_FS!D61:D62),0) -> 0.1112464 | E28: =IFERROR(Historical_FS!E45/SUM(Historical_FS!E61:E62),0) -> 0.084320022 | F28: =IFERROR(Historical_FS!F45/SUM(Historical_FS!F61:F62),0) -> 0.071121001 | G28: =IFERROR(Historical_FS!G45/SUM(Historical_FS!G61:G62),0) -> 0.14729319 | H28: =IFERROR(Historical_FS!H45/SUM(Historical_FS!H61:H62),0) -> 0.1236421 | I28: =IFERROR(Historical_FS!I45/SUM(Historical_FS!I61:I62),0) -> 0.14541927 | J28: =IFERROR(Historical_FS!J45/SUM(Historical_FS!J61:J62),0) -> 0.093390574 | ... L28: =IFERROR(Historical_FS!L45/SUM(Historical_FS!L61:L62),0) -> 0.085418129
B29: Self Sustained Growth Rate | C29: =IFERROR(C28*C27,0) -> 0.10110942 | D29: =IFERROR(D28*D27,0) -> 0.099992252 | E29: =IFERROR(E28*E27,0) -> 0.073390253 | F29: =IFERROR(F28*F27,0) -> 0.061762959 | G29: =IFERROR(G28*G27,0) -> 0.13768295 | H29: =IFERROR(H28*H27,0) -> 0.09946535 | I29: =IFERROR(I28*I27,0) -> 0.12366961 | J29: =IFERROR(J28*J27,0) -> 0.073196754 | ... L29: =IFERROR(L28*L27,0) -> 0.053118959
B31: Debtor Turnover Ratio | C31: =IFERROR(Historical_FS!C12/Historical_FS!C75,0) -> 13.044865 | D31: =IFERROR(Historical_FS!D12/Historical_FS!D75,0) -> 14.441457 | E31: =IFERROR(Historical_FS!E12/Historical_FS!E75,0) -> 13.950374 | F31: =IFERROR(Historical_FS!F12/Historical_FS!F75,0) -> 14.876862 | G31: =IFERROR(Historical_FS!G12/Historical_FS!G75,0) -> 17.803598 | H31: =IFERROR(Historical_FS!H12/Historical_FS!H75,0) -> 17.391328 | I31: =IFERROR(Historical_FS!I12/Historical_FS!I75,0) -> 17.124189 | J31: =IFERROR(Historical_FS!J12/Historical_FS!J75,0) -> 16.353673 | ... L31: =IFERROR(Historical_FS!L12/Historical_FS!L75,0) -> 12.89506
B32: Creditor Turnover Ratio | C32: =IFERROR((Historical_FS!C18+Historical_FS!C76)/Historical_FS!C64,0) -> 1.7206427 | D32: =IFERROR((Historical_FS!D18+Historical_FS!D76)/Historical_FS!D64,0) -> 1.5738719 | E32: =IFERROR((Historical_FS!E18+Historical_FS!E76)/Historical_FS!E64,0) -> 1.6854848 | F32: =IFERROR((Historical_FS!F18+Historical_FS!F76)/Historical_FS!F64,0) -> 1.4811959 | G32: =IFERROR((Historical_FS!G18+Historical_FS!G76)/Historical_FS!G64,0) -> 1.4450522 | H32: =IFERROR((Historical_FS!H18+Historical_FS!H76)/Historical_FS!H64,0) -> 1.22598 | I32: =IFERROR((Historical_FS!I18+Historical_FS!I76)/Historical_FS!I64,0) -> 1.4554496 | J32: =IFERROR((Historical_FS!J18+Historical_FS!J76)/Historical_FS!J64,0) -> 1.6121843 | ... L32: =IFERROR((Historical_FS!L18+Historical_FS!L76)/Historical_FS!L64,0) -> 1.3079766
B33: Inventory Turnover Ratio | C33: =IFERROR(Historical_FS!C18/Historical_FS!C76,0) -> 5.0506115 | D33: =IFERROR(Historical_FS!D18/Historical_FS!D76,0) -> 5.1251416 | E33: =IFERROR(Historical_FS!E18/Historical_FS!E76,0) -> 4.8182881 | F33: =IFERROR(Historical_FS!F18/Historical_FS!F76,0) -> 5.3012764 | G33: =IFERROR(Historical_FS!G18/Historical_FS!G76,0) -> 4.9244911 | H33: =IFERROR(Historical_FS!H18/Historical_FS!H76,0) -> 5.1886151 | I33: =IFERROR(Historical_FS!I18/Historical_FS!I76,0) -> 4.7424789 | J33: =IFERROR(Historical_FS!J18/Historical_FS!J76,0) -> 5.3392071 | ... L33: =IFERROR(Historical_FS!L18/Historical_FS!L76,0) -> 4.310031
B34: Fixed Asset Turnover Ratio | C34: =IFERROR(Historical_FS!C12/SUM(Historical_FS!C68:C70),0) -> 0.78915369 | D34: =IFERROR(Historical_FS!D12/SUM(Historical_FS!D68:D70),0) -> 0.75710517 | E34: =IFERROR(Historical_FS!E12/SUM(Historical_FS!E68:E70),0) -> 0.66373166 | F34: =IFERROR(Historical_FS!F12/SUM(Historical_FS!F68:F70),0) -> 0.68285175 | G34: =IFERROR(Historical_FS!G12/SUM(Historical_FS!G68:G70),0) -> 0.6629749 | H34: =IFERROR(Historical_FS!H12/SUM(Historical_FS!H68:H70),0) -> 0.6456138 | I34: =IFERROR(Historical_FS!I12/SUM(Historical_FS!I68:I70),0) -> 0.78967725 | J34: =IFERROR(Historical_FS!J12/SUM(Historical_FS!J68:J70),0) -> 0.89175471 | ... L34: =IFERROR(Historical_FS!L12/SUM(Historical_FS!L68:L70),0) -> 0.71686297
B35: Capital Turnover Ratio | C35: =IFERROR(Historical_FS!C12/SUM(Historical_FS!C61:C63),0) -> 0.77248122 | D35: =IFERROR(Historical_FS!D12/SUM(Historical_FS!D61:D63),0) -> 0.77206373 | E35: =IFERROR(Historical_FS!E12/SUM(Historical_FS!E61:E63),0) -> 0.67548382 | F35: =IFERROR(Historical_FS!F12/SUM(Historical_FS!F61:F63),0) -> 0.70170772 | G35: =IFERROR(Historical_FS!G12/SUM(Historical_FS!G61:G63),0) -> 0.68366146 | H35: =IFERROR(Historical_FS!H12/SUM(Historical_FS!H61:H63),0) -> 0.67875303 | I35: =IFERROR(Historical_FS!I12/SUM(Historical_FS!I61:I63),0) -> 0.85202272 | J35: =IFERROR(Historical_FS!J12/SUM(Historical_FS!J61:J63),0) -> 0.96723424 | ... L35: =IFERROR(Historical_FS!L12/SUM(Historical_FS!L61:L63),0) -> 0.80113882
B37: Debtor Days | C37: =IFERROR(365/C31,0) -> 27.980358 | D37: =IFERROR(365/D31,0) -> 25.274458 | E37: =IFERROR(365/E31,0) -> 26.164172 | F37: =IFERROR(365/F31,0) -> 24.534744 | G37: =IFERROR(365/G31,0) -> 20.501474 | H37: =IFERROR(365/H31,0) -> 20.987471 | I37: =IFERROR(365/I31,0) -> 21.314878 | J37: =IFERROR(365/J31,0) -> 22.319145 | ... L37: =IFERROR(365/L31,0) -> 28.305412
B38: Payable Days | C38: =IFERROR(365/C32,0) -> 212.13004 | D38: =IFERROR(365/D32,0) -> 231.91214 | E38: =IFERROR(365/E32,0) -> 216.5549 | F38: =IFERROR(365/F32,0) -> 246.4225 | G38: =IFERROR(365/G32,0) -> 252.58603 | H38: =IFERROR(365/H32,0) -> 297.721 | I38: =IFERROR(365/I32,0) -> 250.78161 | J38: =IFERROR(365/J32,0) -> 226.40092 | ... L38: =IFERROR(365/L32,0) -> 279.05698
B39: Inventory Days | C39: =IFERROR(365/C33,0) -> 72.268477 | D39: =IFERROR(365/D33,0) -> 71.217544 | E39: =IFERROR(365/E33,0) -> 75.753046 | F39: =IFERROR(365/F33,0) -> 68.851343 | G39: =IFERROR(365/G33,0) -> 74.119333 | H39: =IFERROR(365/H33,0) -> 70.346324 | I39: =IFERROR(365/I33,0) -> 76.963969 | J39: =IFERROR(365/J33,0) -> 68.36221 | ... L39: =IFERROR(365/L33,0) -> 84.686166
B40: Cash Conversion Cycle | C40: =IFERROR(C37+C39-C38,0) -> -111.88121 | D40: =IFERROR(D37+D39-D38,0) -> -135.42014 | E40: =IFERROR(E37+E39-E38,0) -> -114.63768 | F40: =IFERROR(F37+F39-F38,0) -> -153.03641 | G40: =IFERROR(G37+G39-G38,0) -> -157.96523 | H40: =IFERROR(H37+H39-H38,0) -> -206.38721 | I40: =IFERROR(I37+I39-I38,0) -> -152.50276 | J40: =IFERROR(J37+J39-J38,0) -> -135.71956 | ... L40: =IFERROR(L37+L39-L38,0) -> -166.0654
B42: CFO/Sales | C42: =IFERROR(Historical_FS!C86/Historical_FS!C12,0) -> 0.1798973 | D42: =IFERROR(Historical_FS!D86/Historical_FS!D12,0) -> 0.19724185 | E42: =IFERROR(Historical_FS!E86/Historical_FS!E12,0) -> 0.12550591 | F42: =IFERROR(Historical_FS!F86/Historical_FS!F12,0) -> 0.14364871 | G42: =IFERROR(Historical_FS!G86/Historical_FS!G12,0) -> 0.21147828 | H42: =IFERROR(Historical_FS!H86/Historical_FS!H12,0) -> 0.27948075 | I42: =IFERROR(Historical_FS!I86/Historical_FS!I12,0) -> 0.17648682 | J42: =IFERROR(Historical_FS!J86/Historical_FS!J12,0) -> 0.14340612 | ... L42: =IFERROR(Historical_FS!L86/Historical_FS!L12,0) -> 0.14051717
B43: CFO/Total Assets | C43: =IFERROR(Historical_FS!C86/Historical_FS!C80,0) -> 0.10984847 | D43: =IFERROR(Historical_FS!D86/Historical_FS!D80,0) -> 0.1185763 | E43: =IFERROR(Historical_FS!E86/Historical_FS!E80,0) -> 0.068042104 | F43: =IFERROR(Historical_FS!F86/Historical_FS!F80,0) -> 0.077830398 | G43: =IFERROR(Historical_FS!G86/Historical_FS!G80,0) -> 0.1132757 | H43: =IFERROR(Historical_FS!H86/Historical_FS!H80,0) -> 0.1450514 | I43: =IFERROR(Historical_FS!I86/Historical_FS!I80,0) -> 0.11076054 | J43: =IFERROR(Historical_FS!J86/Historical_FS!J80,0) -> 0.099244477 | ... L43: =IFERROR(Historical_FS!L86/Historical_FS!L80,0) -> 0.079868558
B44: CFO/Total Debt | C44: =IFERROR(Historical_FS!C86/Historical_FS!C63,0) -> 0.42624381 | D44: =IFERROR(Historical_FS!D86/Historical_FS!D63,0) -> 0.59059601 | E44: =IFERROR(Historical_FS!E86/Historical_FS!E63,0) -> 0.19958707 | F44: =IFERROR(Historical_FS!F86/Historical_FS!F63,0) -> 0.23507124 | G44: =IFERROR(Historical_FS!G86/Historical_FS!G63,0) -> 0.3898091 | H44: =IFERROR(Historical_FS!H86/Historical_FS!H63,0) -> 0.57552261 | I44: =IFERROR(Historical_FS!I86/Historical_FS!I63,0) -> 0.82159167 | J44: =IFERROR(Historical_FS!J86/Historical_FS!J63,0) -> 0.82014951 | ... L44: =IFERROR(Historical_FS!L86/Historical_FS!L63,0) -> 0.44282301

Sheet Vertical
B9: ="Vertical Analysis"&" - "&'Data Sheet'!B1 -> Vertical Analysis - ULTRATECH CEMENT LTD
B10: Years | C10: ='Data Sheet'!B16 -> 42460 | D10: ='Data Sheet'!C16 -> 42825 | E10: ='Data Sheet'!D16 -> 43190 | F10: ='Data Sheet'!E16 -> 43555 | G10: ='Data Sheet'!F16 -> 43921 | H10: ='Data Sheet'!G16 -> 44286 | I10: ='Data Sheet'!H16 -> 44651 | J10: ='Data Sheet'!I16 -> 45016 | ... L10: ='Data Sheet'!K16 -> 45747
A11: # | B11: Income Statement % Sales
B12: =Historical_FS!B12&" % Sales" -> Sales % Sales | C12: =IFERROR(Historical_FS!C12/Historical_FS!C12,0) -> 1 | D12: =IFERROR(Historical_FS!D12/Historical_FS!D12,0) -> 1 | E12: =IFERROR(Historical_FS!E12/Historical_FS!E12,0) -> 1 | F12: =IFERROR(Historical_FS!F12/Historical_FS!F12,0) -> 1 | G12: =IFERROR(Historical_FS!G12/Historical_FS!G12,0) -> 1 | H12: =IFERROR(Historical_FS!H12/Historical_FS!H12,0) -> 1 | I12: =IFERROR(Historical_FS!I12/Historical_FS!I12,0) -> 1 | J12: =IFERROR(Historical_FS!J12/Historical_FS!J12,0) -> 1 | ... L12: =IFERROR(Historical_FS!L12/Historical_FS!L12,0) -> 1
B14: =Historical_FS!B18&" % Sales" -> COGS % Sales | C14: =IFERROR(Historical_FS!C19,0) -> 0.49286414 | D14: =IFERROR(Historical_FS!D19,0) -> 0.48487287 | E14: =IFERROR(Historical_FS!E19,0) -> 0.50822761 | F14: =IFERROR(Historical_FS!F19,0) -> 0.52408431 | G14: =IFERROR(Historical_FS!G19,0) -> 0.4855273 | H14: =IFERROR(Historical_FS!H19,0) -> 0.46612246 | I14: =IFERROR(Historical_FS!I19,0) -> 0.5045154 | J14: =IFERROR(Historical_FS!J19,0) -> 0.55822171 | ... L14: =IFERROR(Historical_FS!L19,0) -> 0.5426459
B15: =Historical_FS!B21&" % Sales" -> Gross Profit % Sales | C15: =IFERROR(Historical_FS!C22,0) -> 0.52557523 | D15: =IFERROR(Historical_FS!D22,0) -> 0.54066886 | E15: =IFERROR(Historical_FS!E22,0) -> 0.49958326 | F15: =IFERROR(Historical_FS!F22,0) -> 0.48435951 | G15: =IFERROR(Historical_FS!G22,0) -> 0.52981707 | H15: =IFERROR(Historical_FS!H22,0) -> 0.54770669 | I15: =IFERROR(Historical_FS!I22,0) -> 0.50821168 | J15: =IFERROR(Historical_FS!J22,0) -> 0.44979711 | ... L15: =IFERROR(Historical_FS!L22,0) -> 0.46257745
B16: =Historical_FS!B24&" % Sales" -> Selling & Other Exp. % Sales | C16: =IFERROR(Historical_FS!C25,0) -> 0.31229138 | D16: =IFERROR(Historical_FS!D25,0) -> 0.30971029 | E16: =IFERROR(Historical_FS!E25,0) -> 0.29340881 | F16: =IFERROR(Historical_FS!F25,0) -> 0.29871985 | G16: =IFERROR(Historical_FS!G25,0) -> 0.29656099 | H16: =IFERROR(Historical_FS!H25,0) -> 0.27523689 | I16: =IFERROR(Historical_FS!I25,0) -> 0.27657573 | J16: =IFERROR(Historical_FS!J25,0) -> 0.27384892 | ... L16: =IFERROR(Historical_FS!L25,0) -> 0.28887463
B17: =Historical_FS!B27&" % Sales" -> EBITDA % Sales | C17: =IFERROR(Historical_FS!C28,0) -> 0.21328386 | D17: =IFERROR(Historical_FS!D28,0) -> 0.23095858 | E17: =IFERROR(Historical_FS!E28,0) -> 0.20617445 | F17: =IFERROR(Historical_FS!F28,0) -> 0.18563966 | G17: =IFERROR(Historical_FS!G28,0) -> 0.23325608 | H17: =IFERROR(Historical_FS!H28,0) -> 0.2724698 | I17: =IFERROR(Historical_FS!I28,0) -> 0.23163595 | J17: =IFERROR(Historical_FS!J28,0) -> 0.17594819 | ... L17: =IFERROR(Historical_FS!L28,0) -> 0.17370282
B18: =Historical_FS!B30&" % Sales" -> Depreciation % Sales | C18: =IFERROR(Historical_FS!C31,0) -> 0.054751197 | D18: =IFERROR(Historical_FS!D31,0) -> 0.053139436 | E18: =IFERROR(Historical_FS!E31,0) -> 0.059651786 | F18: =IFERROR(Historical_FS!F31,0) -> 0.059107487 | G18: =IFERROR(Historical_FS!G31,0) -> 0.064168444 | H18: =IFERROR(Historical_FS!H31,0) -> 0.060372984 | I18: =IFERROR(Historical_FS!I31,0) -> 0.051612365 | J18: =IFERROR(Historical_FS!J31,0) -> 0.045667155 | ... L18: =IFERROR(Historical_FS!L31,0) -> 0.052859497
B19: =Historical_FS!B33&" % Sales" -> EBIT % Sales | C19: =IFERROR(Historical_FS!C34,0) -> 0.15853266 | D19: =IFERROR(Historical_FS!D34,0) -> 0.17781914 | E19: =IFERROR(Historical_FS!E34,0) -> 0.14652267 | F19: =IFERROR(Historical_FS!F34,0) -> 0.12653218 | G19: =IFERROR(Historical_FS!G34,0) -> 0.16908764 | H19: =IFERROR(Historical_FS!H34,0) -> 0.21209682 | I19: =IFERROR(Historical_FS!I34,0) -> 0.18002359 | J19: =IFERROR(Historical_FS!J34,0) -> 0.13028103 | ... L19: =IFERROR(Historical_FS!L34,0) -> 0.12084332
B20: =Historical_FS!B36&" % Sales" -> Interest % Sales | C20: =IFERROR(Historical_FS!C37,0) -> 0.022513998 | D20: =IFERROR(Historical_FS!D37,0) -> 0.025225675 | E20: =IFERROR(Historical_FS!E37,0) -> 0.039950133 | F20: =IFERROR(Historical_FS!F37,0) -> 0.042878994 | G20: =IFERROR(Historical_FS!G37,0) -> 0.046939787 | H20: =IFERROR(Historical_FS!H37,0) -> 0.033216846 | I20: =IFERROR(Historical_FS!I37,0) -> 0.017960666 | J20: =IFERROR(Historical_FS!J37,0) -> 0.013009492 | ... L20: =IFERROR(Historical_FS!L37,0) -> 0.021730461
B21: =Historical_FS!B39&" % Sales" -> EBT % Sales | C21: =IFERROR(Historical_FS!C40,0) -> 0.13601866 | D21: =IFERROR(Historical_FS!D40,0) -> 0.15259346 | E21: =IFERROR(Historical_FS!E40,0) -> 0.10657253 | F21: =IFERROR(Historical_FS!F40,0) -> 0.083653182 | G21: =IFERROR(Historical_FS!G40,0) -> 0.12214785 | H21: =IFERROR(Historical_FS!H40,0) -> 0.17887998 | I21: =IFERROR(Historical_FS!I40,0) -> 0.16206292 | J21: =IFERROR(Historical_FS!J40,0) -> 0.11727154 | ... L21: =IFERROR(Historical_FS!L40,0) -> 0.099112858
B22: =Historical_FS!B45&" % Sales" -> Net Profit % Sales | C22: =IFERROR(Historical_FS!C46,0) -> 0.098580541 | D22: =IFERROR(Historical_FS!D46,0) -> 0.10693661 | E22: =IFERROR(Historical_FS!E46,0) -> 0.071806297 | F22: =IFERROR(Historical_FS!F46,0) -> 0.05789313 | G22: =IFERROR(Historical_FS!G46,0) -> 0.13553841 | H22: =IFERROR(Historical_FS!H46,0) -> 0.12211855 | I22: =IFERROR(Historical_FS!I46,0) -> 0.1394377 | J22: =IFERROR(Historical_FS!J46,0) -> 0.080224567 | ... L22: =IFERROR(Historical_FS!L46,0) -> 0.079515893
A24: # | B24: Balance Sheet % Total Assets
B25: =Historical_FS!B80&" % Total Assets" -> Total Assets % Total Assets | C25: =IFERROR(Historical_FS!C80/Historical_FS!C80,0) -> 1 | D25: =IFERROR(Historical_FS!D80/Historical_FS!D80,0) -> 1 | E25: =IFERROR(Historical_FS!E80/Historical_FS!E80,0) -> 1 | F25: =IFERROR(Historical_FS!F80/Historical_FS!F80,0) -> 1 | G25: =IFERROR(Historical_FS!G80/Historical_FS!G80,0) -> 1 | H25: =IFERROR(Historical_FS!H80/Historical_FS!H80,0) -> 1 | I25: =IFERROR(Historical_FS!I80/Historical_FS!I80,0) -> 1 | J25: =IFERROR(Historical_FS!J80/Historical_FS!J80,0) -> 1 | ... L25: =IFERROR(Historical_FS!L80/Historical_FS!L80,0) -> 1
B27: =Historical_FS!B68&" % Total Assets" -> Net Block % Total Assets | C27: =IFERROR(Historical_FS!C68/Historical_FS!C$80,0) -> 0.61440906 | D27: =IFERROR(Historical_FS!D68/Historical_FS!D$80,0) -> 0.61370045 | E27: =IFERROR(Historical_FS!E68/Historical_FS!E$80,0) -> 0.69503924 | F27: =IFERROR(Historical_FS!F68/Historical_FS!F$80,0) -> 0.74020707 | G27: =IFERROR(Historical_FS!G68/Historical_FS!G$80,0) -> 0.72147723 | H27: =IFERROR(Historical_FS!H68/Historical_FS!H$80,0) -> 0.64300252 | I27: =IFERROR(Historical_FS!I68/Historical_FS!I$80,0) -> 0.66205246 | J27: =IFERROR(Historical_FS!J68/Historical_FS!J$80,0) -> 0.65198883 | ... L27: =IFERROR(Historical_FS!L68/Historical_FS!L$80,0) -> 0.7076462
B28: =Historical_FS!B69&" % Total Assets" -> Capital Work in Progress % Total Assets | C28: =IFERROR(Historical_FS!C69/Historical_FS!C$80,0) -> 0.035663488 | D28: =IFERROR(Historical_FS!D69/Historical_FS!D$80,0) -> 0.021831306 | E28: =IFERROR(Historical_FS!E69/Historical_FS!E$80,0) -> 0.026446993 | F28: =IFERROR(Historical_FS!F69/Historical_FS!F$80,0) -> 0.01507108 | G28: =IFERROR(Historical_FS!G69/Historical_FS!G$80,0) -> 0.011608961 | H28: =IFERROR(Historical_FS!H69/Historical_FS!H$80,0) -> 0.019572423 | I28: =IFERROR(Historical_FS!I69/Historical_FS!I$80,0) -> 0.057088507 | J28: =IFERROR(Historical_FS!J69/Historical_FS!J$80,0) -> 0.044215061 | ... L28: =IFERROR(Historical_FS!L69/Historical_FS!L$80,0) -> 0.046651904
B29: =Historical_FS!B70&" % Total Assets" -> Investments % Total Assets | C29: =IFERROR(Historical_FS!C70/Historical_FS!C$80,0) -> 0.1236901 | D29: =IFERROR(Historical_FS!D70/Historical_FS!D$80,0) -> 0.15850867 | E29: =IFERROR(Historical_FS!E70/Historical_FS!E$80,0) -> 0.095323698 | F29: =IFERROR(Historical_FS!F70/Historical_FS!F$80,0) -> 0.03817466 | G29: =IFERROR(Historical_FS!G70/Historical_FS!G$80,0) -> 0.074844146 | H29: =IFERROR(Historical_FS!H70/Historical_FS!H$80,0) -> 0.14131615 | I29: =IFERROR(Historical_FS!I70/Historical_FS!I$80,0) -> 0.075595527 | J29: =IFERROR(Historical_FS!J70/Historical_FS!J$80,0) -> 0.079852463 | ... L29: =IFERROR(Historical_FS!L70/Historical_FS!L$80,0) -> 0.038587073
B30: =Historical_FS!B71&" % Total Assets" -> Other Assets % Total Assets | C30: =IFERROR(Historical_FS!C71/Historical_FS!C$80,0) -> 0.064808654 | D30: =IFERROR(Historical_FS!D71/Historical_FS!D$80,0) -> 0.054179299 | E30: =IFERROR(Historical_FS!E71/Historical_FS!E$80,0) -> 0.083309401 | F30: =IFERROR(Historical_FS!F71/Historical_FS!F$80,0) -> 0.10689827 | G30: =IFERROR(Historical_FS!G71/Historical_FS!G$80,0) -> 0.10235703 | H30: =IFERROR(Historical_FS!H71/Historical_FS!H$80,0) -> 0.096345459 | I30: =IFERROR(Historical_FS!I71/Historical_FS!I$80,0) -> 0.097564962 | J30: =IFERROR(Historical_FS!J71/Historical_FS!J$80,0) -> 0.096690538 | ... L30: =IFERROR(Historical_FS!L71/Historical_FS!L$80,0) -> 0.078952835
B31: =Historical_FS!B72&" % Total Assets" -> Total Non Current Assets % Total Assets | C31: =IFERROR(Historical_FS!C72/Historical_FS!C$80,0) -> 0.8385713 | D31: =IFERROR(Historical_FS!D72/Historical_FS!D$80,0) -> 0.84821973 | E31: =IFERROR(Historical_FS!E72/Historical_FS!E$80,0) -> 0.90011934 | F31: =IFERROR(Historical_FS!F72/Historical_FS!F$80,0) -> 0.90035109 | G31: =IFERROR(Historical_FS!G72/Historical_FS!G$80,0) -> 0.91028736 | H31: =IFERROR(Historical_FS!H72/Historical_FS!H$80,0) -> 0.90023655 | I31: =IFERROR(Historical_FS!I72/Historical_FS!I$80,0) -> 0.89230146 | J31: =IFERROR(Historical_FS!J72/Historical_FS!J$80,0) -> 0.87274689 | ... L31: =IFERROR(Historical_FS!L72/Historical_FS!L$80,0) -> 0.87183802
B32: =Historical_FS!B75&" % Total Assets" -> Receivables % Total Assets | C32: =IFERROR(Historical_FS!C75/Historical_FS!C$80,0) -> 0.046809042 | D32: =IFERROR(Historical_FS!D75/Historical_FS!D$80,0) -> 0.041628217 | E32: =IFERROR(Historical_FS!E75/Historical_FS!E$80,0) -> 0.038862227 | F32: =IFERROR(Historical_FS!F75/Historical_FS!F$80,0) -> 0.036419687 | G32: =IFERROR(Historical_FS!G75/Historical_FS!G$80,0) -> 0.030085916 | H32: =IFERROR(Historical_FS!H75/Historical_FS!H$80,0) -> 0.029842642 | I32: =IFERROR(Historical_FS!I75/Historical_FS!I$80,0) -> 0.036649054 | J32: =IFERROR(Historical_FS!J75/Historical_FS!J$80,0) -> 0.042317827 | ... L32: =IFERROR(Historical_FS!L75/Historical_FS!L$80,0) -> 0.04407812
B33: =Historical_FS!B76&" % Total Assets" -> Inventory % Total Assets | C33: =IFERROR(Historical_FS!C76/Historical_FS!C$80,0) -> 0.059587149 | D33: =IFERROR(Historical_FS!D76/Historical_FS!D$80,0) -> 0.056874926 | E33: =IFERROR(Historical_FS!E76/Historical_FS!E$80,0) -> 0.057184593 | F33: =IFERROR(Historical_FS!F76/Historical_FS!F$80,0) -> 0.053563413 | G33: =IFERROR(Historical_FS!G76/Historical_FS!G$80,0) -> 0.052810867 | H33: =IFERROR(Historical_FS!H76/Historical_FS!H$80,0) -> 0.046624973 | I33: =IFERROR(Historical_FS!I76/Historical_FS!I$80,0) -> 0.066763917 | J33: =IFERROR(Historical_FS!J76/Historical_FS!J$80,0) -> 0.072355013 | ... L33: =IFERROR(Historical_FS!L76/Historical_FS!L$80,0) -> 0.071562019
B34: =Historical_FS!B77&" % Total Assets" -> Cash & Bank % Total Assets | C34: =IFERROR(Historical_FS!C77/Historical_FS!C$80,0) -> 0.055032504 | D34: =IFERROR(Historical_FS!D77/Historical_FS!D$80,0) -> 0.053277124 | E34: =IFERROR(Historical_FS!E77/Historical_FS!E$80,0) -> 0.0038338436 | F34: =IFERROR(Historical_FS!F77/Historical_FS!F$80,0) -> 0.0096658141 | G34: =IFERROR(Historical_FS!G77/Historical_FS!G$80,0) -> 0.006815857 | H34: =IFERROR(Historical_FS!H77/Historical_FS!H$80,0) -> 0.023295835 | I34: =IFERROR(Historical_FS!I77/Historical_FS!I$80,0) -> 0.0042855725 | J34: =IFERROR(Historical_FS!J77/Historical_FS!J$80,0) -> 0.012580269 | ... L34: =IFERROR(Historical_FS!L77/Historical_FS!L$80,0) -> 0.012521845
B35: =Historical_FS!B78&" % Total Assets" -> Total Current Assets % Total Assets | C35: =IFERROR(Historical_FS!C78/Historical_FS!C$80,0) -> 0.1614287 | D35: =IFERROR(Historical_FS!D78/Historical_FS!D$80,0) -> 0.15178027 | E35: =IFERROR(Historical_FS!E78/Historical_FS!E$80,0) -> 0.099880664 | F35: =IFERROR(Historical_FS!F78/Historical_FS!F$80,0) -> 0.099648914 | G35: =IFERROR(Historical_FS!G78/Historical_FS!G$80,0) -> 0.08971264 | H35: =IFERROR(Historical_FS!H78/Historical_FS!H$80,0) -> 0.09976345 | I35: =IFERROR(Historical_FS!I78/Historical_FS!I$80,0) -> 0.10769854 | J35: =IFERROR(Historical_FS!J78/Historical_FS!J$80,0) -> 0.12725311 | ... L35: =IFERROR(Historical_FS!L78/Historical_FS!L$80,0) -> 0.12816198
A37: # | B37: Balance Sheet % Total Liabilities
B38: Total Liabilities | C38: =IFERROR(Historical_FS!C63+Historical_FS!C64,0) -> 19247.48 | D38: =IFERROR(Historical_FS!D63+Historical_FS!D64,0) -> 17817.22 | E38: =IFERROR(Historical_FS!E63+Historical_FS!E64,0) -> 30759.93 | F38: =IFERROR(Historical_FS!F63+Historical_FS!F64,0) -> 42774.72 | G38: =IFERROR(Historical_FS!G63+Historical_FS!G64,0) -> 40170.05 | H38: =IFERROR(Historical_FS!H63+Historical_FS!H64,0) -> 42001.67 | I38: =IFERROR(Historical_FS!I63+Historical_FS!I64,0) -> 33376.17 | J38: =IFERROR(Historical_FS!J63+Historical_FS!J64,0) -> 37055.86 | ... L38: =IFERROR(Historical_FS!L63+Historical_FS!L64,0) -> 62925.29
B39: =B38&" % Total Liabilities" -> Total Liabilities % Total Liabilities | C39: =IFERROR(C38/C38,0) -> 1 | D39: =IFERROR(D38/D38,0) -> 1 | E39: =IFERROR(E38/E38,0) -> 1 | F39: =IFERROR(F38/F38,0) -> 1 | G39: =IFERROR(G38/G38,0) -> 1 | H39: =IFERROR(H38/H38,0) -> 1 | I39: =IFERROR(I38/I38,0) -> 1 | J39: =IFERROR(J38/J38,0) -> 1 | ... L39: =IFERROR(L38/L38,0) -> 1
B41: =Historical_FS!B61&" % Total Liabilities" -> Equity Share Capital % Total Liabilities | C41: =IFERROR(Historical_FS!C61/Vertical!C$38,0) -> 0.01425797 | D41: =IFERROR(Historical_FS!D61/Vertical!D$38,0) -> 0.015407005 | E41: =IFERROR(Historical_FS!E61/Vertical!E$38,0) -> 0.0089275236 | F41: =IFERROR(Historical_FS!F61/Vertical!F$38,0) -> 0.0064206148 | G41: =IFERROR(Historical_FS!G61/Vertical!G$38,0) -> 0.0071852039 | H41: =IFERROR(Historical_FS!H61/Vertical!H$38,0) -> 0.0068723458 | I41: =IFERROR(Historical_FS!I61/Vertical!I$38,0) -> 0.0086489852 | J41: =IFERROR(Historical_FS!J61/Vertical!J$38,0) -> 0.0077906706 | ... L41: =IFERROR(Historical_FS!L61/Vertical!L$38,0) -> 0.0046830138
B42: =Historical_FS!B62&" % Total Liabilities" -> Reserves % Total Liabilities | C42: =IFERROR(Historical_FS!C62/Vertical!C$38,0) -> 1.125924 | D42: =IFERROR(Historical_FS!D62/Vertical!D$38,0) -> 1.3535995 | E42: =IFERROR(Historical_FS!E62/Vertical!E$38,0) -> 0.84871942 | F42: =IFERROR(Historical_FS!F62/Vertical!F$38,0) -> 0.78261202 | G42: =IFERROR(Historical_FS!G62/Vertical!G$38,0) -> 0.96477674 | H42: =IFERROR(Historical_FS!H62/Vertical!H$38,0) -> 1.0448639 | I42: =IFERROR(Historical_FS!I62/Vertical!I$38,0) -> 1.5024672 | J42: =IFERROR(Historical_FS!J62/Vertical!J$38,0) -> 1.4582268 | ... L42: =IFERROR(Historical_FS!L62/Vertical!L$38,0) -> 1.1189792
B43: =Historical_FS!B63&" % Total Liabilities" -> Borrowings % Total Liabilities | C43: =IFERROR(Historical_FS!C63/Vertical!C$38,0) -> 0.5515522 | D43: =IFERROR(Historical_FS!D63/Vertical!D$38,0) -> 0.47563481 | E43: =IFERROR(Historical_FS!E63/Vertical!E$38,0) -> 0.63329858 | F43: =IFERROR(Historical_FS!F63/Vertical!F$38,0) -> 0.59233585 | G43: =IFERROR(Historical_FS!G63/Vertical!G$38,0) -> 0.57303787 | H43: =IFERROR(Historical_FS!H63/Vertical!H$38,0) -> 0.51710777 | I43: =IFERROR(Historical_FS!I63/Vertical!I$38,0) -> 0.33852896 | J43: =IFERROR(Historical_FS!J63/Vertical!J$38,0) -> 0.29840732 | ... L43: =IFERROR(Historical_FS!L63/Vertical!L$38,0) -> 0.38302851
B44: =Historical_FS!B64&" % Total Liabilities" -> Other Liabilities % Total Liabilities | C44: =IFERROR(Historical_FS!C64/Vertical!C$38,0) -> 0.4484478 | D44: =IFERROR(Historical_FS!D64/Vertical!D$38,0) -> 0.52436519 | E44: =IFERROR(Historical_FS!E64/Vertical!E$38,0) -> 0.36670142 | F44: =IFERROR(Historical_FS!F64/Vertical!F$38,0) -> 0.40766415 | G44: =IFERROR(Historical_FS!G64/Vertical!G$38,0) -> 0.42696213 | H44: =IFERROR(Historical_FS!H64/Vertical!H$38,0) -> 0.48289223 | I44: =IFERROR(Historical_FS!I64/Vertical!I$38,0) -> 0.66147104 | J44: =IFERROR(Historical_FS!J64/Vertical!J$38,0) -> 0.70159268 | ... L44: =IFERROR(Historical_FS!L64/Vertical!L$38,0) -> 0.61697149

Sheet Horizontal
B9: ="Horizontal Analysis"&" - "&'Data Sheet'!B1 -> Horizontal Analysis - ULTRATECH CEMENT LTD
B10: Years | C10: ='Data Sheet'!B16 -> 42460 | D10: ='Data Sheet'!C16 -> 42825 | E10: ='Data Sheet'!D16 -> 43190 | F10: ='Data Sheet'!E16 -> 43555 | G10: ='Data Sheet'!F16 -> 43921 | H10: ='Data Sheet'!G16 -> 44286 | I10: ='Data Sheet'!H16 -> 44651 | J10: ='Data Sheet'!I16 -> 45016 | ... L10: ='Data Sheet'!K16 -> 45747 | M10: Trend
A11: # | B11: Income Statement YoY Growth
B13: =Historical_FS!B12 -> Sales | C13: =IFERROR(Historical_FS!C12,0) -> 25153.24 | D13: =IFERROR(Historical_FS!D12,0) -> 25374.94 | E13: =IFERROR(Historical_FS!E12,0) -> 30978.62 | F13: =IFERROR(Historical_FS!F12,0) -> 41462.26 | G13: =IFERROR(Historical_FS!G12,0) -> 42429.89 | H13: =IFERROR(Historical_FS!H12,0) -> 44725.8 | I13: =IFERROR(Historical_FS!I12,0) -> 52598.83 | J13: =IFERROR(Historical_FS!J12,0) -> 63239.98 | ... L13: =IFERROR(Historical_FS!L12,0) -> 75955.13
B14: =B13&" Growth" -> Sales Growth | C14: =IFERROR((C13/B13)-1,"-") -> - | D14: =IFERROR((D13/C13)-1,"-") -> 0.0088139739 | E14: =IFERROR((E13/D13)-1,"-") -> 0.2208352 | F14: =IFERROR((F13/E13)-1,"-") -> 0.33841533 | G14: =IFERROR((G13/F13)-1,"-") -> 0.023337609 | H14: =IFERROR((H13/G13)-1,"-") -> 0.054110675 | I14: =IFERROR((I13/H13)-1,"-") -> 0.17602882 | J14: =IFERROR((J13/I13)-1,"-") -> 0.20230773 | ... L14: =IFERROR((L13/K13)-1,"-") -> 0.071176454
B15: =Historical_FS!B18 -> COGS | C15: =IFERROR(Historical_FS!C18,0) -> 12397.13 | D15: =IFERROR(Historical_FS!D18,0) -> 12303.62 | E15: =IFERROR(Historical_FS!E18,0) -> 15744.19 | F15: =IFERROR(Historical_FS!F18,0) -> 21729.72 | G15: =IFERROR(Historical_FS!G18,0) -> 20600.87 | H15: =IFERROR(Historical_FS!H18,0) -> 20847.7 | I15: =IFERROR(Historical_FS!I18,0) -> 26536.92 | J15: =IFERROR(Historical_FS!J18,0) -> 35301.93 | ... L15: =IFERROR(Historical_FS!L18,0) -> 41216.74
B16: =B15&" Growth" -> COGS Growth | C16: =IFERROR((C15/B15)-1,"-") -> - | D16: =IFERROR((D15/C15)-1,"-") -> -0.0075428748 | E16: =IFERROR((E15/D15)-1,"-") -> 0.27963884 | F16: =IFERROR((F15/E15)-1,"-") -> 0.38017389 | G16: =IFERROR((G15/F15)-1,"-") -> -0.051949588 | H16: =IFERROR((H15/G15)-1,"-") -> 0.011981533 | I16: =IFERROR((I15/H15)-1,"-") -> 0.27289437 | J16: =IFERROR((J15/I15)-1,"-") -> 0.33029492 | ... L16: =IFERROR((L15/K15)-1,"-") -> 0.080771651
B17: =Historical_FS!B21 -> Gross Profit | C17: =IFERROR(Historical_FS!C21,0) -> 13219.92 | D17: =IFERROR(Historical_FS!D21,0) -> 13719.44 | E17: =IFERROR(Historical_FS!E21,0) -> 15476.4 | F17: =IFERROR(Historical_FS!F21,0) -> 20082.64 | G17: =IFERROR(Historical_FS!G21,0) -> 22480.08 | H17: =IFERROR(Historical_FS!H21,0) -> 24496.62 | I17: =IFERROR(Historical_FS!I21,0) -> 26731.34 | J17: =IFERROR(Historical_FS!J21,0) -> 28445.16 | ... L17: =IFERROR(Historical_FS!L21,0) -> 35135.13
B18: =B17&" Growth" -> Gross Profit Growth | C18: =IFERROR((C17/B17)-1,"-") -> - | D18: =IFERROR((D17/C17)-1,"-") -> 0.037785403 | E18: =IFERROR((E17/D17)-1,"-") -> 0.12806354 | F18: =IFERROR((F17/E17)-1,"-") -> 0.29762994 | G18: =IFERROR((G17/F17)-1,"-") -> 0.11937873 | H18: =IFERROR((H17/G17)-1,"-") -> 0.089703417 | I18: =IFERROR((I17/H17)-1,"-") -> 0.091225647 | J18: =IFERROR((J17/I17)-1,"-") -> 0.064112761 | ... L18: =IFERROR((L17/K17)-1,"-") -> 0.054200434
B19: =Historical_FS!B24 -> Selling & Other Exp. | C19: =Historical_FS!C24 -> 7855.14 | D19: =Historical_FS!D24 -> 7858.88 | E19: =Historical_FS!E24 -> 9089.4 | F19: =Historical_FS!F24 -> 12385.6 | G19: =Historical_FS!G24 -> 12583.05 | H19: =Historical_FS!H24 -> 12310.19 | I19: =Historical_FS!I24 -> 14547.56 | ... L19: =Historical_FS!L24 -> 21941.51
B20: =B19&" Growth" -> Selling & Other Exp. Growth | C20: =IFERROR((C19/B19)-1,"-") -> - | D20: =IFERROR((D19/C19)-1,"-") -> 0.00047612137 | E20: =IFERROR((E19/D19)-1,"-") -> 0.15657702 | F20: =IFERROR((F19/E19)-1,"-") -> 0.3626422 | G20: =IFERROR((G19/F19)-1,"-") -> 0.0159419 | H20: =IFERROR((H19/G19)-1,"-") -> -0.021684727 | I20: =IFERROR((I19/H19)-1,"-") -> 0.18174943 | J20: =IFERROR((J19/I19)-1,"-") -> 0.19045393 | ... L20: =IFERROR((L19/K19)-1,"-") -> 0.1085389
B21: =Historical_FS!B27 -> EBITDA | C21: =Historical_FS!C27 -> 5364.78 | D21: =Historical_FS!D27 -> 5860.56 | E21: =Historical_FS!E27 -> 6387 | F21: =Historical_FS!F27 -> 7697.04 | G21: =Historical_FS!G27 -> 9897.03 | H21: =Historical_FS!H27 -> 12186.43 | I21: =Historical_FS!I27 -> 12183.78 | ... L21: =Historical_FS!L27 -> 13193.62
B22: =B21&" Growth" -> EBITDA Growth | C22: =IFERROR((C21/B21)-1,"-") -> - | D22: =IFERROR((D21/C21)-1,"-") -> 0.092413855 | E22: =IFERROR((E21/D21)-1,"-") -> 0.089827593 | F22: =IFERROR((F21/E21)-1,"-") -> 0.20511038 | G22: =IFERROR((G21/F21)-1,"-") -> 0.28582286 | H22: =IFERROR((H21/G21)-1,"-") -> 0.23132192 | I22: =IFERROR((I21/H21)-1,"-") -> -0.00021745499 | J22: =IFERROR((J21/I21)-1,"-") -> -0.086739912 | ... L22: =IFERROR((L21/K21)-1,"-") -> -0.025259465
B23: =Historical_FS!B30 -> Depreciation | C23: =Historical_FS!C30 -> 1377.17 | D23: =Historical_FS!D30 -> 1348.41 | E23: =Historical_FS!E30 -> 1847.93 | F23: =Historical_FS!F30 -> 2450.73 | G23: =Historical_FS!G30 -> 2722.66 | H23: =Historical_FS!H30 -> 2700.23 | I23: =Historical_FS!I30 -> 2714.75 | ... L23: =Historical_FS!L30 -> 4014.95
B24: =B23&" Growth" -> Depreciation Growth | C24: =IFERROR((C23/B23)-1,"-") -> - | D24: =IFERROR((D23/C23)-1,"-") -> -0.020883406 | E24: =IFERROR((E23/D23)-1,"-") -> 0.37045112 | F24: =IFERROR((F23/E23)-1,"-") -> 0.32620283 | G24: =IFERROR((G23/F23)-1,"-") -> 0.11095878 | H24: =IFERROR((H23/G23)-1,"-") -> -0.008238267 | I24: =IFERROR((I23/H23)-1,"-") -> 0.0053773197 | J24: =IFERROR((J23/I23)-1,"-") -> 0.063814348 | ... L24: =IFERROR((L23/K23)-1,"-") -> 0.27649191
B25: =Historical_FS!B33 -> EBIT | C25: =Historical_FS!C33 -> 3987.61 | D25: =Historical_FS!D33 -> 4512.15 | E25: =Historical_FS!E33 -> 4539.07 | F25: =Historical_FS!F33 -> 5246.31 | G25: =Historical_FS!G33 -> 7174.37 | H25: =Historical_FS!H33 -> 9486.2 | I25: =Historical_FS!I33 -> 9469.03 | ... L25: =Historical_FS!L33 -> 9178.67
B26: =B25&" Growth" -> EBIT Growth | C26: =IFERROR((C25/B25)-1,"-") -> - | D26: =IFERROR((D25/C25)-1,"-") -> 0.13154245 | E26: =IFERROR((E25/D25)-1,"-") -> 0.0059661137 | F26: =IFERROR((F25/E25)-1,"-") -> 0.15581165 | G26: =IFERROR((G25/F25)-1,"-") -> 0.36750783 | H26: =IFERROR((H25/G25)-1,"-") -> 0.32223457 | I26: =IFERROR((I25/H25)-1,"-") -> -0.0018099977 | J26: =IFERROR((J25/I25)-1,"-") -> -0.12990349 | ... L26: =IFERROR((L25/K25)-1,"-") -> -0.11660485
B27: =Historical_FS!B36 -> Interest | C27: =Historical_FS!C36 -> 566.3 | D27: =Historical_FS!D36 -> 640.1 | E27: =Historical_FS!E36 -> 1237.6 | F27: =Historical_FS!F36 -> 1777.86 | G27: =Historical_FS!G36 -> 1991.65 | H27: =Historical_FS!H36 -> 1485.65 | I27: =Historical_FS!I36 -> 944.71 | ... L27: =Historical_FS!L36 -> 1650.54
B28: =B27&" Growth" -> Interest Growth | C28: =IFERROR((C27/B27)-1,"-") -> - | D28: =IFERROR((D27/C27)-1,"-") -> 0.13031962 | E28: =IFERROR((E27/D27)-1,"-") -> 0.9334479 | F28: =IFERROR((F27/E27)-1,"-") -> 0.43653846 | G28: =IFERROR((G27/F27)-1,"-") -> 0.12025131 | H28: =IFERROR((H27/G27)-1,"-") -> -0.2540607 | I28: =IFERROR((I27/H27)-1,"-") -> -0.36410999 | J28: =IFERROR((J27/I27)-1,"-") -> -0.12912957 | ... L28: =IFERROR((L27/K27)-1,"-") -> 0.70510331
B29: =Historical_FS!B39 -> EBT | C29: =Historical_FS!C39 -> 3421.31 | D29: =Historical_FS!D39 -> 3872.05 | E29: =Historical_FS!E39 -> 3301.47 | F29: =Historical_FS!F39 -> 3468.45 | G29: =Historical_FS!G39 -> 5182.72 | H29: =Historical_FS!H39 -> 8000.55 | I29: =Historical_FS!I39 -> 8524.32 | ... L29: =Historical_FS!L39 -> 7528.13
B30: =B29&" Growth" -> EBT Growth | C30: =IFERROR((C29/B29)-1,"-") -> - | D30: =IFERROR((D29/C29)-1,"-") -> 0.13174486 | E30: =IFERROR((E29/D29)-1,"-") -> -0.14735863 | F30: =IFERROR((F29/E29)-1,"-") -> 0.05057747 | G30: =IFERROR((G29/F29)-1,"-") -> 0.49424671 | H30: =IFERROR((H29/G29)-1,"-") -> 0.54369713 | I30: =IFERROR((I29/H29)-1,"-") -> 0.065466749 | J30: =IFERROR((J29/I29)-1,"-") -> -0.12998925 | ... L30: =IFERROR((L29/K29)-1,"-") -> -0.20102375
B31: =Historical_FS!B42 -> Tax | C31: =Historical_FS!C42 -> 941.69 | D31: =Historical_FS!D42 -> 1158.54 | E31: =Historical_FS!E42 -> 1077.01 | F31: =Historical_FS!F42 -> 1068.07 | G31: =Historical_FS!G42 -> -568.16 | H31: =Historical_FS!H42 -> 2538.7 | I31: =Historical_FS!I42 -> 1190.06 | ... L31: =Historical_FS!L42 -> 1488.49
B32: =B31&" Growth" -> Tax Growth | C32: =IFERROR((C31/B31)-1,"-") -> - | D32: =IFERROR((D31/C31)-1,"-") -> 0.23027748 | E32: =IFERROR((E31/D31)-1,"-") -> -0.070373056 | F32: =IFERROR((F31/E31)-1,"-") -> -0.0083007586 | G32: =IFERROR((G31/F31)-1,"-") -> -1.5319502 | H32: =IFERROR((H31/G31)-1,"-") -> -5.4682836 | I32: =IFERROR((I31/H31)-1,"-") -> -0.53123252 | J32: =IFERROR((J31/I31)-1,"-") -> 0.96868225 | ... L32: =IFERROR((L31/K31)-1,"-") -> -0.38447892
B33: =Historical_FS!B45 -> Net Profit | C33: =Historical_FS!C45 -> 2479.62 | D33: =Historical_FS!D45 -> 2713.51 | E33: =Historical_FS!E45 -> 2224.46 | F33: =Historical_FS!F45 -> 2400.38 | G33: =Historical_FS!G45 -> 5750.88 | H33: =Historical_FS!H45 -> 5461.85 | I33: =Historical_FS!I45 -> 7334.26 | ... L33: =Historical_FS!L45 -> 6039.64
B34: =B33&" Growth" -> Net Profit Growth | C34: =IFERROR((C33/B33)-1,"-") -> - | D34: =IFERROR((D33/C33)-1,"-") -> 0.094324937 | E34: =IFERROR((E33/D33)-1,"-") -> -0.18022782 | F34: =IFERROR((F33/E33)-1,"-") -> 0.079084362 | G34: =IFERROR((G33/F33)-1,"-") -> 1.3958207 | H34: =IFERROR((H33/G33)-1,"-") -> -0.050258395 | I34: =IFERROR((I33/H33)-1,"-") -> 0.34281608 | J34: =IFERROR((J33/I33)-1,"-") -> -0.30826014 | ... L34: =IFERROR((L33/K33)-1,"-") -> -0.13768211
D35: =IFERROR(IF(AND(C33<0,D33>0),"Profit Swing",IF(AND(C33>0,D33<0),"Loss-Making",IF(C33=0,"-","-"))),0) -> -
B36: =Historical_FS!B50 -> Earnings Per Share | C36: =Historical_FS!C50 -> 90.36516 | D36: =Historical_FS!D50 -> 98.852823 | E36: =Historical_FS!E50 -> 81.007283 | F36: =Historical_FS!F50 -> 87.413693 | G36: =Historical_FS!G50 -> 199.26819 | H36: =Historical_FS!H50 -> 189.18774 | I36: =Historical_FS!I50 -> 254.04434 | ... L36: =Historical_FS!L50 -> 204.94197
B37: =B36&" Growth" -> Earnings Per Share Growth | C37: =IFERROR((C36/B36)-1,"-") -> - | D37: =IFERROR((D36/C36)-1,"-") -> 0.093926276 | E37: =IFERROR((E36/D36)-1,"-") -> -0.18052636 | F37: =IFERROR((F36/E36)-1,"-") -> 0.079084362 | G37: =IFERROR((G36/F36)-1,"-") -> 1.2795993 | H37: =IFERROR((H36/G36)-1,"-") -> -0.050587367 | I37: =IFERROR((I36/H36)-1,"-") -> 0.34281608 | J37: =IFERROR((J36/I36)-1,"-") -> -0.30826014 | ... L37: =IFERROR((L36/K36)-1,"-") -> -0.15523863
D38: =Historical_FS!D52 -> -
B39: =Historical_FS!B54 -> Dividend Per Share | C39: =Historical_FS!C54 -> 9.5010933 | D39: =Historical_FS!D54 -> 10.000364 | E39: =Historical_FS!E54 -> 10.500364 | F39: =Historical_FS!F54 -> 11.501821 | G39: =Historical_FS!G54 -> 13.001386 | H39: =Historical_FS!H54 -> 36.993419 | I39: =Historical_FS!I54 -> 37.99619 | ... L39: =Historical_FS!L54 -> 77.49474
B40: =B39&" Growth" -> Dividend Per Share Growth | C40: =IFERROR((C39/B39)-1,"-") -> - | D40: =IFERROR((D39/C39)-1,"-") -> 0.052548795 | E40: =IFERROR((E39/D39)-1,"-") -> 0.049998165 | F40: =IFERROR((F39/E39)-1,"-") -> 0.095373517 | G40: =IFERROR((G39/F39)-1,"-") -> 0.13037633 | H40: =IFERROR((H39/G39)-1,"-") -> 1.8453442 | I40: =IFERROR((I39/H39)-1,"-") -> 0.027106742 | J40: =IFERROR((J39/I39)-1,"-") -> 6.3813301e-05 | ... L40: =IFERROR((L39/K39)-1,"-") -> 0.10710607
A42: # | B42: Balance Sheet YoY Growth
B44: =Historical_FS!B61 -> Equity Share Capital | C44: =Historical_FS!C61 -> 274.43 | D44: =Historical_FS!D61 -> 274.51 | E44: =Historical_FS!E61 -> 274.61 | F44: =Historical_FS!F61 -> 274.64 | G44: =Historical_FS!G61 -> 288.63 | H44: =Historical_FS!H61 -> 288.65 | I44: =Historical_FS!I61 -> 288.67 | ... L44: =Historical_FS!L61 -> 294.68
B45: =B44&" Growth" -> Equity Share Capital Growth | C45: =IFERROR((C44/B44)-1,"-") -> - | D45: =IFERROR((D44/C44)-1,"-") -> 0.00029151332 | E45: =IFERROR((E44/D44)-1,"-") -> 0.00036428545 | F45: =IFERROR((F44/E44)-1,"-") -> 0.00010924584 | G45: =IFERROR((G44/F44)-1,"-") -> 0.050939412 | H45: =IFERROR((H44/G44)-1,"-") -> 6.9292866e-05 | I45: =IFERROR((I44/H44)-1,"-") -> 6.9288065e-05 | J45: =IFERROR((J44/I44)-1,"-") -> 6.9283265e-05 | ... L45: =IFERROR((L44/K44)-1,"-") -> 0.0207489
B46: =Historical_FS!B62 -> Reserves | C46: =Historical_FS!C62 -> 21671.2 | D46: =Historical_FS!D62 -> 24117.38 | E46: =Historical_FS!E62 -> 26106.55 | F46: =Historical_FS!F62 -> 33476.01 | G46: =Historical_FS!G62 -> 38755.13 | H46: =Historical_FS!H62 -> 43886.03 | I46: =Historical_FS!I62 -> 50146.6 | ... L46: =Historical_FS!L62 -> 70412.09
B47: =B46&" Growth" -> Reserves Growth | C47: =IFERROR((C46/B46)-1,"-") -> - | D47: =IFERROR((D46/C46)-1,"-") -> 0.112877 | E47: =IFERROR((E46/D46)-1,"-") -> 0.082478694 | F47: =IFERROR((F46/E46)-1,"-") -> 0.28228395 | G47: =IFERROR((G46/F46)-1,"-") -> 0.1576986 | H47: =IFERROR((H46/G46)-1,"-") -> 0.1323928 | I47: =IFERROR((I46/H46)-1,"-") -> 0.14265519 | J47: =IFERROR((J46/I46)-1,"-") -> 0.077557601 | ... L47: =IFERROR((L46/K46)-1,"-") -> 0.17473326
B48: Total Equity | C48: =IFERROR(C44+C46,0) -> 21945.63 | D48: =IFERROR(D44+D46,0) -> 24391.89 | E48: =IFERROR(E44+E46,0) -> 26381.16 | F48: =IFERROR(F44+F46,0) -> 33750.65 | G48: =IFERROR(G44+G46,0) -> 39043.76 | H48: =IFERROR(H44+H46,0) -> 44174.68 | I48: =IFERROR(I44+I46,0) -> 50435.27 | J48: =IFERROR(J44+J46,0) -> 54324.54 | ... L48: =IFERROR(L44+L46,0) -> 70706.77
B49: =B48&" Growth" -> Total Equity Growth | C49: =IFERROR((C48/B48)-1,"-") -> - | D49: =IFERROR((D48/C48)-1,"-") -> 0.11146912 | E49: =IFERROR((E48/D48)-1,"-") -> 0.081554566 | F49: =IFERROR((F48/E48)-1,"-") -> 0.2793467 | G49: =IFERROR((G48/F48)-1,"-") -> 0.15682987 | H49: =IFERROR((H48/G48)-1,"-") -> 0.1314146 | I49: =IFERROR((I48/H48)-1,"-") -> 0.14172349 | J49: =IFERROR((J48/I48)-1,"-") -> 0.077114091 | ... L49: =IFERROR((L48/K48)-1,"-") -> 0.17399516
B50: =Historical_FS!B63 -> Borrowings | C50: =Historical_FS!C63 -> 10615.99 | D50: =Historical_FS!D63 -> 8474.49 | E50: =Historical_FS!E63 -> 19480.22 | F50: =Historical_FS!F63 -> 25337 | G50: =Historical_FS!G63 -> 23018.96 | H50: =Historical_FS!H63 -> 21719.39 | I50: =Historical_FS!I63 -> 11298.8 | ... L50: =Historical_FS!L63 -> 24102.18
B51: =B50&" Growth" -> Borrowings Growth | C51: =IFERROR((C50/B50)-1,"-") -> - | D51: =IFERROR((D50/C50)-1,"-") -> -0.201724 | E51: =IFERROR((E50/D50)-1,"-") -> 1.2986894 | F51: =IFERROR((F50/E50)-1,"-") -> 0.30065266 | G51: =IFERROR((G50/F50)-1,"-") -> -0.091488337 | H51: =IFERROR((H50/G50)-1,"-") -> -0.056456504 | I51: =IFERROR((I50/H50)-1,"-") -> -0.47978281 | J51: =IFERROR((J50/I50)-1,"-") -> -0.021335009 | ... L51: =IFERROR((L50/K50)-1,"-") -> 1.1136794
B52: =Historical_FS!B64 -> Other Liabilities | C52: =Historical_FS!C64 -> 8631.49 | D52: =Historical_FS!D64 -> 9342.73 | E52: =Historical_FS!E64 -> 11279.71 | F52: =Historical_FS!F64 -> 17437.72 | G52: =Historical_FS!G64 -> 17151.09 | H52: =Historical_FS!H64 -> 20282.28 | I52: =Historical_FS!I64 -> 22077.37 | ... L52: =Historical_FS!L64 -> 38823.11
B53: =B52&" Growth" -> Other Liabilities Growth | C53: =IFERROR((C52/B52)-1,"-") -> - | D53: =IFERROR((D52/C52)-1,"-") -> 0.082400605 | E53: =IFERROR((E52/D52)-1,"-") -> 0.20732484 | F53: =IFERROR((F52/E52)-1,"-") -> 0.54593691 | G53: =IFERROR((G52/F52)-1,"-") -> -0.016437355 | H53: =IFERROR((H52/G52)-1,"-") -> 0.18256507 | I53: =IFERROR((I52/H52)-1,"-") -> 0.088505336 | J53: =IFERROR((J52/I52)-1,"-") -> 0.17759135 | ... L53: =IFERROR((L52/K52)-1,"-") -> 0.33107745
B54: Total Debt | C54: =IFERROR(C50+C52,0) -> 19247.48 | D54: =IFERROR(D50+D52,0) -> 17817.22 | E54: =IFERROR(E50+E52,0) -> 30759.93 | F54: =IFERROR(F50+F52,0) -> 42774.72 | G54: =IFERROR(G50+G52,0) -> 40170.05 | H54: =IFERROR(H50+H52,0) -> 42001.67 | I54: =IFERROR(I50+I52,0) -> 33376.17 | J54: =IFERROR(J50+J52,0) -> 37055.86 | ... L54: =IFERROR(L50+L52,0) -> 62925.29
B55: =B54&" Growth" -> Total Debt Growth | C55: =IFERROR((C54/B54)-1,"-") -> - | D55: =IFERROR((D54/C54)-1,"-") -> -0.074308948 | E55: =IFERROR((E54/D54)-1,"-") -> 0.72641579 | F55: =IFERROR((F54/E54)-1,"-") -> 0.39059874 | G55: =IFERROR((G54/F54)-1,"-") -> -0.060892742 | H55: =IFERROR((H54/G54)-1,"-") -> 0.045596657 | I55: =IFERROR((I54/H54)-1,"-") -> -0.20536088 | J55: =IFERROR((J54/I54)-1,"-") -> 0.11024902 | ... L55: =IFERROR((L54/K54)-1,"-") -> 0.55104422
B56: =Historical_FS!B68 -> Net Block | C56: =Historical_FS!C68 -> 25309.42 | D56: =Historical_FS!D68 -> 25903.75 | E56: =Historical_FS!E68 -> 39715.3 | F56: =Historical_FS!F68 -> 56644.62 | G56: =Historical_FS!G68 -> 57150.96 | H56: =Historical_FS!H68 -> 55411.61 | I56: =Historical_FS!I68 -> 55487.57 | ... L56: =Historical_FS!L68 -> 94564.22
B57: =B56&" Growth" -> Net Block Growth | C57: =IFERROR((C56/B56)-1,"-") -> - | D57: =IFERROR((D56/C56)-1,"-") -> 0.023482561 | E57: =IFERROR((E56/D56)-1,"-") -> 0.53318728 | F57: =IFERROR((F56/E56)-1,"-") -> 0.42626696 | G57: =IFERROR((G56/F56)-1,"-") -> 0.0089388895 | H57: =IFERROR((H56/G56)-1,"-") -> -0.030434309 | I57: =IFERROR((I56/H56)-1,"-") -> 0.0013708319 | J57: =IFERROR((J56/I56)-1,"-") -> 0.073735974 | ... L57: =IFERROR((L56/K56)-1,"-") -> 0.50394107
B58: =Historical_FS!B69 -> Capital Work in Progress | C58: =Historical_FS!C69 -> 1469.09 | D58: =Historical_FS!D69 -> 921.48 | E58: =Historical_FS!E69 -> 1511.21 | F58: =Historical_FS!F69 -> 1153.32 | G58: =Historical_FS!G69 -> 919.59 | H58: =Historical_FS!H69 -> 1686.68 | I58: =Historical_FS!I69 -> 4784.67 | ... L58: =Historical_FS!L69 -> 6234.19
B59: =B58&" Growth" -> Capital Work in Progress Growth | C59: =IFERROR((C58/B58)-1,"-") -> - | D59: =IFERROR((D58/C58)-1,"-") -> -0.37275456 | E59: =IFERROR((E58/D58)-1,"-") -> 0.63998133 | F59: =IFERROR((F58/E58)-1,"-") -> -0.23682347 | G59: =IFERROR((G58/F58)-1,"-") -> -0.20265841 | H59: =IFERROR((H58/G58)-1,"-") -> 0.83416523 | I59: =IFERROR((I58/H58)-1,"-") -> 1.8367384 | J59: =IFERROR((J58/I58)-1,"-") -> -0.15555514 | ... L59: =IFERROR((L58/K58)-1,"-") -> -0.084712194
B60: =Historical_FS!B70 -> Investments | C60: =Historical_FS!C70 -> 5095.18 | D60: =Historical_FS!D70 -> 6690.51 | E60: =Historical_FS!E70 -> 5446.9 | F60: =Historical_FS!F70 -> 2921.33 | G60: =Historical_FS!G70 -> 5928.69 | H60: =Historical_FS!H70 -> 12178.11 | I60: =Historical_FS!I70 -> 6335.77 | ... L60: =Historical_FS!L70 -> 5156.47
B61: =B60&" Growth" -> Investments Growth | C61: =IFERROR((C60/B60)-1,"-") -> - | D61: =IFERROR((D60/C60)-1,"-") -> 0.31310572 | E61: =IFERROR((E60/D60)-1,"-") -> -0.18587671 | F61: =IFERROR((F60/E60)-1,"-") -> -0.46367108 | G61: =IFERROR((G60/F60)-1,"-") -> 1.0294489 | H61: =IFERROR((H60/G60)-1,"-") -> 1.054098 | I61: =IFERROR((I60/H60)-1,"-") -> -0.47974111 | J61: =IFERROR((J60/I60)-1,"-") -> 0.1517069 | ... L61: =IFERROR((L60/K60)-1,"-") -> -0.37489377
B62: =Historical_FS!B71 -> Other Assets | C62: =Historical_FS!C71 -> 2669.67 | D62: =Historical_FS!D71 -> 2286.86 | E62: =Historical_FS!E71 -> 4760.39 | F62: =Historical_FS!F71 -> 8180.43 | G62: =Historical_FS!G71 -> 8108.09 | H62: =Historical_FS!H71 -> 8302.7 | I62: =Historical_FS!I71 -> 8177.06 | ... L62: =Historical_FS!L71 -> 10550.63
B63: =B62&" Growth" -> Other Assets Growth | C63: =IFERROR((C62/B62)-1,"-") -> - | D63: =IFERROR((D62/C62)-1,"-") -> -0.14339225 | E63: =IFERROR((E62/D62)-1,"-") -> 1.0816272 | F63: =IFERROR((F62/E62)-1,"-") -> 0.71843693 | G63: =IFERROR((G62/F62)-1,"-") -> -0.0088430559 | H63: =IFERROR((H62/G62)-1,"-") -> 0.024001954 | I63: =IFERROR((I62/H62)-1,"-") -> -0.015132427 | J63: =IFERROR((J62/I62)-1,"-") -> 0.080537504 | ... L63: =IFERROR((L62/K62)-1,"-") -> 0.11431562
B64: =Historical_FS!B72 -> Total Non Current Assets | C64: =Historical_FS!C72 -> 34543.36 | D64: =Historical_FS!D72 -> 35802.6 | E64: =Historical_FS!E72 -> 51433.8 | F64: =Historical_FS!F72 -> 68899.7 | G64: =Historical_FS!G72 -> 72107.33 | H64: =Historical_FS!H72 -> 77579.1 | I64: =Historical_FS!I72 -> 74785.07 | ... L64: =Historical_FS!L72 -> 116505.51
B65: =B64&" Growth" -> Total Non Current Assets Growth | C65: =IFERROR((C64/B64)-1,"-") -> - | D65: =IFERROR((D64/C64)-1,"-") -> 0.036453894 | E65: =IFERROR((E64/D64)-1,"-") -> 0.43659399 | F65: =IFERROR((F64/E64)-1,"-") -> 0.3395802 | G65: =IFERROR((G64/F64)-1,"-") -> 0.046555065 | H65: =IFERROR((H64/G64)-1,"-") -> 0.075883686 | I65: =IFERROR((I64/H64)-1,"-") -> -0.036015241 | J65: =IFERROR((J64/I64)-1,"-") -> 0.066415529 | ... L65: =IFERROR((L64/K64)-1,"-") -> 0.33292348
B66: =Historical_FS!B75 -> Receivables | C66: =Historical_FS!C75 -> 1928.21 | D66: =Historical_FS!D75 -> 1757.09 | E66: =Historical_FS!E75 -> 2220.63 | F66: =Historical_FS!F75 -> 2787.03 | G66: =Historical_FS!G75 -> 2383.22 | H66: =Historical_FS!H75 -> 2571.73 | I66: =Historical_FS!I75 -> 3071.61 | ... L66: =Historical_FS!L75 -> 5890.25
B67: =B66&" Growth" -> Receivables Growth | C67: =IFERROR((C66/B66)-1,"-") -> - | D67: =IFERROR((D66/C66)-1,"-") -> -0.08874552 | E67: =IFERROR((E66/D66)-1,"-") -> 0.26381119 | F67: =IFERROR((F66/E66)-1,"-") -> 0.25506275 | G67: =IFERROR((G66/F66)-1,"-") -> -0.144889 | H67: =IFERROR((H66/G66)-1,"-") -> 0.079098866 | I67: =IFERROR((I66/H66)-1,"-") -> 0.19437499 | J67: =IFERROR((J66/I66)-1,"-") -> 0.2589554 | ... L67: =IFERROR((L66/K66)-1,"-") -> 0.37681854
B68: =Historical_FS!B76 -> Inventory | C68: =Historical_FS!C76 -> 2454.58 | D68: =Historical_FS!D76 -> 2400.64 | E68: =Historical_FS!E76 -> 3267.59 | F68: =Historical_FS!F76 -> 4098.96 | G68: =Historical_FS!G76 -> 4183.35 | H68: =Historical_FS!H76 -> 4017.97 | I68: =Historical_FS!I76 -> 5595.58 | ... L68: =Historical_FS!L76 -> 9562.98
B69: =B68&" Growth" -> Inventory Growth | C69: =IFERROR((C68/B68)-1,"-") -> - | D69: =IFERROR((D68/C68)-1,"-") -> -0.021975246 | E69: =IFERROR((E68/D68)-1,"-") -> 0.36113286 | F69: =IFERROR((F68/E68)-1,"-") -> 0.25442911 | G69: =IFERROR((G68/F68)-1,"-") -> 0.020588149 | H69: =IFERROR((H68/G68)-1,"-") -> -0.03953291 | I69: =IFERROR((I68/H68)-1,"-") -> 0.39263857 | J69: =IFERROR((J68/I68)-1,"-") -> 0.18161656 | ... L69: =IFERROR((L68/K68)-1,"-") -> 0.14805264
B70: =Historical_FS!B77 -> Cash & Bank | C70: =Historical_FS!C77 -> 2266.96 | D70: =Historical_FS!D77 -> 2248.78 | E70: =Historical_FS!E77 -> 219.07 | F70: =Historical_FS!F77 -> 739.68 | G70: =Historical_FS!G77 -> 539.91 | H70: =Historical_FS!H77 -> 2007.55 | I70: =Historical_FS!I77 -> 359.18 | ... L70: =Historical_FS!L77 -> 1673.32
B71: =B70&" Growth" -> Cash & Bank Growth | C71: =IFERROR((C70/B70)-1,"-") -> - | D71: =IFERROR((D70/C70)-1,"-") -> -0.0080195504 | E71: =IFERROR((E70/D70)-1,"-") -> -0.90258273 | F71: =IFERROR((F70/E70)-1,"-") -> 2.376455 | G71: =IFERROR((G70/F70)-1,"-") -> -0.27007625 | H71: =IFERROR((H70/G70)-1,"-") -> 2.7183049 | I71: =IFERROR((I70/H70)-1,"-") -> -0.8210854 | J71: =IFERROR((J70/I70)-1,"-") -> 2.2005958 | ... L71: =IFERROR((L70/K70)-1,"-") -> 1.1364896
B72: =Historical_FS!B78 -> Total Current Assets | C72: =Historical_FS!C78 -> 6649.75 | D72: =Historical_FS!D78 -> 6406.51 | E72: =Historical_FS!E78 -> 5707.29 | F72: =Historical_FS!F78 -> 7625.67 | G72: =Historical_FS!G78 -> 7106.48 | H72: =Historical_FS!H78 -> 8597.25 | I72: =Historical_FS!I78 -> 9026.37 | ... L72: =Historical_FS!L78 -> 17126.55
B73: =B72&" Growth" -> Total Current Assets Growth | C73: =IFERROR((C72/B72)-1,"-") -> - | D73: =IFERROR((D72/C72)-1,"-") -> -0.036578819 | E73: =IFERROR((E72/D72)-1,"-") -> -0.10914211 | F73: =IFERROR((F72/E72)-1,"-") -> 0.336128 | G73: =IFERROR((G72/F72)-1,"-") -> -0.068084509 | H73: =IFERROR((H72/G72)-1,"-") -> 0.20977615 | I73: =IFERROR((I72/H72)-1,"-") -> 0.049913635 | J73: =IFERROR((J72/I72)-1,"-") -> 0.28827425 | ... L73: =IFERROR((L72/K72)-1,"-") -> 0.27894924
B75: =Historical_FS!B80 -> Total Assets | C75: =Historical_FS!C80 -> 41193.11 | D75: =Historical_FS!D80 -> 42209.11 | E75: =Historical_FS!E80 -> 57141.09 | F75: =Historical_FS!F80 -> 76525.37 | G75: =Historical_FS!G80 -> 79213.81 | H75: =Historical_FS!H80 -> 86176.35 | I75: =Historical_FS!I80 -> 83811.44 | ... L75: =Historical_FS!L80 -> 133632.06
B76: =B75&" Growth" -> Total Assets Growth | C76: =IFERROR((C75/B75)-1,"-") -> - | D76: =IFERROR((D75/C75)-1,"-") -> 0.024664319 | E76: =IFERROR((E75/D75)-1,"-") -> 0.35376202 | F76: =IFERROR((F75/E75)-1,"-") -> 0.33923539 | G76: =IFERROR((G75/F75)-1,"-") -> 0.035131356 | H76: =IFERROR((H75/G75)-1,"-") -> 0.087895532 | I76: =IFERROR((I75/H75)-1,"-") -> -0.02744268 | J76: =IFERROR((J75/I75)-1,"-") -> 0.09030939 | ... L76: =IFERROR((L75/K75)-1,"-") -> 0.32575289
A78: # | B78: Cash Flow Statement YoY Growth
B80: =Historical_FS!B86 -> Cash from Operating Activity | C80: =Historical_FS!C86 -> 4525 | D80: =Historical_FS!D86 -> 5005 | E80: =Historical_FS!E86 -> 3888 | F80: =Historical_FS!F86 -> 5956 | G80: =Historical_FS!G86 -> 8973 | H80: =Historical_FS!H86 -> 12500 | I80: =Historical_FS!I86 -> 9283 | ... L80: =Historical_FS!L86 -> 10673
B81: =B80&" Growth" -> Cash from Operating Activity Growth | C81: =IFERROR((C80/B80)-1,"-") -> - | D81: =IFERROR((D80/C80)-1,"-") -> 0.10607735 | E81: =IFERROR((E80/D80)-1,"-") -> -0.22317682 | F81: =IFERROR((F80/E80)-1,"-") -> 0.531893 | G81: =IFERROR((G80/F80)-1,"-") -> 0.50654802 | H81: =IFERROR((H80/G80)-1,"-") -> 0.39306809 | I81: =IFERROR((I80/H80)-1,"-") -> -0.25736 | J81: =IFERROR((J80/I80)-1,"-") -> -0.023052892 | ... L81: =IFERROR((L80/K80)-1,"-") -> -0.020556116
B82: =Historical_FS!B97 -> Cash from Investing Activity | C82: =Historical_FS!C97 -> -3675 | D82: =Historical_FS!D97 -> -2501 | E82: =Historical_FS!E97 -> 1866 | F82: =Historical_FS!F97 -> 1164 | G82: =Historical_FS!G97 -> -4193 | H82: =Historical_FS!H97 -> -8856 | I82: =Historical_FS!I97 -> 2322 | ... L82: =Historical_FS!L97 -> -15835
B83: =B82&" Growth" -> Cash from Investing Activity Growth | C83: =IFERROR((C82/B82)-1,"-") -> - | D83: =IFERROR((D82/C82)-1,"-") -> -0.31945578 | E83: =IFERROR((E82/D82)-1,"-") -> -1.7461016 | F83: =IFERROR((F82/E82)-1,"-") -> -0.37620579 | G83: =IFERROR((G82/F82)-1,"-") -> -4.6022337 | H83: =IFERROR((H82/G82)-1,"-") -> 1.1120916 | I83: =IFERROR((I82/H82)-1,"-") -> -1.2621951 | J83: =IFERROR((J82/I82)-1,"-") -> -4.0951766 | ... L83: =IFERROR((L82/K82)-1,"-") -> 0.80188894
B84: =Historical_FS!B110 -> Cash from Financing Activity | C84: =Historical_FS!C110 -> -843 | D84: =Historical_FS!D110 -> -2535 | E84: =Historical_FS!E110 -> -5735 | F84: =Historical_FS!F110 -> -6757 | G84: =Historical_FS!G110 -> -5076 | H84: =Historical_FS!H110 -> -4356 | I84: =Historical_FS!I110 -> -12497 | ... L84: =Historical_FS!L110 -> 5076
B85: =B84&" Growth" -> Cash from Financing Activity Growth | C85: =IFERROR((C84/B84)-1,"-") -> - | D85: =IFERROR((D84/C84)-1,"-") -> 2.0071174 | E85: =IFERROR((E84/D84)-1,"-") -> 1.2623274 | F85: =IFERROR((F84/E84)-1,"-") -> 0.17820401 | G85: =IFERROR((G84/F84)-1,"-") -> -0.24877904 | H85: =IFERROR((H84/G84)-1,"-") -> -0.14184397 | I85: =IFERROR((I84/H84)-1,"-") -> 1.8689164 | J85: =IFERROR((J84/I84)-1,"-") -> -0.86948868 | ... L85: =IFERROR((L84/K84)-1,"-") -> -3.6368831
B86: =Historical_FS!B119 -> Net Cash Flow | C86: =Historical_FS!C119 -> 7 | D86: =Historical_FS!D119 -> -31 | E86: =Historical_FS!E119 -> 19 | F86: =Historical_FS!F119 -> 363 | G86: =Historical_FS!G119 -> -296 | H86: =Historical_FS!H119 -> -712 | I86: =Historical_FS!I119 -> -892 | ... L86: =Historical_FS!L119 -> -86
B87: =B86&" Growth" -> Net Cash Flow Growth | C87: =IFERROR((C86/B86)-1,"-") -> - | D87: =IFERROR((D86/C86)-1,"-") -> -5.4285714 | E87: =IFERROR((E86/D86)-1,"-") -> -1.6129032 | F87: =IFERROR((F86/E86)-1,"-") -> 18.105263 | G87: =IFERROR((G86/F86)-1,"-") -> -1.815427 | H87: =IFERROR((H86/G86)-1,"-") -> 1.4054054 | I87: =IFERROR((I86/H86)-1,"-") -> 0.25280899 | J87: =IFERROR((J86/I86)-1,"-") -> -1.2813901 | ... L87: =IFERROR((L86/K86)-1,"-") -> -1.4673913

Sheet Forecasting
B7: Sales Forecasting | F7: EBITDA Forecasting | J7: EPS Forecasting

Sheet WACC
B9: Figures are in INR Crore
B11: Peer Comps
G12: Debt/ | H12: Debt/ | I12: Levered | J12: Unlevered
B13: Name | C13: Country | D13: Total Debt | E13: Total Equity | F13: Tax Rate1 | G13: Equity | H13: Capital | I13: Beta2 | J13: Beta3
B15: UltraTech Cem. | C15: India | D15: 25214.91 | E15: 363976.05 | F15: 0.2517 | G15: =D15/E15 -> 0.069276289 | H15: =D15/(D15+E15) -> 0.064788016 | I15: =UltraTech_Beta!J16 -> 1.19958 | J15: =I15/(1+(1-F15)*G15) -> 1.1404592
B16: Grasim Inds | C16: India | D16: 186325.56 | E16: 195247.41 | F16: =$F$15 -> 0.2517 | G16: =D16/E16 -> 0.9543049 | H16: =D16/(D16+E16) -> 0.48830912 | I16: =Grasim_Beta!J15 -> 0.99646396 | J16: =I16/(1+(1-F16)*G16) -> 0.58133146
B17: Ambuja Cements | C17: India | D17: 788.5 | E17: 140263.58 | F17: =$F$15 -> 0.2517 | G17: =D17/E17 -> 0.0056215591 | H17: =D17/(D17+E17) -> 0.0055901338 | I17: =Ambuja_Beta!J15 -> 1.0537211 | J17: =I17/(1+(1-F17)*G17) -> 1.0493071
B18: Shree Cement | C18: India | D18: 1046.13 | E18: 104451.6 | F18: =$F$15 -> 0.2517 | G18: =D18/E18 -> 0.010015452 | H18: =D18/(D18+E18) -> 0.0099161375 | I18: =ShreeC_Beta!J15 -> 0.85573404 | J18: =I18/(1+(1-F18)*G18) -> 0.84936839
B19: J K Cements | C19: India | D19: 6028.23 | E19: 49938.35 | F19: =$F$15 -> 0.2517 | G19: =D19/E19 -> 0.12071344 | H19: =D19/(D19+E19) -> 0.10771124 | I19: =JKC_Beta!J15 -> 1.0746142 | J19: =I19/(1+(1-F19)*G19) -> 0.98558629
E21: Average | F21: =AVERAGE(F15:F19) -> 0.2517 | G21: =AVERAGE(G15:G19) -> 0.23198633 | H21: =AVERAGE(H15:H19) -> 0.13526293 | I21: =AVERAGE(I15:I19) -> 1.0360226 | J21: =AVERAGE(J15:J19) -> 0.92121048
E22: Median | F22: =MEDIAN(F15:F19) -> 0.2517 | G22: =MEDIAN(G15:G19) -> 0.069276289 | H22: =MEDIAN(H15:H19) -> 0.064788016 | I22: =MEDIAN(I15:I19) -> 1.0537211 | J22: =MEDIAN(J15:J19) -> 0.98558629
B25: Cost of Debt | G25: Cost of Equity
B27: Pre-tax Cost of Debt | E27: =RM!G13/D15 -> 0.065458889 | G27: Risk Free Rate | J27: =6.53%-2.18% -> 0.0435
B28: Tax Rate | E28: =F15 -> 0.2517 | G28: Equity Risk Premium | J28: =RM!G11-WACC!J27 -> 0.086961915
B29: Post-tax Cost of Debt | E29: =E27*(1-E28) -> 0.048982887 | G29: Levered Beta | J29: =J38 -> 1.1009489
G30: Cost of Equity | J30: =J27+J28*J29 -> 0.13924063
B33: Capital Structure | G33: Levered Beta
D35: Current | E35: Target | G35: Comps Median Unlevered Beta | J35: =J22 -> 0.98558629
B36: Total Debt | C36: =D15 -> 25214.91 | D36: =C36/$C$38 -> 0.064788016 | E36: =H21 -> 0.13526293 | G36: Target Debt / Equity | J36: =E40 -> 0.15642088
B37: Market Capitalization | C37: =E15 -> 363976.05 | D37: =C37/$C$38 -> 0.93521198 | E37: =E38-E36 -> 0.86473707 | G37: Tax Rate | J37: =F15 -> 0.2517
B38: Total Capitalization | C38: =SUM(C36:C37) -> 389190.96 | D38: =SUM(D36:D37) -> 1 | E38: =D38 -> 1 | G38: Levered Beta | J38: =J35*(1+(1-J37)*J36) -> 1.1009489
B40: Debt / Equity | D40: =D36/D37 -> 0.069276289 | E40: =E36/E37 -> 0.15642088 | G40: Weighted Average Cost of Capital
G42: Cost of Debt | J42: =E29 -> 0.048982887
B43: Assumptions: | G43: Weight of Debt | J43: =E36 -> 0.13526293
B44: 1). Tax Rate is considered as Marginal Tax Rate of the Country
B45: 2). Levered Beta is based on 2 Year Weekly data | G45: Cost of Equity | J45: =J30 -> 0.13924063
B46: 3). Unlevered Beta = Levered Beta/(1+(1-Tax Rate)*Debt-to-Equity) | G46: Weight of Equity | J46: =E37 -> 0.86473707
B47: 4). Risk Free Rate = 10Y G-Sec yield (6.53%) less India sovereign default spread
B48: (2.18%) = 4.35%, following Prof. Damodaran's default-spread adjusted Rf methodology | G48: WACC | J48: =(J42*J43)+(J45*J46) -> 0.1270321
B49: 5). Source of Data is Screener.in & Investing.com
B50: 6). ERP = Geometric mean Nifty 50 returns (2000–2025) of 11.70% + Dividend yield 1.35% − Rf 4.35% = 8.70%. Source: NSE historical data

Sheet Intrinsic_Growth
B9: Figures are in INR Crore
B11: Calculation of ROIC | G11: ='Raw FS'!H2 -> 44256 | H11: ='Raw FS'!I2 -> 44621 | I11: ='Raw FS'!J2 -> 44986 | J11: ='Raw FS'!K2 -> 45352 | K11: ='Raw FS'!L2 -> 45717
B13: Current Assets
B14: ='Raw FS'!B49 -> Inventories | G14: ='Raw FS'!H49 -> 4018 | H14: ='Raw FS'!I49 -> 5596 | I14: ='Raw FS'!J49 -> 6612 | J14: ='Raw FS'!K49 -> 8330 | K14: ='Raw FS'!L49 -> 9563
B15: ='Raw FS'!B50 -> Trade receivables | G15: ='Raw FS'!H50 -> 2572 | H15: ='Raw FS'!I50 -> 3072 | I15: ='Raw FS'!J50 -> 3867 | J15: ='Raw FS'!K50 -> 4278 | K15: ='Raw FS'!L50 -> 5890
B16: ='Raw FS'!B52 -> Loans n Advances | G16: ='Raw FS'!H52 -> 660 | H16: ='Raw FS'!I52 -> 873 | I16: ='Raw FS'!J52 -> 951 | J16: ='Raw FS'!K52 -> 985 | K16: ='Raw FS'!L52 -> 1259
B17: ='Raw FS'!B53 -> Other asset items | G17: ='Raw FS'!H53 -> 7642 | H17: ='Raw FS'!I53 -> 7304 | I17: ='Raw FS'!J53 -> 7885 | J17: ='Raw FS'!K53 -> 8483 | K17: ='Raw FS'!L53 -> 9292
B18: Total Current Assets | G18: =SUM(G14:G17) -> 14892 | H18: =SUM(H14:H17) -> 16845 | I18: =SUM(I14:I17) -> 19315 | J18: =SUM(J14:J17) -> 22076 | K18: =SUM(K14:K17) -> 26004
B20: Current Liabilities
B21: ='Raw FS'!B28 -> Trade Payables | G21: ='Raw FS'!H28 -> 4548 | H21: ='Raw FS'!I28 -> 5863 | I21: ='Raw FS'!J28 -> 7209 | J21: ='Raw FS'!K28 -> 8478 | K21: ='Raw FS'!L28 -> 9327
B22: ='Raw FS'!B29 -> Advance from Customers | G22: ='Raw FS'!H29 -> 415 | H22: ='Raw FS'!I29 -> 465 | I22: ='Raw FS'!J29 -> 384 | J22: ='Raw FS'!K29 -> 527 | K22: ='Raw FS'!L29 -> 541
B23: ='Raw FS'!B30 -> Other liability items | G23: ='Raw FS'!H30 -> 15313 | H23: ='Raw FS'!I30 -> 15753 | I23: ='Raw FS'!J30 -> 18349 | J23: ='Raw FS'!K30 -> 20106 | K23: ='Raw FS'!L30 -> 25768
B24: Total Current Liabilities | G24: =SUM(G21:G23) -> 20276 | H24: =SUM(H21:H23) -> 22081 | I24: =SUM(I21:I23) -> 25942 | J24: =SUM(J21:J23) -> 29111 | K24: =SUM(K21:K23) -> 35636
A26: # | B26: Net Working Capital | G26: =G18-G24 -> -5384 | H26: =H18-H24 -> -5236 | I26: =I18-I24 -> -6627 | J26: =J18-J24 -> -7035 | K26: =K18-K24 -> -9632
B28: Non-Current Assets
B29: Land | G29: ='Raw FS'!H34 -> 8085 | H29: ='Raw FS'!I34 -> 8454 | I29: ='Raw FS'!J34 -> 8709 | J29: ='Raw FS'!K34 -> 9259 | K29: ='Raw FS'!L34 -> 19872
B30: Building | G30: ='Raw FS'!H35 -> 5606 | H30: ='Raw FS'!I35 -> 5831 | I30: ='Raw FS'!J35 -> 6287 | J30: ='Raw FS'!K35 -> 6772 | K30: ='Raw FS'!L35 -> 9361
B31: Plant Machinery | G31: ='Raw FS'!H36 -> 38655 | H31: ='Raw FS'!I36 -> 40604 | I31: ='Raw FS'!J36 -> 46270 | J31: ='Raw FS'!K36 -> 51343 | K31: ='Raw FS'!L36 -> 67010
B32: Ships Vessels | G32: ='Raw FS'!H37 -> 830 | H32: ='Raw FS'!I37 -> 719 | I32: ='Raw FS'!J37 -> 793 | J32: ='Raw FS'!K37 -> 801 | K32: ='Raw FS'!L37 -> 792
B33: Equipments | G33: ='Raw FS'!H38 -> 289 | H33: ='Raw FS'!I38 -> 336 | I33: ='Raw FS'!J38 -> 387 | J33: ='Raw FS'!K38 -> 466 | K33: ='Raw FS'!L38 -> 555
B34: Furniture n fittings | G34: ='Raw FS'!H39 -> 111 | H34: ='Raw FS'!I39 -> 114 | I34: ='Raw FS'!J39 -> 122 | J34: ='Raw FS'!K39 -> 154 | K34: ='Raw FS'!L39 -> 219
B35: Railway sidings | G35: ='Raw FS'!H40 -> 959 | H35: ='Raw FS'!I40 -> 989 | I35: ='Raw FS'!J40 -> 1008 | J35: ='Raw FS'!K40 -> 1088 | K35: ='Raw FS'!L40 -> 1305
B36: Vehicles | G36: ='Raw FS'!H41 -> 133 | H36: ='Raw FS'!I41 -> 163 | I36: ='Raw FS'!J41 -> 200 | J36: ='Raw FS'!K41 -> 260 | K36: ='Raw FS'!L41 -> 354
B37: Intangible Assets | G37: ='Raw FS'!H42 -> 6375 | H37: ='Raw FS'!I42 -> 6405 | I37: ='Raw FS'!J42 -> 6484 | J37: ='Raw FS'!K42 -> 6501 | K37: ='Raw FS'!L42 -> 8108
B38: Other fixed assets | G38: ='Raw FS'!H43 -> 6289 | H38: ='Raw FS'!I43 -> 6387 | I38: ='Raw FS'!J43 -> 6695 | J38: ='Raw FS'!K43 -> 6637 | K38: ='Raw FS'!L43 -> 11055
B39: Gross Block | G39: =SUM(G29:G38) -> 67332 | H39: =SUM(H29:H38) -> 70002 | I39: =SUM(I29:I38) -> 76955 | J39: =SUM(J29:J38) -> 83281 | K39: =SUM(K29:K38) -> 118631
B40: Accumulated Dep. | G40: ='Raw FS'!H45 -> 11921 | H40: ='Raw FS'!I45 -> 14514 | I40: ='Raw FS'!J45 -> 17378 | J40: ='Raw FS'!K45 -> 20403 | K40: ='Raw FS'!L45 -> 24067
A41: # | B41: Net Non-Current Assets | G41: =G39-G40 -> 55411 | H41: =H39-H40 -> 55488 | I41: =I39-I40 -> 59577 | J41: =J39-J40 -> 62878 | K41: =K39-K40 -> 94564
A43: # | B43: Invested Capital | G43: =G41+G26 -> 50027 | H43: =H41+H26 -> 50252 | I43: =I41+I26 -> 52950 | J43: =J41+J26 -> 55843 | K43: =K41+K26 -> 84932
B44: EBIT | G44: =Historical_FS!H33 -> 9486.2 | H44: =Historical_FS!I33 -> 9469.03 | I44: =Historical_FS!J33 -> 8238.97 | J44: =Historical_FS!K33 -> 10390.22 | K44: =Historical_FS!L33 -> 9178.67
B45: Marginal Tax Rate | G45: =WACC!$F$15 -> 0.2517 | H45: =WACC!$F$15 -> 0.2517 | I45: =WACC!$F$15 -> 0.2517 | J45: =WACC!$F$15 -> 0.2517 | K45: =WACC!$F$15 -> 0.2517
B46: NOPAT | G46: =G44*(1-G45) -> 7098.5235 | H46: =H44*(1-H45) -> 7085.6751 | I46: =I44*(1-I45) -> 6165.2213 | J46: =J44*(1-J45) -> 7775.0016 | K46: =K44*(1-K45) -> 6868.3988
A48: # | B48: Return on Invested Capital (ROIC) | G48: =G46/G43 -> 0.14189385 | H48: =H46/H43 -> 0.14100285 | I48: =I46/I43 -> 0.11643477 | J48: =J46/J43 -> 0.13922966 | K48: =K46/K43 -> 0.080869387
A50: # | B50: Calculation of Reinvestment Rate | G50: =G11 -> 44256 | H50: =H11 -> 44621 | I50: =I11 -> 44986 | J50: =J11 -> 45352 | K50: =K11 -> 45717
B52: Net Capex | G52: =-SUM(Historical_FS!H98:H99) -> 1839 | H52: =-SUM(Historical_FS!I98:I99) -> 5540 | I52: =-SUM(Historical_FS!J98:J99) -> 6105 | J52: =-SUM(Historical_FS!K98:K99) -> 8884 | K52: =-SUM(Historical_FS!L98:L99) -> 8950
B53: Change in Working Capital | H53: =H26-G26 -> 148 | I53: =I26-H26 -> -1391 | J53: =J26-I26 -> -408 | K53: =K26-J26 -> -2597
B55: EBIT | G55: =G44 -> 9486.2 | H55: =H44 -> 9469.03 | I55: =I44 -> 8238.97 | J55: =J44 -> 10390.22 | K55: =K44 -> 9178.67
B56: Marginal Tax Rate | G56: =WACC!$F$15 -> 0.2517 | H56: =WACC!$F$15 -> 0.2517 | I56: =WACC!$F$15 -> 0.2517 | J56: =WACC!$F$15 -> 0.2517 | K56: =WACC!$F$15 -> 0.2517
B57: NOPAT | G57: =G55*(1-G56) -> 7098.5235 | H57: =H55*(1-H56) -> 7085.6751 | I57: =I55*(1-I56) -> 6165.2213 | J57: =J55*(1-J56) -> 7775.0016 | K57: =K55*(1-K56) -> 6868.3988
B59: Reinvestment | H59: =SUM(H52:H53) -> 5688 | I59: =SUM(I52:I53) -> 4714 | J59: =SUM(J52:J53) -> 8476 | K59: =SUM(K52:K53) -> 6353
A61: # | B61: Reinvestment Rate | H61: =H59/H57 -> 0.80274637 | I61: =I59/I57 -> 0.76461165 | J61: =J59/J57 -> 1.0901605 | K61: =K59/K57 -> 0.92496086
I63: 4 Year Average | K63: =AVERAGE(H61:K61) -> 0.89561986
I64: 4 Year Median | K64: =MEDIAN(H61:K61) -> 0.86385361
A66: # | B66: Calculation of Growth Rate | G66: =G50 -> 44256 | H66: =H50 -> 44621 | I66: =I50 -> 44986 | J66: =J50 -> 45352 | K66: =K50 -> 45717
B68: Reinvestment Rate | H68: =H61 -> 0.80274637 | I68: =I61 -> 0.76461165 | J68: =J61 -> 1.0901605 | K68: =K61 -> 0.92496086
B69: ROIC | H69: =H48 -> 0.14100285 | I69: =I48 -> 0.11643477 | J69: =J48 -> 0.13922966 | K69: =K48 -> 0.080869387
B71: Intrinsic Growth | H71: =H68*H69 -> 0.11318952 | I71: =I68*I69 -> 0.089027384 | J71: =J68*J69 -> 0.15178268 | K71: =K68*K69 -> 0.074801017
B73: 1). Intrinsic Growth is calculated by Gordon Growth Model | I73: 4 Year Average | K73: =AVERAGE(H71:K71) -> 0.10720015
I74: 4 Year Median | K74: =MEDIAN(H71:K71) -> 0.10110845

Sheet DCF
B9: Figures are in INR Crore
B11: Calculation of PV of FCFF | F11: =Intrinsic_Growth!K11 -> 45717 | G11: =F11+365 -> 46082 | H11: =G11+365 -> 46447 | I11: =H11+366 -> 46813 | J11: =I11+365 -> 47178 | K11: =J11+365 -> 47543 | L11: =K11+365 -> 47908 | M11: =L11+366 -> 48274 | N11: =M11+365 -> 48639 | O11: =N11+365 -> 49004 | P11: =O11+365 -> 49369
B13: NOPAT | F13: =Intrinsic_Growth!K57 -> 6868.3988 | G13: =F13*(1+G14) -> 7562.8519 | H13: =G13*(1+H14) -> 8268.7031 | I13: =H13*(1+I14) -> 8976.1256 | J13: =I13*(1+J14) -> 9674.2627 | K13: =J13*(1+K14) -> 10351.461 | L13: =K13*(1+L14) -> 11024.306 | M13: =L13*(1+M14) -> 11707.813 | N13: =M13*(1+N14) -> 12398.574 | ... P13: =O13*(1+P14) -> 13786.818
B14: Expected Growth | G14: =E24 -> 0.10110845 | H14: =G14+(($K$14-$G$14)/4) -> 0.093331341 | I14: =H14+(($K$14-$G$14)/4) -> 0.085554227 | J14: =I14+(($K$14-$G$14)/4) -> 0.077777114 | K14: 0.07 | L14: 0.065 | M14: 0.062 | N14: 0.059 | O14: 0.056 | P14: 0.053
B15: Less: Reinvestment Rate | F15: =Intrinsic_Growth!K64 -> 0.86385361 | G15: =F15+(($K$15-$F$15)/4) -> 0.77039021 | H15: =G15+(($K$15-$F$15)/4) -> 0.67692681 | I15: =H15+(($K$15-$F$15)/4) -> 0.5834634 | J15: =I15+(($K$15-$F$15)/4) -> 0.49 | K15: 0.49 | L15: 0.45 | M15: 0.42 | N15: 0.39 | O15: 0.37 | P15: 0.35
B17: Free Cash Flow to Firm (FCFF) | F17: =F13*(1-F15) -> 935.10768 | G17: =G13*(1-G15) -> 1736.5048 | H17: =H13*(1-H15) -> 2671.3963 | I17: =I13*(1-I15) -> 3738.8848 | J17: =J13*(1-J15) -> 4933.874 | K17: =K13*(1-K15) -> 5279.2452 | L17: =L13*(1-L15) -> 6063.3683 | M17: =M13*(1-M15) -> 6790.5316 | ... P17: =P13*(1-P15) -> 8961.4314
B19: Mid Year Convention | G19: 0.5 | H19: =G19+1 -> 1.5 | I19: =H19+1 -> 2.5 | J19: =I19+1 -> 3.5 | K19: =J19+1 -> 4.5 | L19: =K19+1 -> 5.5 | M19: =L19+1 -> 6.5 | N19: =M19+1 -> 7.5 | O19: =N19+1 -> 8.5 | P19: =O19+1 -> 9.5
B20: Discounting Factor | G20: =1/(1+$E$26)^G19 -> 0.94195869 | H20: =1/(1+$E$26)^H19 -> 0.83578692 | I20: =1/(1+$E$26)^I19 -> 0.74158218 | J20: =1/(1+$E$26)^J19 -> 0.65799562 | K20: =1/(1+$E$26)^K19 -> 0.58383041 | L20: =1/(1+$E$26)^L19 -> 0.51802466 | M20: =1/(1+$E$26)^M19 -> 0.45963612 | N20: =1/(1+$E$26)^N19 -> 0.40782877 | ... P20: =1/(1+$E$26)^P19 -> 0.32107411
B22: PV of FCFF | G22: =G17*G20 -> 1635.7158 | H22: =H17*H20 -> 2232.7181 | I22: =I17*I20 -> 2772.6903 | J22: =J17*J20 -> 3246.4675 | K22: =K17*K20 -> 3082.1839 | L22: =L17*L20 -> 3140.9743 | M22: =M17*M20 -> 3121.1735 | N22: =N17*N20 -> 3084.4621 | ... P22: =P17*P20 -> 2877.2836
B24: Expected Growth | E24: =Intrinsic_Growth!K74 -> 0.10110845 | G24: Sensitivity Analysis - Equity Value per Share
B25: Terminal Growth | E25: 0.05 | G25: =E47 -> 1561.1671 | H25: 0.12 | I25: 0.14 | J25: 0.1270321 | K25: 0.18
B26: WACC | E26: =WACC!J48 -> 0.1270321 | G26: 0.02 | H26: 1255.7212 | I26: 1084.982 | J26: 1188.415 | K26: 871.55785
G27: 0.04 | H27: 1511.8302 | I27: 1255.7212 | J27: 1408.3636 | K27: 963.02533
B28: Calculation of Terminal Value | G28: 0.068 | H28: 2201.3542 | I28: 1654.1129 | J28: 1966.6731 | K28: 1145.9603
G29: 0.08 | H29: 2792.3748 | I29: 1938.6784 | J29: 2409.4484 | K29: 1255.7212
B30: FCFF (n+1) | E30: =P17*(1+$E$25) -> 9409.503 | G30: 0.1 | H30: 5353.4641 | I30: 2792.3748 | J30: 4020.9865 | K30: 1511.8302
B31: WACC | E31: =E26 -> 0.1270321
B32: Terminal Growth | E32: =E25 -> 0.05 | G32: Sensitivity Analysis - Terminal Value
G33: =E34 -> 122150.42 | H33: 0.12 | I33: 0.14 | J33: 0.1270321 | K33: 0.18
B34: Terminal Value | E34: =E30/(E31-E32) -> 122150.42 | G34: 0.02 | H34: 94095.03 | I34: 78412.525 | J34: 87912.907 | K34: 58809.394
G35: 0.04 | H35: 117618.79 | I35: 94095.03 | J35: 108115.32 | K35: 67210.735
B36: Calculation of Equity Value per Share | G36: 0.068 | H36: 180951.98 | I36: 130687.54 | J36: 159396.38 | K36: 84013.419
G37: 0.08 | H37: 235237.57 | I37: 156825.05 | J37: 200065.55 | K37: 94095.03
B38: PV of FCFF | E38: =SUM(G22:P22) -> 28178.487 | G38: 0.1 | H38: 470475.15 | I38: 235237.57 | J38: 348086.29 | K38: 117618.79
B39: PV of Terminal Value | E39: =E34*P20 -> 39219.336
B40: Value of Operating Assets | E40: =SUM(E38:E39) -> 67397.823
B42: Add: Cash | E42: ='Data Sheet'!K69 -> 1673.32
B43: Less: Debt | E43: =SUM('Raw FS'!L22:L23) -> 23031
B44: Value of Equity | E44: =E40+E42-E43 -> 46040.143
B45: No. of Shares | E45: ='Data Sheet'!B6 -> 29.490848
B47: Equity Value per Share | E47: =E44/E45 -> 1561.1671
B49: Share Price | E49: 11937
B50: Discount/Premium | E50: =E49/E47 -> 7.6462025

Sheet Relative_Val.
B9: Figures are in INR Crore
B10: Comparable Company Valuation
D12: Market Data | J12: Financials | N12: Valuation
D13: Share | E13: Shares | F13: Equity | H13: Enterprise
B14: Name | C14: Ticker | D14: Price | E14: Outstanding | F14: Value | G14: Net Debt | H14: Value | J14: Revenue | K14: EBITDA | L14: Net Income | N14: EV/Revenue | O14: EV/EBITDA | P14: P/E Ratio
B16: ='Comps Rel.'!C3 -> UltraTech Cem. | D16: ='Comps Rel.'!D3 -> 11764 | E16: ='Comps Rel.'!E3 -> 29.47 | F16: =D16*E16 -> 346685.08 | G16: ='Comps Rel.'!I3 -> 23541.59 | H16: =F16+G16 -> 370226.67 | J16: ='Comps Rel.'!K3 -> 81724.53 | K16: ='Comps Rel.'!N3 -> 15702.197 | L16: ='Comps Rel.'!L3 -> 7297.12 | N16: =$H16/J16 -> 4.530178 | O16: =$H16/K16 -> 23.578018 | P16: =F16/L16 -> 47.50985
B17: ='Comps Rel.'!C4 -> Grasim Inds | D17: ='Comps Rel.'!D4 -> 2841.3 | E17: ='Comps Rel.'!E4 -> 68.05 | F17: =D17*E17 -> 193350.46 | G17: ='Comps Rel.'!I4 -> 178420.14 | H17: =F17+G17 -> 371770.6 | J17: ='Comps Rel.'!K4 -> 153326.53 | K17: ='Comps Rel.'!N4 -> 32216.315 | L17: ='Comps Rel.'!L4 -> 8574.66 | N17: =$H17/J17 -> 2.4246985 | O17: =$H17/K17 -> 11.539824 | P17: =F17/L17 -> 22.549053
B18: ='Comps Rel.'!C5 -> Ambuja Cements | D18: ='Comps Rel.'!D5 -> 555 | E18: ='Comps Rel.'!E5 -> 247.18 | F18: =D18*E18 -> 137184.9 | G18: ='Comps Rel.'!I5 -> -5383.66 | H18: =F18+G18 -> 131801.24 | J18: ='Comps Rel.'!K5 -> 37114.29 | K18: ='Comps Rel.'!N5 -> 9223.4108 | L18: ='Comps Rel.'!L5 -> 5344.88 | N18: =$H18/J18 -> 3.5512262 | O18: =$H18/K18 -> 14.289859 | P18: =F18/L18 -> 25.666601
B19: ='Comps Rel.'!C6 -> Shree Cement | D19: ='Comps Rel.'!D6 -> 28705 | E19: ='Comps Rel.'!E6 -> 3.61 | F19: =D19*E19 -> 103625.05 | G19: ='Comps Rel.'!I6 -> 752.55 | H19: =F19+G19 -> 104377.6 | J19: ='Comps Rel.'!K6 -> 19439.75 | K19: ='Comps Rel.'!N6 -> 5025.1609 | L19: ='Comps Rel.'!L6 -> 1489.01 | N19: =$H19/J19 -> 5.3692872 | O19: =$H19/K19 -> 20.770997 | P19: =F19/L19 -> 69.593253
B20: ='Comps Rel.'!C7 -> J K Cements | D20: ='Comps Rel.'!D7 -> 6257.5 | E20: ='Comps Rel.'!E7 -> 7.73 | F20: =D20*E20 -> 48370.475 | G20: ='Comps Rel.'!I7 -> 4658.56 | H20: =F20+G20 -> 53029.035 | J20: ='Comps Rel.'!K7 -> 12424.11 | K20: ='Comps Rel.'!N7 -> 2413.8966 | L20: ='Comps Rel.'!L7 -> 1011.6 | N20: =$H20/J20 -> 4.2682361 | O20: =$H20/K20 -> 21.968229 | P20: =F20/L20 -> 47.815812
B21: ='Comps Rel.'!C8 -> Dalmia BharatLtd | D21: ='Comps Rel.'!D8 -> 2098.4 | E21: ='Comps Rel.'!E8 -> 18.76 | F21: =D21*E21 -> 39365.984 | G21: ='Comps Rel.'!I8 -> 5544 | H21: =F21+G21 -> 44909.984 | J21: ='Comps Rel.'!K8 -> 14325 | K21: ='Comps Rel.'!N8 -> 3126.9269 | L21: ='Comps Rel.'!L8 -> 1139 | N21: =$H21/J21 -> 3.1350774 | O21: =$H21/K21 -> 14.362339 | P21: =F21/L21 -> 34.561882
B22: ='Comps Rel.'!C9 -> ACC | D22: ='Comps Rel.'!D9 -> 1850.1 | E22: ='Comps Rel.'!E9 -> 18.78 | F22: =D22*E22 -> 34744.878 | G22: ='Comps Rel.'!I9 -> -1219.5 | H22: =F22+G22 -> 33525.378 | J22: ='Comps Rel.'!K9 -> 22742.68 | K22: ='Comps Rel.'!N9 -> 4232.7045 | L22: ='Comps Rel.'!L9 -> 2417.95 | N22: =$H22/J22 -> 1.4741173 | O22: =$H22/K22 -> 7.9205571 | P22: =F22/L22 -> 14.36956
B23: ='Comps Rel.'!C10 -> The Ramco Cement | D23: ='Comps Rel.'!D10 -> 1046.8 | E23: ='Comps Rel.'!E10 -> 23.63 | F23: =D23*E23 -> 24735.884 | G23: ='Comps Rel.'!I10 -> 4465.46 | H23: =F23+G23 -> 29201.344 | J23: ='Comps Rel.'!K10 -> 8498.87 | K23: ='Comps Rel.'!N10 -> 1348.7552 | L23: ='Comps Rel.'!L10 -> 317.56 | N23: =$H23/J23 -> 3.435909 | O23: =$H23/K23 -> 21.650589 | P23: =F23/L23 -> 77.893576
B24: ='Comps Rel.'!C11 -> JSW Cement | D24: ='Comps Rel.'!D11 -> 135.27 | E24: ='Comps Rel.'!E11 -> 136.34 | F24: =D24*E24 -> 18442.712 | G24: ='Comps Rel.'!I11 -> 6439.01 | H24: =F24+G24 -> 24881.722 | J24: ='Comps Rel.'!K11 -> 5785.29 | K24: ='Comps Rel.'!N11 -> 718.28089 | L24: ='Comps Rel.'!L11 -> -163.77 | N24: =$H24/J24 -> 4.3008599 | O24: =$H24/K24 -> 34.640657 | P24: =F24/L24 -> -112.61349
B25: ='Comps Rel.'!C12 -> Nuvoco Vistas | D25: ='Comps Rel.'!D12 -> 414.9 | E25: ='Comps Rel.'!E12 -> 35.72 | F25: =D25*E25 -> 14820.228 | G25: ='Comps Rel.'!I12 -> 5621.42 | H25: =F25+G25 -> 20441.648 | J25: ='Comps Rel.'!K12 -> 10781.88 | K25: ='Comps Rel.'!N12 -> 1718.2089 | L25: ='Comps Rel.'!L12 -> 273.76 | N25: =$H25/J25 -> 1.8959261 | O25: =$H25/K25 -> 11.897068 | P25: =F25/L25 -> 54.135842
B27: High | N27: =MAX(N16:N25) -> 5.3692872 | O27: =MAX(O16:O25) -> 34.640657 | P27: =MAX(P16:P25) -> 77.893576
B28: 75th Percentile | N28: =QUARTILE(N16:N25,3) -> 4.292704 | O28: =QUARTILE(O16:O25,3) -> 21.888819 | P28: =QUARTILE(P16:P25,3) -> 52.555834
B29: Average | N29: =AVERAGE(N16:N25) -> 3.4385516 | O29: =AVERAGE(O16:O25) -> 18.261814 | P29: =AVERAGE(P16:P25) -> 28.148194
B30: Median | N30: =MEDIAN(N16:N25) -> 3.4935676 | O30: =MEDIAN(O16:O25) -> 17.566668 | P30: =MEDIAN(P16:P25) -> 41.035866
B31: 25th Percentile | N31: =QUARTILE(N16:N25,1) -> 2.6022932 | O31: =QUARTILE(O16:O25,1) -> 12.495266 | P31: =QUARTILE(P16:P25,1) -> 23.32844
B32: Low | N32: =MIN(N16:N25) -> 1.4741173 | O32: =MIN(O16:O25) -> 7.9205571 | P32: =MIN(P16:P25) -> -112.61349
B34: UltraTech Cement Comparable Valuation | N34: =N14 -> EV/Revenue | O34: =O14 -> EV/EBITDA | P34: =P14 -> P/E Ratio
B36: Implied Enterprise Value | N36: =N30*J16 -> 285510.17 | O36: =O30*K16 -> 275835.27 | P36: =P38+P37 -> 322985.23
B37: Net Debt | N37: =$G$16 -> 23541.59 | O37: =$G$16 -> 23541.59 | P37: =$G$16 -> 23541.59
B38: Implied Market Value | N38: =N36-N37 -> 261968.58 | O38: =O36-O37 -> 252293.68 | P38: =P30*L16 -> 299443.64
B39: Shares Outstanding | N39: =$E$16 -> 29.47 | O39: =$E$16 -> 29.47 | P39: =$E$16 -> 29.47
B41: Implied Value per Share | N41: =N38/N39 -> 8889.3309 | O41: =O38/O39 -> 8561.0344 | P41: =P38/P39 -> 10160.965
B43: Source: The Valuation School, Screener.in | N43: =IF(N41>$D$16,"Undervalued","Overvalued") -> Overvalued | O43: =IF(O41>$D$16,"Undervalued","Overvalued") -> Overvalued | P43: =IF(P41>$D$16,"Undervalued","Overvalued") -> Overvalued

Sheet Football_Field
Q9: Football Field Analysis - Data
R10: Open Low | S10: Low | T10: Open High | U10: High
Q11: Comps | R11: ='Relative_Val.'!$O$41 -> 8561.0344 | S11: ='Relative_Val.'!$O$41 -> 8561.0344 | T11: ='Relative_Val.'!$P$41 -> 10160.965 | U11: ='Relative_Val.'!$P$41 -> 10160.965
Q12: DCF Bear | R12: =DCF!K26 -> 871.55785 | S12: =DCF!K26 -> 871.55785 | T12: =DCF!K30 -> 1511.8302 | U12: =DCF!K30 -> 1511.8302
Q13: DCF Base | R13: =DCF!I26 -> 1084.982 | S13: =DCF!I26 -> 1084.982 | T13: =DCF!I30 -> 2792.3748 | U13: =DCF!I30 -> 2792.3748
Q14: DCF Bull | R14: =DCF!H26 -> 1255.7212 | S14: =DCF!H26 -> 1255.7212 | T14: =DCF!H30 -> 5353.4641 | U14: =DCF!H30 -> 5353.4641
Q15: 52W H/L | R15: =S15 -> 10048 | S15: 10048 | T15: 13102 | U15: =T15 -> 13102
Q16: Transaction Comps | R16: 6660 | S16: 6660 | T16: 9856 | U16: 9856
Q17: CMP | R17: =DCF!$E$49 -> 11937 | S17: =DCF!$E$49 -> 11937 | T17: =DCF!$E$49 -> 11937 | U17: =DCF!$E$49 -> 11937

Sheet Monte-Carlo
B9: Monte-Carlo Simulation (Calculated on Weekly Returns)
B11: Date | C11: Price | D11: Returns | E11: Sorted Returns | G11: Replication | H11: Simulated Returns | J11: Calculation of Value at Risk
B12: 39726 | C12: 447.45 | D12: =(C12-C13)/C13 -> -0.38414424 | E12: 0.19623045 | G12: 1 | H12: =_xlfn.NORM.INV(RAND(),N$14,N$15) -> 0.018844511
B13: 38907 | C13: 726.55 | D13: =(C13-C14)/C14 -> 0.40640728 | E13: 0.15462853 | G13: 2 | H13: =_xlfn.NORM.INV(RAND(),N$14,N$15) -> -0.0477478 | J13: Historical Approach
B14: 39719 | C14: 516.6 | D14: =(C14-C15)/C15 -> -0.85545 | E14: 0.15454241 | G14: 3 | H14: =_xlfn.NORM.INV(RAND(),N$14,N$15) -> 0.0094668687 | J14: Mean | N14: =AVERAGE(E12:E1123) -> -0.002557895
B15: 43905 | C15: 3573.85 | D15: =(C15-C16)/C16 -> 2.4465018 | E15: 0.13686538 | G15: 4 | H15: =_xlfn.NORM.INV(RAND(),N$14,N$15) -> -0.018327528 | J15: Std Deviation | N15: =_xlfn.STDEV.S(E12:E1123) -> 0.041483832
B16: 40188 | C16: 1036.95 | D16: =(C16-C17)/C17 -> 0.17534712 | E16: 0.13619679 | G16: 5 | H16: =_xlfn.NORM.INV(RAND(),N$14,N$15) -> 0.01738902 | J16: Min | N16: =MIN(E12:E1123) -> -0.17212859
B17: 39138 | C17: 882.25 | D17: =(C17-C18)/C18 -> -0.10748609 | E17: 0.13159751 | G17: 6 | H17: =_xlfn.NORM.INV(RAND(),N$14,N$15) -> 0.032107556 | J17: Max | N17: =MAX(E12:E1123) -> 0.19623045
B18: 39278 | C18: 988.5 | D18: =(C18-C19)/C19 -> -0.097054122 | E18: 0.12913359 | G18: 7 | H18: =_xlfn.NORM.INV(RAND(),N$14,N$15) -> 0.031796769 | J18: CMP | N18: ='Comps Rel.'!D3 -> 11764
B19: 40286 | C19: 1094.75 | D19: =(C19-C20)/C20 -> -0.69325712 | E19: 0.12541763 | G19: 8 | H19: =_xlfn.NORM.INV(RAND(),N$14,N$15) -> 0.050086486
B20: 42708 | C20: 3568.95 | D20: =(C20-C21)/C21 -> 8.5413715 | E20: 0.12314132 | G20: 9 | H20: =_xlfn.NORM.INV(RAND(),N$14,N$15) -> -0.011886399 | J20: Monte-Carlo Simulation
B21: 39733 | C21: 374.05 | D21: =(C21-C22)/C22 -> 0.15840818 | E21: 0.12243061 | G21: 10 | H21: =_xlfn.NORM.INV(RAND(),N$14,N$15) -> 0.01807396 | J21: Mean | N21: =AVERAGE(H12:H1123) -> -0.0018583859
B22: 39761 | C22: 322.9 | D22: =(C22-C23)/C23 -> -0.58178992 | E22: 0.11364028 | G22: 11 | H22: =_xlfn.NORM.INV(RAND(),N$14,N$15) -> 0.021304654 | J22: Std Deviation | N22: =_xlfn.STDEV.S(H12:H1123) -> 0.042760945
B23: 39166 | C23: 772.1 | D23: =(C23-C24)/C24 -> -0.30994727 | E23: 0.1134987 | G23: 12 | H23: =_xlfn.NORM.INV(RAND(),N$14,N$15) -> 0.038486574 | J23: Min | N23: =MIN(H12:H1123) -> -0.1357877
B24: 39362 | C24: 1118.9 | D24: =(C24-C25)/C25 -> -0.83337801 | E24: 0.11206083 | G24: 13 | H24: =_xlfn.NORM.INV(RAND(),N$14,N$15) -> 0.0050019263 | J24: Max | N24: =MAX(H12:H1123) -> 0.12804113
B25: 44297 | C25: 6715.2 | D25: =(C25-C26)/C26 -> 0.52786594 | E25: 0.10667612 | G25: 14 | H25: =_xlfn.NORM.INV(RAND(),N$14,N$15) -> 0.055703625 | J25: CMP | N25: =N18 -> 11764
B26: 43730 | C26: 4395.15 | D26: =(C26-C27)/C27 -> 12.717697 | E26: 0.10443392 | G26: 15 | H26: =_xlfn.NORM.INV(RAND(),N$14,N$15) -> 0.064072732
B27: 38263 | C27: 320.4 | D27: =(C27-C28)/C28 -> -0.97128325 | E27: 0.10216718 | G27: 16 | H27: =_xlfn.NORM.INV(RAND(),N$14,N$15) -> -0.066841768 | J27: Percentile | K27: Confidence | L27: VAR % | M27: Stock Price | N27: VAR (INR)
B28: 45704 | C28: 11157.25 | D28: =(C28-C29)/C29 -> 10.081343 | E28: 0.10157527 | G28: 17 | H28: =_xlfn.NORM.INV(RAND(),N$14,N$15) -> -0.048426311 | J28: 0.05 | K28: =100%-J28 -> 0.95 | L28: =_xlfn.PERCENTILE.INC($H$12:$H$1123,J28) -> -0.068000615 | M28: =$N$25*(1-L28) -> 12563.959 | N28: =$N$25-M28 -> -799.95923
B29: 40573 | C29: 1006.85 | D29: =(C29-C30)/C30 -> -0.75842461 | E29: 0.10062309 | G29: 18 | H29: =_xlfn.NORM.INV(RAND(),N$14,N$15) -> -0.0062521196 | J29: 0.01 | K29: =100%-J29 -> 0.99 | L29: =_xlfn.PERCENTILE.INC($H$12:$H$1123,J29) -> -0.098022643 | M29: =$N$25*(1-L29) -> 12917.138 | N29: =$N$25-M29 -> -1153.1384
B30: 43891 | C30: 4167.85 | D30: =(C30-C31)/C31 -> 2.6716293 | E30: 0.10001584 | G30: 19 | H30: =_xlfn.NORM.INV(RAND(),N$14,N$15) -> -0.066053156 | J30: 0.005 | K30: =100%-J30 -> 0.995 | L30: =_xlfn.PERCENTILE.INC($H$12:$H$1123,J30) -> -0.1018384 | M30: =$N$25*(1-L30) -> 12962.027 | N30: =$N$25-M30 -> -1198.027
B31: 39096 | C31: 1135.15 | D31: =(C31-C32)/C32 -> 0.069131151 | E31: 0.09846139 | G31: 20 | H31: =_xlfn.NORM.INV(RAND(),N$14,N$15) -> 0.011751365 | J31: 0.1 | K31: =100%-J31 -> 0.9 | L31: =_xlfn.PERCENTILE.INC($H$12:$H$1123,J31) -> -0.055533124 | M31: =$N$25*(1-L31) -> 12417.292 | N31: =$N$25-M31 -> -653.29167
B32: 39117 | C32: 1061.75 | D32: =(C32-C33)/C33 -> -0.020751672 | E32: 0.098381007 | G32: 21 | H32: =_xlfn.NORM.INV(RAND(),N$14,N$15) -> 0.097258118
B33: 40538 | C33: 1084.25 | D33: =(C33-C34)/C34 -> 0.43154212 | E33: 0.097696786 | G33: 22 | H33: =_xlfn.NORM.INV(RAND(),N$14,N$15) -> -0.0068084085
B34: 39565 | C34: 757.4 | D34: =(C34-C35)/C35 -> 0.03455812 | E34: 0.0951417 | G34: 23 | H34: =_xlfn.NORM.INV(RAND(),N$14,N$15) -> -0.016226783
B35: 39971 | C35: 732.1 | D35: =(C35-C36)/C36 -> -0.82602186 | E35: 0.091627526 | G35: 24 | H35: =_xlfn.NORM.INV(RAND(),N$14,N$15) -> 0.025444941
B36: 43688 | C36: 4208 | D36: =(C36-C37)/C37 -> 0.1015851 | E36: 0.089647315 | G36: 25 | H36: =_xlfn.NORM.INV(RAND(),N$14,N$15) -> -0.011288166
B37: 43478 | C37: 3819.95 | D37: =(C37-C38)/C38 -> 3.4969686 | E37: 0.088056853 | G37: 26 | H37: =_xlfn.NORM.INV(RAND(),N$14,N$15) -> 0.0051453025
B38: 39516 | C38: 849.45 | D38: =(C38-C39)/C39 -> -0.87071268 | E38: 0.087435192 | G38: 27 | H38: =_xlfn.NORM.INV(RAND(),N$14,N$15) -> 0.04865569
B39: 44612 | C39: 6570.25 | D39: =(C39-C40)/C40 -> -0.44253776 | E39: 0.085937887 | G39: 28 | H39: =_xlfn.NORM.INV(RAND(),N$14,N$15) -> -0.044558121
B40: 45655 | C40: 11786 | D40: =(C40-C41)/C41 -> 4.772075 | E40: 0.084747635 | G40: 29 | H40: =_xlfn.NORM.INV(RAND(),N$14,N$15) -> 0.023597077
B41: 41273 | C41: 2041.9 | D41: =(C41-C42)/C42 -> 3.4906532 | E41: 0.08421388 | G41: 30 | H41: =_xlfn.NORM.INV(RAND(),N$14,N$15) -> -0.027517644
B42: 38627 | C42: 454.7 | D42: =(C42-C43)/C43 -> 0.30062929 | E42: 0.083134826 | G42: 31 | H42: =_xlfn.NORM.INV(RAND(),N$14,N$15) -> -0.01194591
B43: 39754 | C43: 349.6 | D43: =(C43-C44)/C44 -> -0.89039206 | E43: 0.082688139 | G43: 32 | H43: =_xlfn.NORM.INV(RAND(),N$14,N$15) -> -0.012625984
... B1122: 44220 | C1122: 5327.25 | D1122: =(C1122-C1123)/C1123 -> 19.083883 | E1122: -0.16134034 | G1122: 1111 | H1122: =_xlfn.NORM.INV(RAND(),N$14,N$15) -> 0.057693246
B1123: 38256 | C1123: 265.25 | D1123: =IFERROR((C1123-C1124)/C1124,0) -> 0 | E1123: -0.17212859 | G1123: 1112 | H1123: =_xlfn.NORM.INV(RAND(),N$14,N$15) -> -0.016649981

Sheet DuPont
B9: ULTRACEMCO | BSE Code : 532538
B10: =CONCATENATE("INR"," - ",DCF!E49) -> INR - 11937
B11: 52 Week High - INR 13102
B12: 52 Week Low - INR 10048
B14: About the company
B15: UltraTech Cement Limited is the cement flagship company of the Aditya Birla Group. A USD 8.9 billion building solutions powerhouse, UltraTech is the largest manufacturer of grey cement and ready-mix concrete (RMC) and one of the largest manufacturers of white cement in India. It is the second largest cement company globally by capacity and the largest by sales volume (excluding China).
B19: Financial Summary
B41: Recent Updates
A48: # | B48: Return on Equity (ROE)
C49: ='Data Sheet'!C16 -> 42825 | D49: ='Data Sheet'!D16 -> 43190 | E49: ='Data Sheet'!E16 -> 43555 | F49: ='Data Sheet'!F16 -> 43921 | G49: ='Data Sheet'!G16 -> 44286 | H49: ='Data Sheet'!H16 -> 44651 | I49: ='Data Sheet'!I16 -> 45016 | J49: ='Data Sheet'!J16 -> 45382 | K49: ='Data Sheet'!K16 -> 45747
B50: =IFERROR(Historical_FS!B45,0) -> Net Profit | C50: =IFERROR(Historical_FS!D45,0) -> 2713.51 | D50: =IFERROR(Historical_FS!E45,0) -> 2224.46 | E50: =IFERROR(Historical_FS!F45,0) -> 2400.38 | F50: =IFERROR(Historical_FS!G45,0) -> 5750.88 | G50: =IFERROR(Historical_FS!H45,0) -> 5461.85 | H50: =IFERROR(Historical_FS!I45,0) -> 7334.26 | I50: =IFERROR(Historical_FS!J45,0) -> 5073.4 | J50: =IFERROR(Historical_FS!K45,0) -> 7003.96 | K50: =IFERROR(Historical_FS!L45,0) -> 6039.64
B51: Average Shareholder's Equity | C51: =IFERROR((('Data Sheet'!C57+'Data Sheet'!C58)+('Data Sheet'!B57+'Data Sheet'!B58))/2,"-") -> 23168.76 | D51: =IFERROR((('Data Sheet'!D57+'Data Sheet'!D58)+('Data Sheet'!C57+'Data Sheet'!C58))/2,"-") -> 25386.525 | E51: =IFERROR((('Data Sheet'!E57+'Data Sheet'!E58)+('Data Sheet'!D57+'Data Sheet'!D58))/2,"-") -> 30065.905 | F51: =IFERROR((('Data Sheet'!F57+'Data Sheet'!F58)+('Data Sheet'!E57+'Data Sheet'!E58))/2,"-") -> 36397.205 | G51: =IFERROR((('Data Sheet'!G57+'Data Sheet'!G58)+('Data Sheet'!F57+'Data Sheet'!F58))/2,"-") -> 41609.22 | H51: =IFERROR((('Data Sheet'!H57+'Data Sheet'!H58)+('Data Sheet'!G57+'Data Sheet'!G58))/2,"-") -> 47304.975 | I51: =IFERROR((('Data Sheet'!I57+'Data Sheet'!I58)+('Data Sheet'!H57+'Data Sheet'!H58))/2,"-") -> 52379.905 | J51: =IFERROR((('Data Sheet'!J57+'Data Sheet'!J58)+('Data Sheet'!I57+'Data Sheet'!I58))/2,"-") -> 57276.01 | K51: =IFERROR((('Data Sheet'!K57+'Data Sheet'!K58)+('Data Sheet'!J57+'Data Sheet'!J58))/2,"-") -> 65467.125
B52: Return on Equity (ROE) | C52: =IFERROR(C50/C51,"-") -> 0.11711935 | D52: =IFERROR(D50/D51,"-") -> 0.087623651 | E52: =IFERROR(E50/E51,"-") -> 0.079837277 | F52: =IFERROR(F50/F51,"-") -> 0.15800334 | G52: =IFERROR(G50/G51,"-") -> 0.13126538 | H52: =IFERROR(H50/H51,"-") -> 0.15504204 | I52: =IFERROR(I50/I51,"-") -> 0.096857755 | J52: =IFERROR(J50/J51,"-") -> 0.12228436 | K52: =IFERROR(K50/K51,"-") -> 0.092254548
B54: ROE - DuPont Equation
C55: =C49 -> 42825 | D55: =D49 -> 43190 | E55: =E49 -> 43555 | F55: =F49 -> 43921 | G55: =G49 -> 44286 | H55: =H49 -> 44651 | I55: =I49 -> 45016 | J55: =J49 -> 45382 | K55: =K49 -> 45747
B56: =IFERROR(B50,0) -> Net Profit | C56: =IFERROR(C50,0) -> 2713.51 | D56: =IFERROR(D50,0) -> 2224.46 | E56: =IFERROR(E50,0) -> 2400.38 | F56: =IFERROR(F50,0) -> 5750.88 | G56: =IFERROR(G50,0) -> 5461.85 | H56: =IFERROR(H50,0) -> 7334.26 | I56: =IFERROR(I50,0) -> 5073.4 | ... K56: =IFERROR(K50,0) -> 6039.64
B57: Sales | C57: =IFERROR(Historical_FS!D12,0) -> 25374.94 | D57: =IFERROR(Historical_FS!E12,0) -> 30978.62 | E57: =IFERROR(Historical_FS!F12,0) -> 41462.26 | F57: =IFERROR(Historical_FS!G12,0) -> 42429.89 | G57: =IFERROR(Historical_FS!H12,0) -> 44725.8 | H57: =IFERROR(Historical_FS!I12,0) -> 52598.83 | I57: =IFERROR(Historical_FS!J12,0) -> 63239.98 | J57: =IFERROR(Historical_FS!K12,0) -> 70908.14 | K57: =IFERROR(Historical_FS!L12,0) -> 75955.13
B58: Net Profit Margin (A) | C58: =IFERROR(C56/C57,0) -> 0.10693661 | D58: =IFERROR(D56/D57,0) -> 0.071806297 | E58: =IFERROR(E56/E57,0) -> 0.05789313 | F58: =IFERROR(F56/F57,0) -> 0.13553841 | G58: =IFERROR(G56/G57,0) -> 0.12211855 | H58: =IFERROR(H56/H57,0) -> 0.1394377 | I58: =IFERROR(I56/I57,0) -> 0.080224567 | J58: =IFERROR(J56/J57,0) -> 0.098775119 | K58: =IFERROR(K56/K57,0) -> 0.079515893
B60: =IFERROR(B57,0) -> Sales | C60: =IFERROR(C57,0) -> 25374.94 | D60: =IFERROR(D57,0) -> 30978.62 | E60: =IFERROR(E57,0) -> 41462.26 | F60: =IFERROR(F57,0) -> 42429.89 | G60: =IFERROR(G57,0) -> 44725.8 | H60: =IFERROR(H57,0) -> 52598.83 | I60: =IFERROR(I57,0) -> 63239.98 | ... K60: =IFERROR(K57,0) -> 75955.13
B61: Average Total Assets | C61: =IFERROR((Historical_FS!D80+Historical_FS!C80)/2,0) -> 41701.11 | D61: =IFERROR((Historical_FS!E80+Historical_FS!D80)/2,0) -> 49675.1 | E61: =IFERROR((Historical_FS!F80+Historical_FS!E80)/2,0) -> 66833.23 | F61: =IFERROR((Historical_FS!G80+Historical_FS!F80)/2,0) -> 77869.59 | G61: =IFERROR((Historical_FS!H80+Historical_FS!G80)/2,0) -> 82695.08 | H61: =IFERROR((Historical_FS!I80+Historical_FS!H80)/2,0) -> 84993.895 | I61: =IFERROR((Historical_FS!J80+Historical_FS!I80)/2,0) -> 87595.92 | J61: =IFERROR((Historical_FS!K80+Historical_FS!J80)/2,0) -> 96088.755 | K61: =IFERROR((Historical_FS!L80+Historical_FS!K80)/2,0) -> 117214.58
B62: Asset Turnover Ratio (B) | C62: =IFERROR(C60/C61,0) -> 0.60849555 | D62: =IFERROR(D60/D61,0) -> 0.62362471 | E62: =IFERROR(E60/E61,0) -> 0.6203839 | F62: =IFERROR(F60/F61,0) -> 0.54488395 | G62: =IFERROR(G60/G61,0) -> 0.54085201 | H62: =IFERROR(H60/H61,0) -> 0.61885421 | I62: =IFERROR(I60/I61,0) -> 0.72195121 | J62: =IFERROR(J60/J61,0) -> 0.73794421 | K62: =IFERROR(K60/K61,0) -> 0.64800067
B64: =IFERROR(B61,0) -> Average Total Assets | C64: =IFERROR(C61,0) -> 41701.11 | D64: =IFERROR(D61,0) -> 49675.1 | E64: =IFERROR(E61,0) -> 66833.23 | F64: =IFERROR(F61,0) -> 77869.59 | G64: =IFERROR(G61,0) -> 82695.08 | H64: =IFERROR(H61,0) -> 84993.895 | I64: =IFERROR(I61,0) -> 87595.92 | ... K64: =IFERROR(K61,0) -> 117214.58
B65: =IFERROR(B51,0) -> Average Shareholder's Equity | C65: =IFERROR(C51,0) -> 23168.76 | D65: =IFERROR(D51,0) -> 25386.525 | E65: =IFERROR(E51,0) -> 30065.905 | F65: =IFERROR(F51,0) -> 36397.205 | G65: =IFERROR(G51,0) -> 41609.22 | H65: =IFERROR(H51,0) -> 47304.975 | I65: =IFERROR(I51,0) -> 52379.905 | ... K65: =IFERROR(K51,0) -> 65467.125
B66: Equity Multiplier (C) | C66: =IFERROR(C64/C65,0) -> 1.7998853 | D66: =IFERROR(D64/D65,0) -> 1.9567507 | E66: =IFERROR(E64/E65,0) -> 2.222891 | F66: =IFERROR(F64/F65,0) -> 2.1394387 | G66: =IFERROR(G64/G65,0) -> 1.987422 | H66: =IFERROR(H64/H65,0) -> 1.7967221 | I66: =IFERROR(I64/I65,0) -> 1.6723192 | J66: =IFERROR(J64/J65,0) -> 1.677644 | K66: =IFERROR(K64/K65,0) -> 1.7904343
B68: Return on Equity (A*B*C) | C68: =IFERROR(C58*C62*C66,0) -> 0.11711935 | D68: =IFERROR(D58*D62*D66,0) -> 0.087623651 | E68: =IFERROR(E58*E62*E66,0) -> 0.079837277 | F68: =IFERROR(F58*F62*F66,0) -> 0.15800334 | G68: =IFERROR(G58*G62*G66,0) -> 0.13126538 | H68: =IFERROR(H58*H62*H66,0) -> 0.15504204 | I68: =IFERROR(I58*I62*I66,0) -> 0.096857755 | J68: =IFERROR(J58*J62*J66,0) -> 0.12228436 | K68: =IFERROR(K58*K62*K66,0) -> 0.092254548
B70: Check | C70: =IF(ABS(C52-C68)<0.0001,"✓ CHECK","✗ ERROR") -> ✓ CHECK | D70: =IF(ABS(D52-D68)<0.0001,"✓ CHECK","✗ ERROR") -> ✓ CHECK | E70: =IF(ABS(E52-E68)<0.0001,"✓ CHECK","✗ ERROR") -> ✓ CHECK | F70: =IF(ABS(F52-F68)<0.0001,"✓ CHECK","✗ ERROR") -> ✓ CHECK | G70: =IF(ABS(G52-G68)<0.0001,"✓ CHECK","✗ ERROR") -> ✓ CHECK | H70: =IF(ABS(H52-H68)<0.0001,"✓ CHECK","✗ ERROR") -> ✓ CHECK | I70: =IF(ABS(I52-I68)<0.0001,"✓ CHECK","✗ ERROR") -> ✓ CHECK | J70: =IF(ABS(J52-J68)<0.0001,"✓ CHECK","✗ ERROR") -> ✓ CHECK | K70: =IF(ABS(K52-K68)<0.0001,"✓ CHECK","✗ ERROR") -> ✓ CHECK
A72: # | B72: Return on Assets (ROA)
C73: =C49 -> 42825 | D73: =D49 -> 43190 | E73: =E49 -> 43555 | F73: =F49 -> 43921 | G73: =G49 -> 44286 | H73: =H49 -> 44651 | I73: =I49 -> 45016 | J73: =J49 -> 45382 | K73: =K49 -> 45747
B74: =IFERROR(B56,0) -> Net Profit | C74: =IFERROR(C56,0) -> 2713.51 | D74: =IFERROR(D56,0) -> 2224.46 | E74: =IFERROR(E56,0) -> 2400.38 | F74: =IFERROR(F56,0) -> 5750.88 | G74: =IFERROR(G56,0) -> 5461.85 | H74: =IFERROR(H56,0) -> 7334.26 | I74: =IFERROR(I56,0) -> 5073.4 | ... K74: =IFERROR(K56,0) -> 6039.64
B75: =IFERROR(B61,0) -> Average Total Assets | C75: =IFERROR(C61,0) -> 41701.11 | D75: =IFERROR(D61,0) -> 49675.1 | E75: =IFERROR(E61,0) -> 66833.23 | F75: =IFERROR(F61,0) -> 77869.59 | G75: =IFERROR(G61,0) -> 82695.08 | H75: =IFERROR(H61,0) -> 84993.895 | I75: =IFERROR(I61,0) -> 87595.92 | ... K75: =IFERROR(K61,0) -> 117214.58
B76: Return on Assets (ROA) | C76: =IFERROR(C74/C75,"-") -> 0.06507045 | D76: =IFERROR(D74/D75,"-") -> 0.044780182 | E76: =IFERROR(E74/E75,"-") -> 0.035915966 | F76: =IFERROR(F74/F75,"-") -> 0.073852707 | G76: =IFERROR(G74/G75,"-") -> 0.066048065 | H76: =IFERROR(H74/H75,"-") -> 0.08629161 | I76: =IFERROR(I74/I75,"-") -> 0.057918223 | J76: =IFERROR(J74/J75,"-") -> 0.072890527 | K76: =IFERROR(K74/K75,"-") -> 0.051526352
B78: ROA - DuPont Equation
C79: =C55 -> 42825 | D79: =D55 -> 43190 | E79: =E55 -> 43555 | F79: =F55 -> 43921 | G79: =G55 -> 44286 | H79: =H55 -> 44651 | I79: =I55 -> 45016 | J79: =J55 -> 45382 | K79: =K55 -> 45747
B80: =IFERROR(B56,0) -> Net Profit | C80: =IFERROR(C56,0) -> 2713.51 | D80: =IFERROR(D56,0) -> 2224.46 | E80: =IFERROR(E56,0) -> 2400.38 | F80: =IFERROR(F56,0) -> 5750.88 | G80: =IFERROR(G56,0) -> 5461.85 | H80: =IFERROR(H56,0) -> 7334.26 | I80: =IFERROR(I56,0) -> 5073.4 | ... K80: =IFERROR(K56,0) -> 6039.64
B81: =IFERROR(B57,0) -> Sales | C81: =IFERROR(C57,0) -> 25374.94 | D81: =IFERROR(D57,0) -> 30978.62 | E81: =IFERROR(E57,0) -> 41462.26 | F81: =IFERROR(F57,0) -> 42429.89 | G81: =IFERROR(G57,0) -> 44725.8 | H81: =IFERROR(H57,0) -> 52598.83 | I81: =IFERROR(I57,0) -> 63239.98 | ... K81: =IFERROR(K57,0) -> 75955.13
B82: Net Profit Margin (A) | C82: =IFERROR(C80/C81,"-") -> 0.10693661 | D82: =IFERROR(D80/D81,"-") -> 0.071806297 | E82: =IFERROR(E80/E81,"-") -> 0.05789313 | F82: =IFERROR(F80/F81,"-") -> 0.13553841 | G82: =IFERROR(G80/G81,"-") -> 0.12211855 | H82: =IFERROR(H80/H81,"-") -> 0.1394377 | I82: =IFERROR(I80/I81,"-") -> 0.080224567 | J82: =IFERROR(J80/J81,"-") -> 0.098775119 | K82: =IFERROR(K80/K81,"-") -> 0.079515893
B84: =IFERROR(B60,0) -> Sales | C84: =IFERROR(C60,0) -> 25374.94 | D84: =IFERROR(D60,0) -> 30978.62 | E84: =IFERROR(E60,0) -> 41462.26 | F84: =IFERROR(F60,0) -> 42429.89 | G84: =IFERROR(G60,0) -> 44725.8 | H84: =IFERROR(H60,0) -> 52598.83 | I84: =IFERROR(I60,0) -> 63239.98 | ... K84: =IFERROR(K60,0) -> 75955.13
B85: =IFERROR(B61,0) -> Average Total Assets | C85: =IFERROR(C61,0) -> 41701.11 | D85: =IFERROR(D61,0) -> 49675.1 | E85: =IFERROR(E61,0) -> 66833.23 | F85: =IFERROR(F61,0) -> 77869.59 | G85: =IFERROR(G61,0) -> 82695.08 | H85: =IFERROR(H61,0) -> 84993.895 | I85: =IFERROR(I61,0) -> 87595.92 | ... K85: =IFERROR(K61,0) -> 117214.58
B86: Asset Turnover Ratio (B) | C86: =IFERROR(C84/C85,"-") -> 0.60849555 | D86: =IFERROR(D84/D85,"-") -> 0.62362471 | E86: =IFERROR(E84/E85,"-") -> 0.6203839 | F86: =IFERROR(F84/F85,"-") -> 0.54488395 | G86: =IFERROR(G84/G85,"-") -> 0.54085201 | H86: =IFERROR(H84/H85,"-") -> 0.61885421 | I86: =IFERROR(I84/I85,"-") -> 0.72195121 | J86: =IFERROR(J84/J85,"-") -> 0.73794421 | K86: =IFERROR(K84/K85,"-") -> 0.64800067
A88: # | B88: Return on Assets (A*B) | C88: =IFERROR(C82*C86,0) -> 0.06507045 | D88: =IFERROR(D82*D86,0) -> 0.044780182 | E88: =IFERROR(E82*E86,0) -> 0.035915966 | F88: =IFERROR(F82*F86,0) -> 0.073852707 | G88: =IFERROR(G82*G86,0) -> 0.066048065 | H88: =IFERROR(H82*H86,0) -> 0.08629161 | I88: =IFERROR(I82*I86,0) -> 0.057918223 | J88: =IFERROR(J82*J86,0) -> 0.072890527 | K88: =IFERROR(K82*K86,0) -> 0.051526352
B90: Check | C90: =IF(ABS(C76-C88)<0.0001,"✓ CHECK","✗ ERROR") -> ✓ CHECK | D90: =IF(ABS(D76-D88)<0.0001,"✓ CHECK","✗ ERROR") -> ✓ CHECK | E90: =IF(ABS(E76-E88)<0.0001,"✓ CHECK","✗ ERROR") -> ✓ CHECK | F90: =IF(ABS(F76-F88)<0.0001,"✓ CHECK","✗ ERROR") -> ✓ CHECK | G90: =IF(ABS(G76-G88)<0.0001,"✓ CHECK","✗ ERROR") -> ✓ CHECK | H90: =IF(ABS(H76-H88)<0.0001,"✓ CHECK","✗ ERROR") -> ✓ CHECK | I90: =IF(ABS(I76-I88)<0.0001,"✓ CHECK","✗ ERROR") -> ✓ CHECK | J90: =IF(ABS(J76-J88)<0.0001,"✓ CHECK","✗ ERROR") -> ✓ CHECK | K90: =IF(ABS(K76-K88)<0.0001,"✓ CHECK","✗ ERROR") -> ✓ CHECK
B92: DuPont Summary

Sheet Altman Z
B9: ULTRACEMCO | BSE Code : 532538
B10: =CONCATENATE("INR"," - ",DCF!E49) -> INR - 11937
B11: 52 Week High - INR 13102
B12: 52 Week Low - INR 10048
B14: About the company
B15: UltraTech Cement Limited is the cement flagship company of the Aditya Birla Group. A USD 8.9 billion building solutions powerhouse, UltraTech is the largest manufacturer of grey cement and ready-mix concrete (RMC) and one of the largest manufacturers of white cement in India. It is the second largest cement company globally by capacity and the largest by sales volume (excluding China).
B19: Altman Z's Score Summary
B41: Recent Updates
A50: # | B50: Working Capital/Total Assets
C51: ='Data Sheet'!C16 -> 42825 | D51: ='Data Sheet'!D16 -> 43190 | E51: ='Data Sheet'!E16 -> 43555 | F51: ='Data Sheet'!F16 -> 43921 | G51: ='Data Sheet'!G16 -> 44286 | H51: ='Data Sheet'!H16 -> 44651 | I51: ='Data Sheet'!I16 -> 45016 | J51: ='Data Sheet'!J16 -> 45382 | K51: ='Data Sheet'!K16 -> 45747
B52: Working Capital | C52: =IFERROR(Historical_FS!D78-Historical_FS!D64,0) -> -2936.22 | D52: =IFERROR(Historical_FS!E78-Historical_FS!E64,0) -> -5572.42 | E52: =IFERROR(Historical_FS!F78-Historical_FS!F64,0) -> -9812.05 | F52: =IFERROR(Historical_FS!G78-Historical_FS!G64,0) -> -10044.61 | G52: =IFERROR(Historical_FS!H78-Historical_FS!H64,0) -> -11685.03 | H52: =IFERROR(Historical_FS!I78-Historical_FS!I64,0) -> -13051 | I52: =IFERROR(Historical_FS!J78-Historical_FS!J64,0) -> -14369.68 | J52: =IFERROR(Historical_FS!K78-Historical_FS!K64,0) -> -15775.57 | K52: =IFERROR(Historical_FS!L78-Historical_FS!L64,0) -> -21696.56
B53: Total Assets | C53: =Historical_FS!D80 -> 42209.11 | D53: =Historical_FS!E80 -> 57141.09 | E53: =Historical_FS!F80 -> 76525.37 | F53: =Historical_FS!G80 -> 79213.81 | G53: =Historical_FS!H80 -> 86176.35 | H53: =Historical_FS!I80 -> 83811.44 | I53: =Historical_FS!J80 -> 91380.4 | J53: =Historical_FS!K80 -> 100797.11 | K53: =Historical_FS!L80 -> 133632.06
B54: Working Capital/Total Assets (A) | C54: =IFERROR(C52/C53,"-") -> -0.069563656 | D54: =IFERROR(D52/D53,"-") -> -0.097520366 | E54: =IFERROR(E52/E53,"-") -> -0.12821957 | F54: =IFERROR(F52/F53,"-") -> -0.12680377 | G54: =IFERROR(G52/G53,"-") -> -0.13559439 | H54: =IFERROR(H52/H53,"-") -> -0.1557186 | I54: =IFERROR(I52/I53,"-") -> -0.15725123 | J54: =IFERROR(J52/J53,"-") -> -0.15650816 | K54: =IFERROR(K52/K53,"-") -> -0.16236044
B56: Retained Earnings/Total Assets
C57: =C51 -> 42825 | D57: =D51 -> 43190 | E57: =E51 -> 43555 | F57: =F51 -> 43921 | G57: =G51 -> 44286 | H57: =H51 -> 44651 | I57: =I51 -> 45016 | J57: =J51 -> 45382 | K57: =K51 -> 45747
B58: Retained Earnings | C58: =Historical_FS!D57*Historical_FS!D45 -> 2439 | D58: =Historical_FS!E57*Historical_FS!E45 -> 1936.12 | E58: =Historical_FS!F57*Historical_FS!F45 -> 2084.54 | F58: =Historical_FS!G57*Historical_FS!G45 -> 5375.66 | G58: =Historical_FS!H57*Historical_FS!H45 -> 4393.85 | H58: =Historical_FS!I57*Historical_FS!I45 -> 6237.31 | I58: =Historical_FS!J57*Historical_FS!J45 -> 3976.38 | J58: =Historical_FS!K57*Historical_FS!K45 -> 4983.13 | K58: =Historical_FS!L57*Historical_FS!L45 -> 3755.87
B59: Total Assets | C59: =C53 -> 42209.11 | D59: =D53 -> 57141.09 | E59: =E53 -> 76525.37 | F59: =F53 -> 79213.81 | G59: =G53 -> 86176.35 | H59: =H53 -> 83811.44 | I59: =I53 -> 91380.4 | J59: =J53 -> 100797.11 | K59: =K53 -> 133632.06
B60: Retained Earnings/Total Assets (B) | C60: =IFERROR(C58/C59,0) -> 0.057783734 | D60: =IFERROR(D58/D59,0) -> 0.033883148 | E60: =IFERROR(E58/E59,0) -> 0.027239855 | F60: =IFERROR(F58/F59,0) -> 0.067862662 | G60: =IFERROR(G58/G59,0) -> 0.050986727 | H60: =IFERROR(H58/H59,0) -> 0.074420747 | I60: =IFERROR(I58/I59,0) -> 0.043514583 | J60: =IFERROR(J58/J59,0) -> 0.049437231 | K60: =IFERROR(K58/K59,0) -> 0.028106055
B62: EBIT/Total Assets
C63: =C57 -> 42825 | D63: =D57 -> 43190 | E63: =E57 -> 43555 | F63: =F57 -> 43921 | G63: =G57 -> 44286 | H63: =H57 -> 44651 | I63: =I57 -> 45016 | J63: =J57 -> 45382 | K63: =K57 -> 45747
B64: EBIT | C64: =Historical_FS!D33 -> 4512.15 | D64: =Historical_FS!E33 -> 4539.07 | E64: =Historical_FS!F33 -> 5246.31 | F64: =Historical_FS!G33 -> 7174.37 | G64: =Historical_FS!H33 -> 9486.2 | H64: =Historical_FS!I33 -> 9469.03 | I64: =Historical_FS!J33 -> 8238.97 | J64: =Historical_FS!K33 -> 10390.22 | K64: =Historical_FS!L33 -> 9178.67
B65: Total Assets | C65: =C59 -> 42209.11 | D65: =D59 -> 57141.09 | E65: =E59 -> 76525.37 | F65: =F59 -> 79213.81 | G65: =G59 -> 86176.35 | H65: =H59 -> 83811.44 | I65: =I59 -> 91380.4 | J65: =J59 -> 100797.11 | K65: =K59 -> 133632.06
B66: EBIT/Total Assets (C) | C66: =IFERROR(C64/C65,0) -> 0.10689991 | D66: =IFERROR(D64/D65,0) -> 0.079436182 | E66: =IFERROR(E64/E65,0) -> 0.06855648 | F66: =IFERROR(F64/F65,0) -> 0.090569687 | G66: =IFERROR(G64/G65,0) -> 0.11007893 | H66: =IFERROR(H64/H65,0) -> 0.11298016 | I66: =IFERROR(I64/I65,0) -> 0.090161238 | J66: =IFERROR(J64/J65,0) -> 0.10308053 | K66: =IFERROR(K64/K65,0) -> 0.068686137
B68: Market Cap/Long Term Liabilities
C69: =C63 -> 42825 | D69: =D63 -> 43190 | E69: =E63 -> 43555 | F69: =F63 -> 43921 | G69: =G63 -> 44286 | H69: =H63 -> 44651 | I69: =I63 -> 45016 | J69: =J63 -> 45382 | K69: =K63 -> 45747
B70: Market Cap | C70: =('Data Sheet'!C70*'Data Sheet'!C90)/10000000 -> 109384.54 | D70: =('Data Sheet'!D70*'Data Sheet'!D90)/10000000 -> 108472.52 | E70: =('Data Sheet'!E70*'Data Sheet'!E90)/10000000 -> 109811.77 | F70: =('Data Sheet'!F70*'Data Sheet'!F90)/10000000 -> 93654.517 | G70: =('Data Sheet'!G70*'Data Sheet'!G90)/10000000 -> 194493.22 | H70: =('Data Sheet'!H70*'Data Sheet'!H90)/10000000 -> 190589.15 | I70: =('Data Sheet'!I70*'Data Sheet'!I90)/10000000 -> 220041.06 | J70: =('Data Sheet'!J70*'Data Sheet'!J90)/10000000 -> 281444.65 | K70: =('Data Sheet'!K70*'Data Sheet'!K90)/10000000 -> 339160.44
B71: Long Term Liabilities | C71: ='Data Sheet'!C59 -> 8474.49 | D71: ='Data Sheet'!D59 -> 19480.22 | E71: ='Data Sheet'!E59 -> 25337 | F71: ='Data Sheet'!F59 -> 23018.96 | G71: ='Data Sheet'!G59 -> 21719.39 | H71: ='Data Sheet'!H59 -> 11298.8 | I71: ='Data Sheet'!I59 -> 11057.74 | J71: ='Data Sheet'!J59 -> 11402.95 | K71: ='Data Sheet'!K59 -> 24102.18
B72: Market Cap/Long Term Liabilities (D) | C72: =IFERROR(C70/C71,0) -> 12.907507 | D72: =IFERROR(D70/D71,0) -> 5.5683418 | E72: =IFERROR(E70/E71,0) -> 4.3340479 | F72: =IFERROR(F70/F71,0) -> 4.0685816 | G72: =IFERROR(G70/G71,0) -> 8.9548195 | H72: =IFERROR(H70/H71,0) -> 16.868088 | I72: =IFERROR(I70/I71,0) -> 19.89928 | J72: =IFERROR(J70/J71,0) -> 24.68174 | K72: =IFERROR(K70/K71,0) -> 14.071774
B74: Sales/Total Assets
C75: =C69 -> 42825 | D75: =D69 -> 43190 | E75: =E69 -> 43555 | F75: =F69 -> 43921 | G75: =G69 -> 44286 | H75: =H69 -> 44651 | I75: =I69 -> 45016 | J75: =J69 -> 45382 | K75: =K69 -> 45747
B76: Sales | C76: ='Data Sheet'!C17 -> 25374.94 | D76: ='Data Sheet'!D17 -> 30978.62 | E76: ='Data Sheet'!E17 -> 41462.26 | F76: ='Data Sheet'!F17 -> 42429.89 | G76: ='Data Sheet'!G17 -> 44725.8 | H76: ='Data Sheet'!H17 -> 52598.83 | I76: ='Data Sheet'!I17 -> 63239.98 | J76: ='Data Sheet'!J17 -> 70908.14 | K76: ='Data Sheet'!K17 -> 75955.13
B77: Total Assets | C77: =C65 -> 42209.11 | D77: =D65 -> 57141.09 | E77: =E65 -> 76525.37 | F77: =F65 -> 79213.81 | G77: =G65 -> 86176.35 | H77: =H65 -> 83811.44 | I77: =I65 -> 91380.4 | J77: =J65 -> 100797.11 | K77: =K65 -> 133632.06
B78: Sales/Total Assets (E) | C78: =IFERROR(C76/C77,0) -> 0.60117212 | D78: =IFERROR(D76/D77,0) -> 0.54214262 | E78: =IFERROR(E76/E77,0) -> 0.54181064 | F78: =IFERROR(F76/F77,0) -> 0.53563754 | G78: =IFERROR(G76/G77,0) -> 0.51900318 | H78: =IFERROR(H76/H77,0) -> 0.62758533 | I78: =IFERROR(I76/I77,0) -> 0.69205191 | J78: =IFERROR(J76/J77,0) -> 0.70347394 | K78: =IFERROR(K76/K77,0) -> 0.56839003
A80: # | B80: Altman's Z Score
C81: =C51 -> 42825 | D81: =D51 -> 43190 | E81: =E51 -> 43555 | F81: =F51 -> 43921 | G81: =G51 -> 44286 | H81: =H51 -> 44651 | I81: =I51 -> 45016 | J81: =J51 -> 45382 | K81: =K51 -> 45747
B82: Final Score | C82: =(C54*1.2)+(C60*1.4)+(C66*3.3)+(C72*0.6)+(C78*1) -> 8.6958668 | D82: =(D54*1.2)+(D60*1.4)+(D66*3.3)+(D72*0.6)+(D78*1) -> 4.0756991 | E82: =(E54*1.2)+(E60*1.4)+(E66*3.3)+(E72*0.6)+(E78*1) -> 3.2527481 | F82: =(F54*1.2)+(F60*1.4)+(F66*3.3)+(F72*0.6)+(F78*1) -> 3.2185097 | G82: =(G54*1.2)+(G60*1.4)+(G66*3.3)+(G72*0.6)+(G78*1) -> 6.1638235 | H82: =(H54*1.2)+(H60*1.4)+(H66*3.3)+(H72*0.6)+(H78*1) -> 11.038599 | I82: =(I54*1.2)+(I60*1.4)+(I66*3.3)+(I72*0.6)+(I78*1) -> 12.801371 | J82: =(J54*1.2)+(J60*1.4)+(J66*3.3)+(J72*0.6)+(J78*1) -> 15.734086 | K82: =(K54*1.2)+(K60*1.4)+(K66*3.3)+(K72*0.6)+(K78*1) -> 9.0826348
B83: Financial Stability | C83: =IF(C82<1.81,"Distressed",IF(C82>3,"Strong","Grey Zone")) -> Strong | D83: =IF(D82<1.81,"Distressed",IF(D82>3,"Strong","Grey Zone")) -> Strong | E83: =IF(E82<1.81,"Distressed",IF(E82>3,"Strong","Grey Zone")) -> Strong | F83: =IF(F82<1.81,"Distressed",IF(F82>3,"Strong","Grey Zone")) -> Strong | G83: =IF(G82<1.81,"Distressed",IF(G82>3,"Strong","Grey Zone")) -> Strong | H83: =IF(H82<1.81,"Distressed",IF(H82>3,"Strong","Grey Zone")) -> Strong | I83: =IF(I82<1.81,"Distressed",IF(I82>3,"Strong","Grey Zone")) -> Strong | J83: =IF(J82<1.81,"Distressed",IF(J82>3,"Strong","Grey Zone")) -> Strong | K83: =IF(K82<1.81,"Distressed",IF(K82>3,"Strong","Grey Zone")) -> Strong

Sheet Summary
B9: Valuation Summary - UltraTech Cement Ltd.
B11: Historical Financials
B30: DCF Valuation Summary
B32: Enterprise Value: | D32: =DCF!E40 -> 67397.823
B33: Equity Value per Share: | D33: =DCF!E47 -> 1561.1671
B34: Weighted Average Cost of Capital: | D34: =WACC!J48 -> 0.1270321
B35: Premium/Discount | D35: =DCF!E50 -> 7.6462025
B37: The value of DCF is lower than the current price of the share implying that the share is trading at premium in the market.
B39: Relative Valuation Summary
B41: EV/Revenue Implied Value: Rs. 8,889.83 Cr.
B42: EV/EBITDA Implied Value: Rs. 8,561.03 Cr.
B43: P/E Implied Value: Rs. 10,160.97 Cr.
B45: Market multiples imply a much closer valuation range compared to DCF results. Even if we look at the multiples the stock is still overvalued
B47: Sources
B49: The Valuation School
B50: Screener.in
B51: moneycontrol
B52: UltraTech Cement Annual Reports
B53: Investing.com
... B56: Disclaimer:

Sheet Data Sheet
A1: COMPANY NAME | B1: ULTRATECH CEMENT LTD | E1: =IF(B2<>B3, "A NEW VERSION OF THE WORKSHEET IS AVAILABLE", "")
A2: LATEST VERSION | B2: 2.1 | E2: PLEASE DO NOT MAKE ANY CHANGES TO THIS SHEET
A3: CURRENT VERSION | B3: 2.1
A5: META
A6: Number of shares | B6: =IF(B9>0, B9/B8, 0) -> 29.490848
A7: Face Value | B7: 10
A8: Current Price | B8: 12342
A9: Market Capitalization | B9: 363976.05
A15: PROFIT & LOSS
A16: Report Date | B16: 42460 | C16: 42825 | D16: 43190 | E16: 43555 | F16: 43921 | G16: 44286 | H16: 44651 | I16: 45016 | J16: 45382 | K16: 45747
A17: Sales | B17: 25153.24 | C17: 25374.94 | D17: 30978.62 | E17: 41462.26 | F17: 42429.89 | G17: 44725.8 | H17: 52598.83 | I17: 63239.98 | J17: 70908.14 | K17: 75955.13
A18: Raw Material Cost | B18: 4436.12 | C18: 4416.9 | D18: 5399.98 | E18: 6936.74 | F18: 6875.89 | G18: 6635.66 | H18: 8348.15 | I18: 10233.17 | J18: 11986.27 | K18: 13691.46
A19: Change in Inventory | B19: 18.61 | C19: -75.69 | D19: 111.2 | E19: -46.35 | F19: 357.83 | G19: -450.15 | H19: 383.16 | I19: 518.21 | J19: 83.35 | K19: -12.27
A20: Power and Fuel | B20: 4579.25 | C20: 4271.98 | D20: 6334.07 | E20: 9436.14 | F20: 8516.87 | G20: 8331.18 | H20: 12137.26 | I20: 18491.32 | J20: 18283.32 | K20: 18419.15
A21: Other Mfr. Exp | B21: 1933.88 | C21: 1991.28 | D21: 2289.53 | E21: 3001.06 | F21: 3043.3 | G21: 3067.38 | H21: 3889.67 | I21: 4344.34 | J21: 4898.17 | K21: 5474.61
A22: Employee Cost | B22: 1466.49 | C22: 1547.77 | D22: 1831.81 | E22: 2309.43 | F22: 2522.64 | G22: 2363.33 | H22: 2545 | I22: 2751.31 | J22: 3051.99 | K22: 3619.25
A23: Selling and admin | B23: 7200.47 | C23: 7149.12 | D23: 8320.28 | E23: 11563.8 | F23: 11237.32 | G23: 11266.02 | H23: 13282.22 | I23: 15859.6 | J23: 18066.95 | K23: 19571.95
A24: Other Expenses | B24: 654.67 | C24: 709.76 | D24: 769.12 | E24: 821.8 | F24: 1345.73 | G24: 1044.17 | H24: 1265.34 | I24: 1458.6 | J24: 1726.23 | K24: 2369.56
A25: Other Income | B25: 463.81 | C25: 648.12 | D25: 241.97 | E25: 350.1 | F25: 651.06 | G25: 618.52 | H25: 669.43 | I25: 507.11 | J25: 556.96 | K25: 396.74
A26: Depreciation | B26: 1377.17 | C26: 1348.41 | D26: 1847.93 | E26: 2450.73 | F26: 2722.66 | G26: 2700.23 | H26: 2714.75 | I26: 2887.99 | J26: 3145.3 | K26: 4014.95
A27: Interest | B27: 566.3 | C27: 640.1 | D27: 1237.6 | E27: 1777.86 | F27: 1991.65 | G27: 1485.65 | H27: 944.71 | I27: 822.72 | J27: 968 | K27: 1650.54
... A31: Dividend Amount | B31: 260.71 | C31: 274.51 | D31: 288.34 | E31: 315.84 | F31: 375.22 | G31: 1068 | H31: 1096.95 | I31: 1097.02 | J31: 2020.83 | K31: 2283.77
A40: Quarters
A41: Report Date | B41: 45107 | C41: 45199 | D41: 45291 | E41: 45382 | F41: 45473 | G41: 45565 | H41: 45657 | I41: 45747 | J41: 45838 | K41: 45930
A42: Sales | B42: 17737.1 | C42: 16012.13 | D42: 16739.97 | E42: 20418.94 | F42: 18818.56 | G42: 16294.42 | H42: 17778.83 | I42: 23063.32 | J42: 21275.45 | K42: 19606.93
A43: Expenses | B43: 14687.92 | C43: 13461.24 | D43: 13485.4 | E43: 16305.02 | F43: 15801.46 | G43: 14268.68 | H43: 14885.35 | I43: 18455.65 | J43: 16869.42 | K43: 16518.27
A44: Other Income | B44: 177.43 | C44: 170.62 | D44: 146.24 | E44: 72.67 | F44: 83.31 | G44: 226.22 | H44: 247.32 | I44: 92.78 | J44: 141.85 | K44: 174.14
A45: Depreciation | B45: 749.07 | C45: 797.83 | D45: 783.48 | E45: 814.92 | F45: 917.93 | G45: 979.67 | H45: 992.78 | I45: 1124.57 | J45: 1106.78 | K45: 1147.68
A46: Interest | B46: 210.75 | C46: 233.94 | D46: 262.16 | E46: 261.15 | F46: 325.76 | G46: 392.99 | H46: 456.75 | I46: 475.04 | J46: 433.3 | K46: 459.29
A47: Profit before tax | B47: 2266.79 | C47: 1689.74 | D47: 2355.17 | E47: 3110.52 | F47: 1856.72 | G47: 879.3 | H47: 1691.27 | I47: 3100.84 | J47: 3007.8 | K47: 1655.83
A48: Tax | B48: 576.57 | C48: 409.36 | D48: 580.39 | E48: 851.94 | F48: 363.27 | G48: 171.34 | H48: 327.83 | I48: 626.05 | J48: 786.89 | K48: 417.85
A49: Net profit | B49: 1688.45 | C49: 1281.45 | D49: 1776.98 | E49: 2258.12 | F49: 1494.82 | G49: 702.82 | H49: 1359.43 | I49: 2482.04 | J49: 2225.9 | K49: 1231.58
A50: Operating Profit | B50: 3049.18 | C50: 2550.89 | D50: 3254.57 | E50: 4113.92 | F50: 3017.1 | G50: 2025.74 | H50: 2893.48 | I50: 4607.67 | J50: 4406.03 | K50: 3088.66
A55: BALANCE SHEET
A56: Report Date | B56: 42460 | C56: 42825 | D56: 43190 | E56: 43555 | F56: 43921 | G56: 44286 | H56: 44651 | I56: 45016 | J56: 45382 | K56: 45747
A57: Equity Share Capital | B57: 274.43 | C57: 274.51 | D57: 274.61 | E57: 274.64 | F57: 288.63 | G57: 288.65 | H57: 288.67 | I57: 288.69 | J57: 288.69 | K57: 294.68
A58: Reserves | B58: 21671.2 | C58: 24117.38 | D58: 26106.55 | E58: 33476.01 | F58: 38755.13 | G58: 43886.03 | H58: 50146.6 | I58: 54035.85 | J58: 59938.79 | K58: 70412.09
A59: Borrowings | B59: 10615.99 | C59: 8474.49 | D59: 19480.22 | E59: 25337 | F59: 23018.96 | G59: 21719.39 | H59: 11298.8 | I59: 11057.74 | J59: 11402.95 | K59: 24102.18
A60: Other Liabilities | B60: 8631.49 | C60: 9342.73 | D60: 11279.71 | E60: 17437.72 | F60: 17151.09 | G60: 20282.28 | H60: 22077.37 | I60: 25998.12 | J60: 29166.68 | K60: 38823.11
A61: Total | B61: 41193.11 | C61: 42209.11 | D61: 57141.09 | E61: 76525.37 | F61: 79213.81 | G61: 86176.35 | H61: 83811.44 | I61: 91380.4 | J61: 100797.11 | K61: 133632.06
A62: Net Block | B62: 25309.42 | C62: 25903.75 | D62: 39715.3 | E62: 56644.62 | F62: 57150.96 | G62: 55411.61 | H62: 55487.57 | I62: 59579 | J62: 62877.61 | K62: 94564.22
A63: Capital Work in Progress | B63: 1469.09 | C63: 921.48 | D63: 1511.21 | E63: 1153.32 | F63: 919.59 | G63: 1686.68 | H63: 4784.67 | I63: 4040.39 | J63: 6811.18 | K63: 6234.19
A64: Investments | B64: 5095.18 | C64: 6690.51 | D64: 5446.9 | E64: 2921.33 | F64: 5928.69 | G64: 12178.11 | H64: 6335.77 | I64: 7296.95 | J64: 8248.95 | K64: 5156.47
A65: Other Assets | B65: 9319.42 | C65: 8693.37 | D65: 10467.68 | E65: 15806.1 | F65: 15214.57 | G65: 16899.95 | H65: 17203.43 | I65: 20464.06 | J65: 22859.37 | K65: 27677.18
A66: Total | B66: 41193.11 | C66: 42209.11 | D66: 57141.09 | E66: 76525.37 | F66: 79213.81 | G66: 86176.35 | H66: 83811.44 | I66: 91380.4 | J66: 100797.11 | K66: 133632.06
A67: Receivables | B67: 1928.21 | C67: 1757.09 | D67: 2220.63 | E67: 2787.03 | F67: 2383.22 | G67: 2571.73 | H67: 3071.61 | I67: 3867.02 | J67: 4278.16 | K67: 5890.25
... A70: No. of Equity Shares | B70: 274431377 | C70: 274507906 | D70: 274613985 | E70: 274642720 | F70: 288625105 | G70: 288653398 | H70: 288670847 | I70: 288686345 | J70: 288686345 | K70: 294677410
A71: New Bonus Shares
A72: Face value | B72: 10 | C72: 10 | D72: 10 | E72: 10 | F72: 10 | G72: 10 | H72: 10 | I72: 10 | J72: 10 | K72: 10
A80: CASH FLOW:
A81: Report Date | B81: 42460 | C81: 42825 | D81: 43190 | E81: 43555 | F81: 43921 | G81: 44286 | H81: 44651 | I81: 45016 | J81: 45382 | K81: 45747
A82: Cash from Operating Activity | B82: 4525.51 | C82: 5005.02 | D82: 3887.72 | E82: 5956.11 | F82: 8972.43 | G82: 12500.43 | H82: 9283.24 | I82: 9068.51 | J82: 10897.54 | K82: 10673.43
A83: Cash from Investing Activity | B83: -3673.35 | C83: -2501.44 | D83: 1865.72 | E83: 1165.18 | F83: -4191.95 | G83: -8856.15 | H83: 2256.54 | I83: -7187.68 | J83: -8788.68 | K83: -15835.56
A84: Cash from Financing Activity | B84: -844.02 | C84: -2534.98 | D84: -5735.05 | E84: -6757.24 | F84: -5075.88 | G84: -4356.47 | H84: -12497.93 | I84: -1631 | J84: -1925.65 | K84: 5075.76
A85: Net Cash Flow | B85: 8.14 | C85: -31.4 | D85: 18.39 | E85: 364.05 | F85: -295.4 | G85: -712.19 | H85: -958.15 | I85: 249.83 | J85: 183.21 | K85: -86.37
A90: PRICE: | B90: 3228.75 | C90: 3984.75 | D90: 3950 | E90: 3998.35 | F90: 3244.85 | G90: 6737.95 | H90: 6602.3 | I90: 7622.15 | J90: 9749.15 | K90: 11509.55
A92: DERIVED:
A93: Adjusted Equity Shares in Cr | B93: 27.44 | C93: 27.45 | D93: 27.46 | E93: 27.46 | F93: 28.86 | G93: 28.87 | H93: 28.87 | I93: 28.87 | J93: 28.87 | K93: 29.47

Sheet JKC_Beta
B5: Regression Beta
B7: =WACC!B18&" Returns" -> Shree Cement Returns | F7: Nifty Returns | I7: Beta Drifting
B9: Date | C9: Closing Price | D9: Weekly Returns | F9: Closing Price | G9: Weekly Returns | I9: Levered Raw Beta | J9: =J34 -> 1.0994856
B10: 45928 | C10: 6318 | F10: 24894.25 | I10: Raw Beta Weight | J10: 0.75
B11: 45921 | C11: 6347.5 | D11: =C11/C10-1 -> 0.0046691991 | F11: 24654.7 | G11: =F11/F10-1 -> -0.009622704
B12: 45914 | C12: 6862 | D12: =C12/C11-1 -> 0.081055534 | F12: 25327.05 | G12: =F12/F11-1 -> 0.027270662 | I12: Market Beta | J12: 1
B13: 45907 | C13: 6555 | D13: =C13/C12-1 -> -0.044739143 | F13: 25114 | G13: =F13/F12-1 -> -0.0084119548 | I13: Market Beta Weight | J13: 0.25
B14: 45900 | C14: 6634 | D14: =C14/C13-1 -> 0.012051869 | F14: 24741 | G14: =F14/F13-1 -> -0.014852274
B15: 45893 | C15: 6946.5 | D15: =C15/C14-1 -> 0.047105819 | F15: 24426.85 | G15: =F15/F14-1 -> -0.012697547 | I15: Adjusted Beta | J15: =(J9*J10)+(J12*J13) -> 1.0746142
B16: 45886 | C16: 6841 | D16: =C16/C15-1 -> -0.015187504 | F16: 24870.1 | G16: =F16/F15-1 -> 0.018146016
B17: 45879 | C17: 7001.5 | D17: =C17/C16-1 -> 0.023461482 | F17: 24631.3 | G17: =F17/F16-1 -> -0.0096018914 | I17: SUMMARY OUTPUT
B18: 45872 | C18: 7051 | D18: =C18/C17-1 -> 0.0070699136 | F18: 24363.3 | G18: =F18/F17-1 -> -0.010880465
B19: 45865 | C19: 6681.5 | D19: =C19/C18-1 -> -0.052403914 | F19: 24565.35 | G19: =F19/F18-1 -> 0.0082932115 | I19: Regression Statistics
B20: 45858 | C20: 6479 | D20: =C20/C19-1 -> -0.030307566 | F20: 24837 | G20: =F20/F19-1 -> 0.011058259 | I20: Multiple R | J20: 0.4920618
B21: 45851 | C21: 6498 | D21: =C21/C20-1 -> 0.0029325513 | F21: 24968.4 | G21: =F21/F20-1 -> 0.005290494 | I21: R Square | J21: 0.24212481
B22: 45844 | C22: 6447.5 | D22: =C22/C21-1 -> -0.007771622 | F22: 25149.85 | G22: =F22/F21-1 -> 0.0072671857 | I22: Adjusted R Square | J22: 0.2346211
B23: 45837 | C23: 6252 | D23: =C23/C22-1 -> -0.03032183 | F23: 25461 | G23: =F23/F22-1 -> 0.012371843 | I23: Standard Error | J23: 0.033981276
B24: 45830 | C24: 6336 | D24: =C24/C23-1 -> 0.013435701 | F24: 25637.8 | G24: =F24/F23-1 -> 0.0069439535 | I24: Observations | J24: 103
B25: 45823 | C25: 5693.5 | D25: =C25/C24-1 -> -0.10140467 | F25: 25112.4 | G25: =F25/F24-1 -> -0.020493178
B26: 45816 | C26: 6082.5 | D26: =C26/C25-1 -> 0.068323527 | F26: 24718.6 | G26: =F26/F25-1 -> -0.015681496 | I26: ANOVA
B27: 45809 | C27: 5876.5 | D27: =C27/C26-1 -> -0.033867653 | F27: 25003.05 | G27: =F27/F26-1 -> 0.011507529 | J27: df | K27: SS | L27: MS | M27: F | N27: Significance F
B28: 45802 | C28: 5497.5 | D28: =C28/C27-1 -> -0.064494172 | F28: 24750.7 | G28: =F28/F27-1 -> -0.010092769 | I28: Regression | J28: 1 | K28: 0.037259956 | L28: 0.037259956 | M28: 32.267326 | N28: 1.3002657e-07
B29: 45795 | C29: 5108.5 | D29: =C29/C28-1 -> -0.070759436 | F29: 24853.15 | G29: =F29/F28-1 -> 0.0041392769 | I29: Residual | J29: 101 | K29: 0.11662744 | L29: 0.0011547271
B30: 45788 | C30: 5251.5 | D30: =C30/C29-1 -> 0.027992561 | F30: 25019.8 | G30: =F30/F29-1 -> 0.0067053874 | I30: Total | J30: 102 | K30: 0.15388739
B31: 45781 | C31: 5108 | D31: =C31/C30-1 -> -0.027325526 | F31: 24008 | G31: =F31/F30-1 -> -0.040439972
B32: 45774 | C32: 5162 | D32: =C32/C31-1 -> 0.010571652 | F32: 24346.7 | G32: =F32/F31-1 -> 0.014107797 | J32: Coefficients | K32: Standard Error | L32: t Stat | M32: P-value | N32: Lower 95% | O32: Upper 95% | P32: Lower 95.0% | Q32: Upper 95.0%
B33: 45767 | C33: 5245.3 | D33: =C33/C32-1 -> 0.016137156 | F33: 24039.35 | G33: =F33/F32-1 -> -0.012623887 | I33: Intercept | J33: -0.0033860315 | K33: 0.0033727397 | L33: -1.0039409 | M33: 0.31780628 | N33: -0.01007664 | O33: 0.0033045769 | P33: -0.01007664 | Q33: 0.0033045769
B34: 45760 | C34: 5060.8 | D34: =C34/C33-1 -> -0.035174347 | F34: 23851.65 | G34: =F34/F33-1 -> -0.0078080314 | I34: X Variable 1 | J34: 1.0994856 | K34: 0.19355662 | L34: 5.6804337 | M34: 1.3002657e-07 | N34: 0.71552128 | O34: 1.4834498 | P34: 0.71552128 | Q34: 1.4834498
B35: 45753 | C35: 4957.45 | D35: =C35/C34-1 -> -0.020421672 | F35: 22828.55 | G35: =F35/F34-1 -> -0.042894307
B36: 45746 | C36: 4954.7 | D36: =C36/C35-1 -> -0.00055472067 | F36: 22904.45 | G36: =F36/F35-1 -> 0.0033247841
B37: 45739 | C37: 4932.65 | D37: =C37/C36-1 -> -0.0044503199 | F37: 23519.35 | G37: =F37/F36-1 -> 0.026846312
B38: 45732 | C38: 4822.5 | D38: =C38/C37-1 -> -0.022330796 | F38: 23350.4 | G38: =F38/F37-1 -> -0.0071834468
B39: 45725 | C39: 4271.3 | D39: =C39/C38-1 -> -0.11429756 | F39: 22397.2 | G39: =F39/F38-1 -> -0.040821571
B40: 45718 | C40: 4421.55 | D40: =C40/C39-1 -> 0.035176644 | F40: 22552.5 | G40: =F40/F39-1 -> 0.0069339025
B41: 45711 | C41: 4389.35 | D41: =C41/C40-1 -> -0.0072825141 | F41: 22124.7 | G41: =F41/F40-1 -> -0.018969072
B42: 45704 | C42: 4580.15 | D42: =C42/C41-1 -> 0.043468851 | F42: 22795.9 | G42: =F42/F41-1 -> 0.030337135
B43: 45697 | C43: 4657.25 | D43: =C43/C42-1 -> 0.01683351 | F43: 22929.25 | G43: =F43/F42-1 -> 0.0058497361
B44: 45690 | C44: 4879.7 | D44: =C44/C43-1 -> 0.047764239 | F44: 23559.95 | G44: =F44/F43-1 -> 0.027506351
B45: 45683 | C45: 4834.85 | D45: =C45/C44-1 -> -0.0091911388 | F45: 23508.4 | G45: =F45/F44-1 -> -0.0021880352
B46: 45676 | C46: 4755.9 | D46: =C46/C45-1 -> -0.016329359 | F46: 23092.2 | G46: =F46/F45-1 -> -0.01770431
... B113: 45207 | C113: 3246.2 | D113: =C113/C112-1 -> -0.0156259 | F113: 19751.05 | G113: =F113/F112-1 -> 0.010663856

Sheet ShreeC_Beta
B5: Regression Beta
B7: =WACC!B18&" Returns" -> Shree Cement Returns | F7: Nifty Returns | I7: Beta Drifting
B9: Date | C9: Closing Price | D9: Weekly Returns | F9: Closing Price | G9: Weekly Returns | I9: Levered Raw Beta | J9: =J34 -> 0.80764538
B10: 45928 | C10: 29180 | F10: 24894.25 | I10: Raw Beta Weight | J10: 0.75
B11: 45921 | C11: 28910 | D11: =C11/C10-1 -> -0.009252913 | F11: 24654.7 | G11: =F11/F10-1 -> -0.009622704
B12: 45914 | C12: 29880 | D12: =C12/C11-1 -> 0.033552404 | F12: 25327.05 | G12: =F12/F11-1 -> 0.027270662 | I12: Market Beta | J12: 1
B13: 45907 | C13: 29580 | D13: =C13/C12-1 -> -0.010040161 | F13: 25114 | G13: =F13/F12-1 -> -0.0084119548 | I13: Market Beta Weight | J13: 0.25
B14: 45900 | C14: 30040 | D14: =C14/C13-1 -> 0.015551048 | F14: 24741 | G14: =F14/F13-1 -> -0.014852274
B15: 45893 | C15: 29275 | D15: =C15/C14-1 -> -0.025466045 | F15: 24426.85 | G15: =F15/F14-1 -> -0.012697547 | I15: Adjusted Beta | J15: =(J9*J10)+(J12*J13) -> 0.85573404
B16: 45886 | C16: 30005 | D16: =C16/C15-1 -> 0.024935952 | F16: 24870.1 | G16: =F16/F15-1 -> 0.018146016
B17: 45879 | C17: 30400 | D17: =C17/C16-1 -> 0.013164473 | F17: 24631.3 | G17: =F17/F16-1 -> -0.0096018914 | I17: SUMMARY OUTPUT
B18: 45872 | C18: 30415 | D18: =C18/C17-1 -> 0.00049342105 | F18: 24363.3 | G18: =F18/F17-1 -> -0.010880465
B19: 45865 | C19: 30675 | D19: =C19/C18-1 -> 0.0085484136 | F19: 24565.35 | G19: =F19/F18-1 -> 0.0082932115 | I19: Regression Statistics
B20: 45858 | C20: 30950 | D20: =C20/C19-1 -> 0.0089649552 | F20: 24837 | G20: =F20/F19-1 -> 0.011058259 | I20: Multiple R | J20: 0.43772362
B21: 45851 | C21: 30790 | D21: =C21/C20-1 -> -0.0051696284 | F21: 24968.4 | G21: =F21/F20-1 -> 0.005290494 | I21: R Square | J21: 0.19160196
B22: 45844 | C22: 31210 | D22: =C22/C21-1 -> 0.013640792 | F22: 25149.85 | G22: =F22/F21-1 -> 0.0072671857 | I22: Adjusted R Square | J22: 0.18359802
B23: 45837 | C23: 31315 | D23: =C23/C22-1 -> 0.0033643063 | F23: 25461 | G23: =F23/F22-1 -> 0.012371843 | I23: Standard Error | J23: 0.028980396
B24: 45830 | C24: 31030 | D24: =C24/C23-1 -> -0.0091010698 | F24: 25637.8 | G24: =F24/F23-1 -> 0.0069439535 | I24: Observations | J24: 103
B25: 45823 | C25: 28875 | D25: =C25/C24-1 -> -0.06944892 | F25: 25112.4 | G25: =F25/F24-1 -> -0.020493178
B26: 45816 | C26: 29610 | D26: =C26/C25-1 -> 0.025454545 | F26: 24718.6 | G26: =F26/F25-1 -> -0.015681496 | I26: ANOVA
B27: 45809 | C27: 29600 | D27: =C27/C26-1 -> -0.00033772374 | F27: 25003.05 | G27: =F27/F26-1 -> 0.011507529 | J27: df | K27: SS | L27: MS | M27: F | N27: Significance F
B28: 45802 | C28: 29595 | D28: =C28/C27-1 -> -0.00016891892 | F28: 24750.7 | G28: =F28/F27-1 -> -0.010092769 | I28: Regression | J28: 1 | K28: 0.020105029 | L28: 0.020105029 | M28: 23.938453 | N28: 3.769609e-06
B29: 45795 | C29: 31495 | D29: =C29/C28-1 -> 0.064200034 | F29: 24853.15 | G29: =F29/F28-1 -> 0.0041392769 | I29: Residual | J29: 101 | K29: 0.084826197 | L29: 0.00083986334
B30: 45788 | C30: 31615 | D30: =C30/C29-1 -> 0.0038101286 | F30: 25019.8 | G30: =F30/F29-1 -> 0.0067053874 | I30: Total | J30: 102 | K30: 0.10493123
B31: 45781 | C31: 29230 | D31: =C31/C30-1 -> -0.075438874 | F31: 24008 | G31: =F31/F30-1 -> -0.040439972
B32: 45774 | C32: 29335 | D32: =C32/C31-1 -> 0.0035921998 | F32: 24346.7 | G32: =F32/F31-1 -> 0.014107797 | J32: Coefficients | K32: Standard Error | L32: t Stat | M32: P-value | N32: Lower 95% | O32: Upper 95% | P32: Lower 95.0% | Q32: Upper 95.0%
B33: 45767 | C33: 30540 | D33: =C33/C32-1 -> 0.041077212 | F33: 24039.35 | G33: =F33/F32-1 -> -0.012623887 | I33: Intercept | J33: 0.0013922486 | K33: 0.002876388 | L33: 0.48402671 | M33: 0.62941478 | N33: -0.0043137314 | O33: 0.0070982286 | P33: -0.0043137314 | Q33: 0.0070982286
B34: 45760 | C34: 31000 | D34: =C34/C33-1 -> 0.015062213 | F34: 23851.65 | G34: =F34/F33-1 -> -0.0078080314 | I34: X Variable 1 | J34: 0.80764538 | K34: 0.16507172 | L34: 4.8926939 | M34: 3.769609e-06 | N34: 0.4801875 | O34: 1.1351033 | P34: 0.4801875 | Q34: 1.1351033
B35: 45753 | C35: 30107.95 | D35: =C35/C34-1 -> -0.028775806 | F35: 22828.55 | G35: =F35/F34-1 -> -0.042894307
B36: 45746 | C36: 30694.5 | D36: =C36/C35-1 -> 0.019481566 | F36: 22904.45 | G36: =F36/F35-1 -> 0.0033247841
B37: 45739 | C37: 30502.95 | D37: =C37/C36-1 -> -0.0062405317 | F37: 23519.35 | G37: =F37/F36-1 -> 0.026846312
B38: 45732 | C38: 28987.4 | D38: =C38/C37-1 -> -0.049685358 | F38: 23350.4 | G38: =F38/F37-1 -> -0.0071834468
B39: 45725 | C39: 27495.15 | D39: =C39/C38-1 -> -0.051479263 | F39: 22397.2 | G39: =F39/F38-1 -> -0.040821571
B40: 45718 | C40: 27985.2 | D40: =C40/C39-1 -> 0.017823143 | F40: 22552.5 | G40: =F40/F39-1 -> 0.0069339025
B41: 45711 | C41: 27284 | D41: =C41/C40-1 -> -0.025056101 | F41: 22124.7 | G41: =F41/F40-1 -> -0.018969072
B42: 45704 | C42: 28405.7 | D42: =C42/C41-1 -> 0.041112007 | F42: 22795.9 | G42: =F42/F41-1 -> 0.030337135
B43: 45697 | C43: 28556.05 | D43: =C43/C42-1 -> 0.0052929518 | F43: 22929.25 | G43: =F43/F42-1 -> 0.0058497361
B44: 45690 | C44: 28249.1 | D44: =C44/C43-1 -> -0.010749036 | F44: 23559.95 | G44: =F44/F43-1 -> 0.027506351
B45: 45683 | C45: 27795.9 | D45: =C45/C44-1 -> -0.016042989 | F45: 23508.4 | G45: =F45/F44-1 -> -0.0021880352
B46: 45676 | C46: 25783.15 | D46: =C46/C45-1 -> -0.072411759 | F46: 23092.2 | G46: =F46/F45-1 -> -0.01770431
... B113: 45207 | C113: 26851.15 | D113: =C113/C112-1 -> 0.029385098 | F113: 19751.05 | G113: =F113/F112-1 -> 0.010663856

Sheet Ambuja_Beta
B5: Regression Beta
B7: =WACC!B17&" Returns" -> Ambuja Cements Returns | F7: Nifty Returns | I7: Beta Drifting
B9: Date | C9: Closing Price | D9: Weekly Returns | F9: Closing Price | G9: Weekly Returns | I9: Levered Raw Beta | J9: =J34 -> 1.0716281
B10: 45928 | C10: 576.15 | F10: 24894.25 | I10: Raw Beta Weight | J10: 0.75
B11: 45921 | C11: 565.2 | D11: =C11/C10-1 -> -0.019005467 | F11: 24654.7 | G11: =F11/F10-1 -> -0.009622704
B12: 45914 | C12: 582.45 | D12: =C12/C11-1 -> 0.03052017 | F12: 25327.05 | G12: =F12/F11-1 -> 0.027270662 | I12: Market Beta | J12: 1
B13: 45907 | C13: 560.55 | D13: =C13/C12-1 -> -0.037599794 | F13: 25114 | G13: =F13/F12-1 -> -0.0084119548 | I13: Market Beta Weight | J13: 0.25
B14: 45900 | C14: 566.7 | D14: =C14/C13-1 -> 0.010971367 | F14: 24741 | G14: =F14/F13-1 -> -0.014852274
B15: 45893 | C15: 563.2 | D15: =C15/C14-1 -> -0.0061761073 | F15: 24426.85 | G15: =F15/F14-1 -> -0.012697547 | I15: Adjusted Beta | J15: =(J9*J10)+(J12*J13) -> 1.0537211
B16: 45886 | C16: 577.15 | D16: =C16/C15-1 -> 0.024769176 | F16: 24870.1 | G16: =F16/F15-1 -> 0.018146016
B17: 45879 | C17: 578.05 | D17: =C17/C16-1 -> 0.0015593866 | F17: 24631.3 | G17: =F17/F16-1 -> -0.0096018914 | I17: SUMMARY OUTPUT
B18: 45872 | C18: 580 | D18: =C18/C17-1 -> 0.0033734106 | F18: 24363.3 | G18: =F18/F17-1 -> -0.010880465
B19: 45865 | C19: 607.95 | D19: =C19/C18-1 -> 0.048189655 | F19: 24565.35 | G19: =F19/F18-1 -> 0.0082932115 | I19: Regression Statistics
B20: 45858 | C20: 613.1 | D20: =C20/C19-1 -> 0.0084710914 | F20: 24837 | G20: =F20/F19-1 -> 0.011058259 | I20: Multiple R | J20: 0.50260007
B21: 45851 | C21: 596.7 | D21: =C21/C20-1 -> -0.026749307 | F21: 24968.4 | G21: =F21/F20-1 -> 0.005290494 | I21: R Square | J21: 0.25260683
B22: 45844 | C22: 587.15 | D22: =C22/C21-1 -> -0.016004692 | F22: 25149.85 | G22: =F22/F21-1 -> 0.0072671857 | I22: Adjusted R Square | J22: 0.2452069
B23: 45837 | C23: 595.75 | D23: =C23/C22-1 -> 0.014647024 | F23: 25461 | G23: =F23/F22-1 -> 0.012371843 | I23: Standard Error | J23: 0.03220083
B24: 45830 | C24: 574.95 | D24: =C24/C23-1 -> -0.034913974 | F24: 25637.8 | G24: =F24/F23-1 -> 0.0069439535 | I24: Observations | J24: 103
B25: 45823 | C25: 533.45 | D25: =C25/C24-1 -> -0.07218019 | F25: 25112.4 | G25: =F25/F24-1 -> -0.020493178
B26: 45816 | C26: 542.5 | D26: =C26/C25-1 -> 0.016965039 | F26: 24718.6 | G26: =F26/F25-1 -> -0.015681496 | I26: ANOVA
B27: 45809 | C27: 555.15 | D27: =C27/C26-1 -> 0.023317972 | F27: 25003.05 | G27: =F27/F26-1 -> 0.011507529 | J27: df | K27: SS | L27: MS | M27: F | N27: Significance F
B28: 45802 | C28: 553.5 | D28: =C28/C27-1 -> -0.0029721697 | F28: 24750.7 | G28: =F28/F27-1 -> -0.010092769 | I28: Regression | J28: 1 | K28: 0.03539578 | L28: 0.03539578 | M28: 34.13637 | N28: 6.3097538e-08
B29: 45795 | C29: 570.9 | D29: =C29/C28-1 -> 0.031436314 | F29: 24853.15 | G29: =F29/F28-1 -> 0.0041392769 | I29: Residual | J29: 101 | K29: 0.10472624 | L29: 0.0010368935
B30: 45788 | C30: 563.5 | D30: =C30/C29-1 -> -0.01296199 | F30: 25019.8 | G30: =F30/F29-1 -> 0.0067053874 | I30: Total | J30: 102 | K30: 0.14012202
B31: 45781 | C31: 527.45 | D31: =C31/C30-1 -> -0.063975155 | F31: 24008 | G31: =F31/F30-1 -> -0.040439972
B32: 45774 | C32: 531.7 | D32: =C32/C31-1 -> 0.0080576358 | F32: 24346.7 | G32: =F32/F31-1 -> 0.014107797 | J32: Coefficients | K32: Standard Error | L32: t Stat | M32: P-value | N32: Lower 95% | O32: Upper 95% | P32: Lower 95.0% | Q32: Upper 95.0%
B33: 45767 | C33: 548.7 | D33: =C33/C32-1 -> 0.031972917 | F33: 24039.35 | G33: =F33/F32-1 -> -0.012623887 | I33: Intercept | J33: 0.00031477339 | K33: 0.0031960254 | L33: 0.098489014 | M33: 0.9217392 | N33: -0.0060252813 | O33: 0.006654828 | P33: -0.0060252813 | Q33: 0.006654828
B34: 45760 | C34: 569.8 | D34: =C34/C33-1 -> 0.038454529 | F34: 23851.65 | G34: =F34/F33-1 -> -0.0078080314 | I34: X Variable 1 | J34: 1.0716281 | K34: 0.18341524 | L34: 5.8426339 | M34: 6.3097538e-08 | N34: 0.70778161 | O34: 1.4354746 | P34: 0.70778161 | Q34: 1.4354746
B35: 45753 | C35: 548.65 | D35: =C35/C34-1 -> -0.037118287 | F35: 22828.55 | G35: =F35/F34-1 -> -0.042894307
B36: 45746 | C36: 528.2 | D36: =C36/C35-1 -> -0.037273307 | F36: 22904.45 | G36: =F36/F35-1 -> 0.0033247841
B37: 45739 | C37: 538.35 | D37: =C37/C36-1 -> 0.019216206 | F37: 23519.35 | G37: =F37/F36-1 -> 0.026846312
B38: 45732 | C38: 514.5 | D38: =C38/C37-1 -> -0.044302034 | F38: 23350.4 | G38: =F38/F37-1 -> -0.0071834468
B39: 45725 | C39: 485.8 | D39: =C39/C38-1 -> -0.055782313 | F39: 22397.2 | G39: =F39/F38-1 -> -0.040821571
B40: 45718 | C40: 499.8 | D40: =C40/C39-1 -> 0.028818444 | F40: 22552.5 | G40: =F40/F39-1 -> 0.0069339025
B41: 45711 | C41: 464.95 | D41: =C41/C40-1 -> -0.069727891 | F41: 22124.7 | G41: =F41/F40-1 -> -0.018969072
B42: 45704 | C42: 481.95 | D42: =C42/C41-1 -> 0.036563071 | F42: 22795.9 | G42: =F42/F41-1 -> 0.030337135
B43: 45697 | C43: 489.5 | D43: =C43/C42-1 -> 0.015665525 | F43: 22929.25 | G43: =F43/F42-1 -> 0.0058497361
B44: 45690 | C44: 512.75 | D44: =C44/C43-1 -> 0.047497446 | F44: 23559.95 | G44: =F44/F43-1 -> 0.027506351
B45: 45683 | C45: 512.8 | D45: =C45/C44-1 -> 9.7513408e-05 | F45: 23508.4 | G45: =F45/F44-1 -> -0.0021880352
B46: 45676 | C46: 551.8 | D46: =C46/C45-1 -> 0.076053042 | F46: 23092.2 | G46: =F46/F45-1 -> -0.01770431
... B113: 45207 | C113: 439.9 | D113: =C113/C112-1 -> 0.02100499 | F113: 19751.05 | G113: =F113/F112-1 -> 0.010663856

Sheet Grasim_Beta
B5: Regression Beta
B7: =WACC!B16&" Returns" -> Grasim Inds Returns | F7: Nifty Returns | I7: Beta Drifting
B9: Date | C9: Closing Price | D9: Weekly Returns | F9: Closing Price | G9: Weekly Returns | I9: Levered Raw Beta | J9: =J34 -> 0.99528527
B10: 45928 | C10: 2873 | F10: 24894.25 | I10: Raw Beta Weight | J10: 0.75
B11: 45921 | C11: 2836.2 | D11: =C11/C10-1 -> -0.012808911 | F11: 24654.7 | G11: =F11/F10-1 -> -0.009622704
B12: 45914 | C12: 2811 | D12: =C12/C11-1 -> -0.008885128 | F12: 25327.05 | G12: =F12/F11-1 -> 0.027270662 | I12: Market Beta | J12: 1
B13: 45907 | C13: 2791.4 | D13: =C13/C12-1 -> -0.0069726076 | F13: 25114 | G13: =F13/F12-1 -> -0.0084119548 | I13: Market Beta Weight | J13: 0.25
B14: 45900 | C14: 2746.8 | D14: =C14/C13-1 -> -0.015977646 | F14: 24741 | G14: =F14/F13-1 -> -0.014852274
B15: 45893 | C15: 2877.9 | D15: =C15/C14-1 -> 0.047728266 | F15: 24426.85 | G15: =F15/F14-1 -> -0.012697547 | I15: Adjusted Beta | J15: =(J9*J10)+(J12*J13) -> 0.99646396
B16: 45886 | C16: 2802 | D16: =C16/C15-1 -> -0.026373397 | F16: 24870.1 | G16: =F16/F15-1 -> 0.018146016
B17: 45879 | C17: 2804 | D17: =C17/C16-1 -> 0.00071377587 | F17: 24631.3 | G17: =F17/F16-1 -> -0.0096018914 | I17: SUMMARY OUTPUT
B18: 45872 | C18: 2775.6 | D18: =C18/C17-1 -> -0.010128388 | F18: 24363.3 | G18: =F18/F17-1 -> -0.010880465
B19: 45865 | C19: 2813.8 | D19: =C19/C18-1 -> 0.01376279 | F19: 24565.35 | G19: =F19/F18-1 -> 0.0082932115 | I19: Regression Statistics
B20: 45858 | C20: 2764.9 | D20: =C20/C19-1 -> -0.017378634 | F20: 24837 | G20: =F20/F19-1 -> 0.011058259 | I20: Multiple R | J20: 0.053833216
B21: 45851 | C21: 2691.6 | D21: =C21/C20-1 -> -0.026510905 | F21: 24968.4 | G21: =F21/F20-1 -> 0.005290494 | I21: R Square | J21: 0.0028980152
B22: 45844 | C22: 2722.2 | D22: =C22/C21-1 -> 0.011368703 | F22: 25149.85 | G22: =F22/F21-1 -> 0.0072671857 | I22: Adjusted R Square | J22: -0.0069742817
B23: 45837 | C23: 2708.6 | D23: =C23/C22-1 -> -0.0049959592 | F23: 25461 | G23: =F23/F22-1 -> 0.012371843 | I23: Standard Error | J23: 0.32250615
B24: 45830 | C24: 2728.5 | D24: =C24/C23-1 -> 0.0073469689 | F24: 25637.8 | G24: =F24/F23-1 -> 0.0069439535 | I24: Observations | J24: 103
B25: 45823 | C25: 2762 | D25: =C25/C24-1 -> 0.012277808 | F25: 25112.4 | G25: =F25/F24-1 -> -0.020493178
B26: 45816 | C26: 2805.9 | D26: =C26/C25-1 -> 0.01589428 | F26: 24718.6 | G26: =F26/F25-1 -> -0.015681496 | I26: ANOVA
B27: 45809 | C27: 2861.1 | D27: =C27/C26-1 -> 0.019672832 | F27: 25003.05 | G27: =F27/F26-1 -> 0.011507529 | J27: df | K27: SS | L27: MS | M27: F | N27: Significance F
B28: 45802 | C28: 2712.6 | D28: =C28/C27-1 -> -0.051903114 | F28: 24750.7 | G28: =F28/F27-1 -> -0.010092769 | I28: Regression | J28: 1 | K28: 0.030532224 | L28: 0.030532224 | M28: 0.29355024 | N28: 0.58914766
B29: 45795 | C29: 2663.8 | D29: =C29/C28-1 -> -0.01799012 | F29: 24853.15 | G29: =F29/F28-1 -> 0.0041392769 | I29: Residual | J29: 101 | K29: 10.505032 | L29: 0.10401021
B30: 45788 | C30: 2574.4 | D30: =C30/C29-1 -> -0.033561078 | F30: 25019.8 | G30: =F30/F29-1 -> 0.0067053874 | I30: Total | J30: 102 | K30: 10.535564
B31: 45781 | C31: 2545.8 | D31: =C31/C30-1 -> -0.011109385 | F31: 24008 | G31: =F31/F30-1 -> -0.040439972
B32: 45774 | C32: 2659.4 | D32: =C32/C31-1 -> 0.044622516 | F32: 24346.7 | G32: =F32/F31-1 -> 0.014107797 | J32: Coefficients | K32: Standard Error | L32: t Stat | M32: P-value | N32: Lower 95% | O32: Upper 95% | P32: Lower 95.0% | Q32: Upper 95.0%
B33: 45767 | C33: 2804.2 | D33: =C33/C32-1 -> 0.054448372 | F33: 24039.35 | G33: =F33/F32-1 -> -0.012623887 | I33: Intercept | J33: 0.030423988 | K33: 0.032009666 | L33: 0.95046251 | M33: 0.34414618 | N33: -0.03307458 | O33: 0.093922555 | P33: -0.03307458 | Q33: 0.093922555
B34: 45760 | C34: 2634.8 | D34: =C34/C33-1 -> -0.060409386 | F34: 23851.65 | G34: =F34/F33-1 -> -0.0078080314 | I34: X Variable 1 | J34: 0.99528527 | K34: 1.8369882 | L34: 0.54180277 | M34: 0.58914766 | N34: -2.6488051 | O34: 4.6393756 | P34: -2.6488051 | Q34: 4.6393756
B35: 45753 | C35: 2718.3 | D35: =C35/C34-1 -> 0.03169121 | F35: 22828.55 | G35: =F35/F34-1 -> -0.042894307
B36: 45746 | C36: 2734.8 | D36: =C36/C35-1 -> 0.0060699702 | F36: 22904.45 | G36: =F36/F35-1 -> 0.0033247841
B37: 45739 | C37: 2760.7 | D37: =C37/C36-1 -> 0.009470528 | F37: 23519.35 | G37: =F37/F36-1 -> 0.026846312
B38: 45732 | C38: 2651.25 | D38: =C38/C37-1 -> -0.039645742 | F38: 23350.4 | G38: =F38/F37-1 -> -0.0071834468
B39: 45725 | C39: 2616.9 | D39: =C39/C38-1 -> -0.012956153 | F39: 22397.2 | G39: =F39/F38-1 -> -0.040821571
B40: 45718 | C40: 2611.15 | D40: =C40/C39-1 -> -0.0021972563 | F40: 22552.5 | G40: =F40/F39-1 -> 0.0069339025
B41: 45711 | C41: 2469.4 | D41: =C41/C40-1 -> -0.054286426 | F41: 22124.7 | G41: =F41/F40-1 -> -0.018969072
B42: 45704 | C42: 2370.2 | D42: =C42/C41-1 -> -0.040171702 | F42: 22795.9 | G42: =F42/F41-1 -> 0.030337135
B43: 45697 | C43: 2407.25 | D43: =C43/C42-1 -> 0.015631592 | F43: 22929.25 | G43: =F43/F42-1 -> 0.0058497361
B44: 45690 | C44: 2306.65 | D44: =C44/C43-1 -> -0.041790425 | F44: 23559.95 | G44: =F44/F43-1 -> 0.027506351
B45: 45683 | C45: 2431.05 | D45: =C45/C44-1 -> 0.053931026 | F45: 23508.4 | G45: =F45/F44-1 -> -0.0021880352
B46: 45676 | C46: 2431.3 | D46: =C46/C45-1 -> 0.00010283622 | F46: 23092.2 | G46: =F46/F45-1 -> -0.01770431
... B113: 45207 | C113: 8369 | D113: =C113/C112-1 -> -0.010879264 | F113: 19751.05 | G113: =F113/F112-1 -> 0.010663856

Sheet Raw FS
B2: Particulars | C2: 42430 | D2: 42795 | E2: 43160 | F2: 43525 | G2: 43891 | H2: 44256 | I2: 44621 | J2: 44986 | K2: 45352 | L2: 45717
B3: Income Statement
B4: Sales | C4: 25153 | D4: 25375 | E4: 30979 | F4: 41462 | G4: 42430 | H4: 44726 | I4: 52599 | J4: 63240 | K4: 70908 | L4: 75955
B5: Expenses | C5: 20252 | D5: 20162 | E5: 24834 | F5: 34115 | G5: 33184 | H5: 33158 | I5: 41084 | J5: 52620 | K5: 57930 | L5: 63158
B6: Operating Profit | C6: 4901 | D6: 5212 | E6: 6145 | F6: 7347 | G6: 9246 | H6: 11568 | I6: 11514 | J6: 10620 | K6: 12979 | L6: 12797
B8: Other Income | C8: 464 | D8: 648 | E8: 242 | F8: 350 | G8: 651 | H8: 619 | I8: 669 | J8: 507 | K8: 557 | L8: 397
B9: Exceptional items | C9: 63 | D9: 68 | E9: -232 | F9: 8 | G9: 82 | H9: 40 | I9: 350 | J9: 32 | K9: 17 | L9: -57
B10: Other income normal | C10: 401 | D10: 580 | E10: 474 | F10: 342 | G10: 569 | H10: 578 | I10: 320 | J10: 475 | K10: 540 | L10: 454
B11: Interest | C11: 566 | D11: 640 | E11: 1238 | F11: 1778 | G11: 1992 | H11: 1486 | I11: 945 | J11: 823 | K11: 968 | L11: 1651
B12: Depreciation | C12: 1377 | D12: 1348 | E12: 1848 | F12: 2451 | G12: 2723 | H12: 2700 | I12: 2715 | J12: 2888 | K12: 3145 | L12: 4015
B13: Profit before tax | C13: 3421 | D13: 3872 | E13: 3301 | F13: 3468 | G13: 5183 | H13: 8001 | I13: 8524 | J13: 7416 | K13: 9422 | L13: 7528
B15: Tax % | C15: 0.28 | D15: 0.3 | E15: 0.33 | F15: 0.31 | G15: -0.11 | H15: 0.32 | I15: 0.14 | J15: 0.32 | K15: 0.26 | L15: 0.2
B16: Net Profit | C16: 2480 | D16: 2714 | E16: 2224 | F16: 2400 | G16: 5751 | H16: 5462 | I16: 7334 | J16: 5073 | K16: 7004 | L16: 6040
B18: Balance Sheet
B19: Equity Capital | C19: 274 | D19: 275 | E19: 275 | F19: 275 | G19: 289 | H19: 289 | I19: 289 | J19: 289 | K19: 289 | L19: 295
B20: Reserves | C20: 21671 | D20: 24117 | E20: 26107 | F20: 33476 | G20: 38755 | H20: 43886 | I20: 50147 | J20: 54036 | K20: 59939 | L20: 70412
B21: Borrowings | C21: 10616 | D21: 8474 | E21: 19480 | F21: 25337 | G21: 23019 | H21: 21719 | I21: 11299 | J21: 11058 | K21: 11403 | L21: 24102
B22: Long term Borrowings | C22: 4897 | D22: 6371 | E22: 15863 | F22: 20650 | G22: 17368 | H22: 13548 | I22: 5303 | J22: 5356 | K22: 5308 | L22: 15781
B23: Short term Borrowings | C23: 2476 | D23: 1079 | E23: 2763 | F23: 3668 | G23: 4106 | H23: 6939 | I23: 4900 | J23: 4544 | K23: 4991 | L23: 7250
B24: Lease Liabilities | C24: 0 | D24: 0 | E24: 0 | F24: 0 | G24: 0 | H24: 1232 | I24: 1096 | J24: 1157 | K24: 1105 | L24: 1071
B25: Other Borrowings | C25: 3244 | D25: 1024 | E25: 853 | F25: 1018 | G25: 1545 | H25: 0 | I25: 0 | J25: 0 | K25: 0 | L25: 0
B26: Other Liabilities | C26: 8631 | D26: 9343 | E26: 11280 | F26: 17438 | G26: 17151 | H26: 20282 | I26: 22077 | J26: 25998 | K26: 29167 | L26: 38823
B27: Non controlling int | C27: 15 | D27: 10 | E27: 16 | F27: 12 | G27: 8 | H27: 6 | I27: -3 | J27: 56 | K27: 56 | L27: 3187
B28: Trade Payables | C28: 1717 | D28: 1849 | E28: 2385 | F28: 3160 | G28: 3363 | H28: 4548 | I28: 5863 | J28: 7209 | K28: 8478 | L28: 9327
B29: Advance from Customers | C29: 166 | D29: 196 | E29: 305 | F29: 357 | G29: 464 | H29: 415 | I29: 465 | J29: 384 | K29: 527 | L29: 541
B30: Other liability items | C30: 6733 | D30: 7288 | E30: 8574 | F30: 13909 | G30: 13316 | H30: 15313 | I30: 15753 | J30: 18349 | K30: 20106 | L30: 25768
... B54: Total Assets | C54: 41193 | D54: 42209 | E54: 57141 | F54: 76525 | G54: 79214 | H54: 86176 | I54: 83811 | J54: 91380 | K54: 100797 | L54: 133632
B56: Cash from Operating Activity | C56: =C57+C63+C64 -> 4525 | D56: =D57+D63+D64 -> 5005 | E56: =E57+E63+E64 -> 3888 | F56: =F57+F63+F64 -> 5956 | G56: =G57+G63+G64 -> 8973 | H56: =H57+H63+H64 -> 12500 | I56: =I57+I63+I64 -> 9283 | J56: =J57+J63+J64 -> 9069 | ... L56: =L57+L63+L64 -> 10673
B57: Profit from operations | C57: 4948 | D57: 5220 | E57: 5986 | F57: 7362 | G57: 9348 | H57: 11465 | I57: 11311 | J57: 10530 | K57: 13029 | L57: 12645
B58: Receivables | C58: -287 | D58: 156 | E58: -454 | F58: -279 | G58: 473 | H58: -201 | I58: -495 | J58: -752 | K58: -421 | L58: -608
B59: Inventory | C59: 374 | D59: 54 | E59: -623 | F59: -15 | G59: -64 | H59: 165 | I59: -1579 | J59: -992 | K59: -1712 | L59: -317
B60: Payables | C60: 310 | D60: 482 | E60: 346 | F60: 766 | G60: 279 | H60: 2868 | I60: 2077 | J60: 1869 | K60: 1959 | L60: -476
B61: Loans Advances | C61: 0 | D61: 0 | E61: 0 | F61: 0 | G61: 0 | H61: 0 | I61: 0 | J61: 0 | K61: 0 | L61: 0
B62: Other WC items | C62: 32 | D62: -162 | E62: -525 | F62: -1167 | G62: -172 | H62: -505 | I62: -476 | J62: -461 | K62: -308 | L62: 729
B63: Working capital changes | C63: 429 | D63: 529 | E63: -1255 | F63: -696 | G63: 516 | H63: 2326 | I63: -473 | J63: -337 | K63: -481 | L63: -671
B64: Direct taxes | C64: -852 | D64: -744 | E64: -843 | F64: -710 | G64: -891 | H64: -1291 | I64: -1555 | J64: -1124 | K64: -1651 | L64: -1301
B65: Other operating items | C65: 0 | D65: 0 | E65: 0 | F65: 0 | G65: 0 | H65: 0 | I65: 0 | J65: 0 | K65: 0 | L65: 0
B66: Cash from Investing Activity | C66: =SUM(C67:C77) -> -3675 | D66: =SUM(D67:D77) -> -2501 | E66: =SUM(E67:E77) -> 1866 | F66: =SUM(F67:F77) -> 1164 | G66: =SUM(G67:G77) -> -4193 | H66: =SUM(H67:H77) -> -8856 | I66: =SUM(I67:I77) -> 2322 | J66: =SUM(J67:J77) -> -7187 | ... L66: =SUM(L67:L77) -> -15835
B67: Fixed assets purchased | C67: -2150 | D67: -1402 | E67: -2103 | F67: -1808 | G67: -1766 | H67: -1925 | I67: -5613 | J67: -6200 | K67: -9006 | L67: -9129
B68: Fixed assets sold | C68: 18 | D68: 35 | E68: 220 | F68: 160 | G68: 79 | H68: 86 | I68: 73 | J68: 95 | K68: 122 | L68: 179
B69: Investments purchased | C69: -2698 | D69: -3377 | E69: -3960 | F69: -1700 | G69: -6086 | H69: -12689 | I69: -7795 | J69: -7260 | K69: -7750 | L69: -15885
B70: Investments sold | C70: 2948 | D70: 2228 | E70: 5588 | F70: 4478 | G70: 3443 | H70: 7101 | I70: 13965 | J70: 7156 | K70: 7164 | L70: 19115
B71: Interest received | C71: 59 | D71: 47 | E71: 67 | F71: 78 | G71: 89 | H71: 77 | I71: 174 | J71: 283 | K71: 161 | L71: 342
B72: Dividends received | C72: 0 | D72: 0 | E72: 0 | F72: 22 | G72: 32 | H72: 0 | I72: 0 | J72: 0 | K72: 0 | L72: 1
B73: Invest in subsidiaries | C73: -13 | D73: 0 | E73: 0 | F73: 0 | G73: 0 | H73: 0 | I73: 0 | J73: 0 | K73: 0 | L73: 0
B74: Investment in group cos | C74: 0 | D74: 0 | E74: -1 | F74: -8 | G74: -6 | H74: -3 | I74: 0 | J74: 0 | K74: 0 | L74: 0
B75: Redemp n Canc of Shares | C75: 0 | D75: 0 | E75: 0 | F75: 0 | G75: 0 | H75: 0 | I75: 0 | J75: 3 | K75: 0 | L75: 36
B76: Acquisition of companies | C76: 0 | D76: 0 | E76: 0 | F76: 0 | G76: 0 | H76: 0 | I76: 0 | J76: -847 | K76: -60 | L76: -10262
B77: Other investing items | C77: -1839 | D77: -32 | E77: 2055 | F77: -58 | G77: 22 | H77: -1503 | I77: 1518 | J77: -417 | K77: 581 | L77: -232
B78: Cash from Financing Activity | C78: =SUM(C79:C85) -> -843 | D78: =SUM(D79:D85) -> -2535 | E78: =SUM(E79:E85) -> -5735 | F78: =SUM(F79:F85) -> -6757 | G78: =SUM(G79:G85) -> -5076 | H78: =SUM(H79:H85) -> -4356 | I78: =SUM(I79:I85) -> -12497 | J78: =SUM(J79:J85) -> -1631 | ... L78: =SUM(L79:L85) -> 5076
B79: Proceeds from shares | C79: 3 | D79: 7 | E79: 16 | F79: 5 | G79: 3 | H79: 14 | I79: 13 | J79: 13 | K79: 18 | L79: 33
B80: Proceeds from borrowings | C80: 2821 | D80: 3656 | E80: 15775 | F80: 9772 | G80: 1510 | H80: 4103 | I80: 175 | J80: 1032 | K80: 1399 | L80: 9410
B81: Repayment of borrowings | C81: -2775 | D81: -5272 | E81: -19982 | F81: -14420 | G81: -4154 | H81: -6499 | I81: -10346 | J81: -579 | K81: -1069 | L81: -550
B82: Interest paid fin | C82: -596 | D82: -614 | E82: -1210 | F82: -1685 | G82: -1950 | H82: -1481 | I82: -1026 | J82: -765 | K82: -917 | L82: -1540
B83: Dividends paid | C83: -297 | D83: -312 | E83: -334 | F83: -346 | G83: -380 | H83: -375 | I83: -1065 | J83: -1091 | K83: -1094 | L83: -2012
B84: Financial liabilities | C84: 0 | D84: 0 | E84: 0 | F84: 0 | G84: -101 | H84: -118 | I84: -157 | J84: -126 | K84: -162 | L84: -165
B85: Other financing items | C85: 1 | D85: 0 | E85: 0 | F85: -83 | G85: -4 | H85: 0 | I85: -91 | J85: -115 | K85: -100 | L85: -100
B86: Net Cash Flow | C86: =C78+C66+C56 -> 7 | D86: =D78+D66+D56 -> -31 | E86: =E78+E66+E56 -> 19 | F86: =F78+F66+F56 -> 363 | G86: =G78+G66+G56 -> -296 | H86: =H78+H66+H56 -> -712 | I86: =I78+I66+I56 -> -892 | J86: =J78+J66+J56 -> 251 | ... L86: =L78+L66+L56 -> -86

Sheet Comps Rel.
B2: S.No. | C2: Name | D2: CMP Rs. | E2: No. Eq. Shares Cr. | F2: Market Cap | G2: Debt Rs.Cr. | H2: Cash End Rs.Cr. | I2: Net Debt | J2: EV Rs.Cr. | K2: Sales Rs.Cr. | L2: NP 12M Rs.Cr. | M2: EV / EBITDA | N2: EBITDA | O2: EBITDA Margin | Q2: Shareholder's name | R2: Total Shares Held | S2: Shareholding (%) | T2: Quarter Ending | V2: 10000000
B3: 1 | C3: UltraTech Cem. | D3: 11764 | E3: 29.47 | F3: =D3*E3 -> 346685.08 | G3: 25214.91 | H3: 1673.32 | I3: =G3-H3 -> 23541.59 | J3: 375125.48 | K3: 81724.53 | L3: 7297.12 | M3: 23.89 | N3: =J3/M3 -> 15702.197 | O3: =N3/K3 -> 0.19213566 | Q3: Grasim Industries Limited | R3: 16.533515 | S3: 0.5611 | T3: =R3*'One-Page'!$K$43 -> 197360.57
B4: 2 | C4: Grasim Inds | D4: 2841.3 | E4: 68.05 | F4: =D4*E4 -> 193350.46 | G4: 186325.56 | H4: 7905.42 | I4: =G4-H4 -> 178420.14 | J4: 371776.28 | K4: 153326.53 | L4: 8574.66 | M4: 11.54 | N4: =J4/M4 -> 32216.315 | O4: =N4/K4 -> 0.21011573 | Q4: LIFE INSURANCE CORPORATION OF INDIA | R4: 0.6104355 | S4: 0.0207 | T4: =R4*'One-Page'!$K$43 -> 7286.7686
B5: 3 | C5: Ambuja Cements | D5: 555 | E5: 247.18 | F5: =D5*E5 -> 137184.9 | G5: 788.5 | H5: 6172.16 | I5: =G5-H5 -> -5383.66 | J5: 131802.54 | K5: 37114.29 | L5: 5344.88 | M5: 14.29 | N5: =J5/M5 -> 9223.4108 | O5: =N5/K5 -> 0.24851373 | Q5: ICICI PRUDENTIAL NIFTY INFRASTRUCTURE ETF | R5: 0.6038328 | S5: 0.0205 | T5: =R5*'One-Page'!$K$43 -> 7207.9521
B6: 4 | C6: Shree Cement | D6: 28705 | E6: 3.61 | F6: =D6*E6 -> 103625.05 | G6: 1046.13 | H6: 293.58 | I6: =G6-H6 -> 752.55 | J6: 104322.34 | K6: 19439.75 | L6: 1489.01 | M6: 20.76 | N6: =J6/M6 -> 5025.1609 | O6: =N6/K6 -> 0.25849925 | Q6: NPS TRUST-A/C TATA PENSION FUND MANAGEMENT PRIVATE | R6: 0.5769186 | S6: 0.0196 | T6: =R6*'One-Page'!$K$43 -> 6886.6773
B7: 5 | C7: J K Cements | D7: 6257.5 | E7: 7.73 | F7: =D7*E7 -> 48370.475 | G7: 6028.23 | H7: 1369.67 | I7: =G7-H7 -> 4658.56 | J7: 53009.17 | K7: 12424.11 | L7: 1011.6 | M7: 21.96 | N7: =J7/M7 -> 2413.8966 | O7: =N7/K7 -> 0.19429131 | Q7: Pilani Investment and Industries Corporation Limited | R7: 0.4405944 | S7: 0.015 | T7: =R7*'One-Page'!$K$43 -> 5259.3754
B8: 6 | C8: Dalmia BharatLtd | D8: 2098.4 | E8: 18.76 | F8: =D8*E8 -> 39365.984 | G8: 5702 | H8: 158 | I8: =G8-H8 -> 5544 | J8: 44902.67 | K8: 14325 | L8: 1139 | M8: 14.36 | N8: =J8/M8 -> 3126.9269 | O8: =N8/K8 -> 0.2182846 | Q8: SBI NIFTY 50 EQUAL WEIGHT INDEX FUND | R8: 0.4310567 | S8: 0.0146 | T8: =R8*'One-Page'!$K$43 -> 5145.5238
B9: 7 | C9: ACC | D9: 1850.1 | E9: 18.78 | F9: =D9*E9 -> 34744.878 | G9: 429.77 | H9: 1649.27 | I9: =G9-H9 -> -1219.5 | J9: 33523.02 | K9: 22742.68 | L9: 2417.95 | M9: 7.92 | N9: =J9/M9 -> 4232.7045 | O9: =N9/K9 -> 0.18611283 | Q9: Government of Singapore - E | R9: 0.3937328 | S9: 0.0134 | T9: =R9*'One-Page'!$K$43 -> 4699.9884
B10: 8 | C10: The Ramco Cement | D10: 1046.8 | E10: 23.63 | F10: =D10*E10 -> 24735.884 | G10: 4674.61 | H10: 209.15 | I10: =G10-H10 -> 4465.46 | J10: 29200.55 | K10: 8498.87 | L10: 317.56 | M10: 21.65 | N10: =J10/M10 -> 1348.7552 | O10: =N10/K10 -> 0.15869818 | Q10: KOTAK AGGRESSIVE HYBRID FUND | R10: 0.3256356 | S10: 0.0111 | T10: =R10*'One-Page'!$K$43 -> 3887.1122
B11: 9 | C11: JSW Cement | D11: 135.27 | E11: 136.34 | F11: =D11*E11 -> 18442.712 | G11: 6562.53 | H11: 123.52 | I11: =G11-H11 -> 6439.01 | J11: 24881.25 | K11: 5785.29 | L11: -163.77 | M11: 34.64 | N11: =J11/M11 -> 718.28089 | O11: =N11/K11 -> 0.12415642 | Q11: PT. Indo Bharat Rayon | R11: 0.2286172 | S11: 0.0078 | T11: =R11*'One-Page'!$K$43 -> 2729.0035
B12: 10 | C12: Nuvoco Vistas | D12: 414.9 | E12: 35.72 | F12: =D12*E12 -> 14820.228 | G12: 5803.75 | H12: 182.33 | I12: =G12-H12 -> 5621.42 | J12: 20395.14 | K12: 10781.88 | L12: 273.76 | M12: 11.87 | N12: =J12/M12 -> 1718.2089 | O12: =N12/K12 -> 0.15936079 | Q12: Hindalco Industries Limited | R12: 0.1258515 | S12: 0.0043 | T12: =R12*'One-Page'!$K$43 -> 1502.2894
B13: 11 | C13: India Cements | D13: 390.3 | E13: 30.99 | F13: =D13*E13 -> 12095.397 | G13: 1340.37 | H13: 104.13 | I13: =G13-H13 -> 1236.24 | J13: 13396.27 | K13: 4279.89 | L13: 12.56 | M13: 279.55 | N13: =J13/M13 -> 47.920837 | O13: =N13/K13 -> 0.011196745
B14: 12 | C14: JK Lakshmi Cem. | D14: 832.95 | E14: 12.41 | F14: =D14*E14 -> 10336.91 | G14: 2613.91 | H14: 196.9 | I14: =G14-H14 -> 2417.01 | J14: 12757.62 | K14: 6369.67 | L14: 366.45 | M14: 12.68 | N14: =J14/M14 -> 1006.1215 | O14: =N14/K14 -> 0.15795504
B15: 13 | C15: Star Cement | D15: 251 | E15: 40.42 | F15: =D15*E15 -> 10145.42 | G15: 402.75 | H15: 52.43 | I15: =G15-H15 -> 350.32 | J15: 10495.25 | K15: 3324.39 | L15: 236 | M15: 14.96 | N15: =J15/M15 -> 701.55414 | O15: =N15/K15 -> 0.21103244 | Q15: Chairman and Non-Executive Director
B16: 14 | C16: Birla Corpn. | D16: 1168.8 | E16: 7.7 | F16: =D16*E16 -> 8999.76 | G16: 3488.58 | H16: 126.48 | I16: =G16-H16 -> 3362.1 | J16: 12363.03 | K16: 9478.34 | L16: 382.17 | M16: 8.72 | N16: =J16/M16 -> 1417.7787 | O16: =N16/K16 -> 0.1495809 | Q16: Non-Executive Director
B17: 15 | C17: Prism Johnson | D17: 158.38 | E17: 50.34 | F17: =D17*E17 -> 7972.8492 | G17: 1977.8 | H17: 478.22 | I17: =G17-H17 -> 1499.58 | J17: 9471.8 | K17: 7530.11 | L17: 57.81 | M17: 15.92 | N17: =J17/M17 -> 594.96231 | O17: =N17/K17 -> 0.079011105 | Q17: Vice Chairman and Non-Executive
B18: 16 | C18: Heidelberg Cem. | D18: 194.37 | E18: 22.66 | F18: =D18*E18 -> 4404.4242 | G18: 75.41 | H18: 478.16 | I18: =G18-H18 -> -402.75 | J18: 4001.93 | K18: 2214.23 | L18: 115.08 | M18: 13.67 | N18: =J18/M18 -> 292.75274 | O18: =N18/K18 -> 0.13221424 | Q18: Director
B19: 17 | C19: Orient Cement | D19: 213.18 | E19: 20.55 | F19: =D19*E19 -> 4380.849 | G19: 69.73 | H19: 48.87 | I19: =G19-H19 -> 20.86 | J19: 4400.85 | K19: 2879.05 | L19: 259.9 | M19: 10.9 | N19: =J19/M19 -> 403.74771 | O19: =N19/K19 -> 0.14023643 | Q19: Not Applicable -
B20: 18 | C20: Sagar Cements | D20: 227.92 | E20: 13.07 | F20: =D20*E20 -> 2978.9144 | G20: 1640.01 | H20: 163.72 | I20: =G20-H20 -> 1476.29 | J20: 4444.26 | K20: 2494.44 | L20: -164.18 | M20: 16.83 | N20: =J20/M20 -> 264.06774 | O20: =N20/K20 -> 0.10586253 | Q20: Managing Director 8.05% 247.5
B21: 19 | C21: K C P | D21: 199.89 | E21: 12.89 | F21: =D21*E21 -> 2576.5821 | G21: 542.15 | H21: 977.93 | I21: =G21-H21 -> -435.78 | J21: 2141.23 | K21: 2514.42 | L21: 291.12 | M21: 4.86 | N21: =J21/M21 -> 440.5823 | O21: =N21/K21 -> 0.17522224 | Q21: Whole-time Director and Chief Financial Officer 12.46% 121.4
B22: 20 | C22: Mangalam Cement | D22: 788.5 | E22: 2.75 | F22: =D22*E22 -> 2168.375 | G22: 627.31 | H22: 167.17 | I22: =G22-H22 -> 460.14 | J22: 2628.3 | K22: 1752.16 | L22: 60.26 | M22: 10.84 | N22: =J22/M22 -> 242.4631 | O22: =N22/K22 -> 0.13837954
B23: 21 | C23: Sanghi Industrie | D23: 63.76 | E23: 25.83 | F23: =D23*E23 -> 1646.9208 | G23: 2506.14 | H23: 21.88 | I23: =G23-H23 -> 2484.26 | J23: 4131.35 | K23: 991.09 | L23: -484.95 | M23: 33.1 | N23: =J23/M23 -> 124.8142 | O23: =N23/K23 -> 0.12593629
B24: 22 | C24: Deccan Cements | D24: 1029.5 | E24: 1.4 | F24: =D24*E24 -> 1441.3 | G24: 714.15 | H24: 144.36 | I24: =G24-H24 -> 569.79 | J24: 2011.86 | K24: 505.39 | L24: 20.07 | M24: 29.65 | N24: =J24/M24 -> 67.853626 | O24: =N24/K24 -> 0.13425993
B25: 23 | C25: Sh. Digvijay Cem | D25: 90.08 | E25: 14.79 | F25: =D25*E25 -> 1332.2832 | G25: 142.98 | H25: 49.94 | I25: =G25-H25 -> 93.04 | J25: 1468.94 | K25: 760.48 | L25: 37.55 | M25: 18.35 | N25: =J25/M25 -> 80.051226 | O25: =N25/K25 -> 0.10526408
B26: 24 | C26: Saurashtra Cem. | D26: 101.72 | E26: 11.13 | F26: =D26*E26 -> 1132.1436 | G26: 135.71 | H26: 235.72 | I26: =G26-H26 -> -100.01 | J26: 1031.66 | K26: 1575.4 | L26: 13.97 | M26: 14.2 | N26: =J26/M26 -> 72.652113 | O26: =N26/K26 -> 0.046116613
B27: 25 | C27: NCL Industries | D27: 198.47 | E27: 4.52 | F27: =D27*E27 -> 897.0844 | G27: 252.47 | H27: 21.38 | I27: =G27-H27 -> 231.09 | J27: 1128.83 | K27: 1393.11 | L27: 32.66 | M27: 7.73 | N27: =J27/M27 -> 146.03234 | O27: =N27/K27 -> 0.1048247

Sheet RM
B7: Return on Markets
B9: Year | C9: Annual | E9: Average Return | G9: {=PRODUCT(1+C10:C34)^(1/25)-1} -> 0.11696191
B10: 2000 | C10: -0.1465 | E10: Dividend Yield | G10: 0.0135
B11: 2001 | C11: -0.1618 | E11: Total Market Returns | G11: =SUM(G9:G10) -> 0.13046191
B12: 2002 | C12: 0.0325
B13: 2003 | C13: 0.719 | E13: Interest TTM | G13: ='Data Sheet'!K27 -> 1650.54
B14: 2004 | C14: 0.1068
B15: 2005 | C15: 0.3634
B16: 2006 | C16: 0.3983
B17: 2007 | C17: 0.5477
B18: 2008 | C18: -0.5179
B19: 2009 | C19: 0.7576
B20: 2010 | C20: 0.1795
B21: 2011 | C21: -0.2462
B22: 2012 | C22: 0.277
B23: 2013 | C23: 0.0676
B24: 2014 | C24: 0.3139
B25: 2015 | C25: -0.0406
... B34: 2024 | C34: 0.0875

Sheet UltraTech_Beta
AA3: Date | AB3: Price | AC3: Vol. | AD3: =AC3 -> Vol. | AF3: Promoters | AG3: 0.5923
AA4: 44200 | AB4: 5327.2 | AC4: 453.78K | AD4: =(IF(RIGHT(AC4,1)="K", VALUE(LEFT(AC4,LEN(AC4)-1))*1000, IF(RIGHT(AC4,1)="M", VALUE(LEFT(AC4,LEN(AC4)-1))*1000000, VALUE(AC4) ) ))/10000 -> 45.378 | AF4: FIIs | AG4: 0.1533
AA5: 44201 | AB5: 5341.2 | AC5: 530.96K | AD5: =(IF(RIGHT(AC5,1)="K", VALUE(LEFT(AC5,LEN(AC5)-1))*1000, IF(RIGHT(AC5,1)="M", VALUE(LEFT(AC5,LEN(AC5)-1))*1000000, VALUE(AC5) ) ))/10000 -> 53.096 | AF5: DIIs | AG5: 0.1665
B6: Regression Beta | AA6: 44202 | AB6: 5448.35 | AC6: 701.45K | AD6: =(IF(RIGHT(AC6,1)="K", VALUE(LEFT(AC6,LEN(AC6)-1))*1000, IF(RIGHT(AC6,1)="M", VALUE(LEFT(AC6,LEN(AC6)-1))*1000000, VALUE(AC6) ) ))/10000 -> 70.145 | AF6: Public & Govt. | AG6: =0.05%+8.55%+0.2% -> 0.088
AA7: 44203 | AB7: 5397.95 | AC7: 742.40K | AD7: =(IF(RIGHT(AC7,1)="K", VALUE(LEFT(AC7,LEN(AC7)-1))*1000, IF(RIGHT(AC7,1)="M", VALUE(LEFT(AC7,LEN(AC7)-1))*1000000, VALUE(AC7) ) ))/10000 -> 74.24
B8: ='Data Sheet'!$B$1&" Returns" -> ULTRATECH CEMENT LTD Returns | F8: Nifty Returns | I8: Beta Drifting | AA8: 44204 | AB8: 5591.75 | AC8: 802.68K | AD8: =(IF(RIGHT(AC8,1)="K", VALUE(LEFT(AC8,LEN(AC8)-1))*1000, IF(RIGHT(AC8,1)="M", VALUE(LEFT(AC8,LEN(AC8)-1))*1000000, VALUE(AC8) ) ))/10000 -> 80.268
AA9: 44207 | AB9: 5623.7 | AC9: 714.58K | AD9: =(IF(RIGHT(AC9,1)="K", VALUE(LEFT(AC9,LEN(AC9)-1))*1000, IF(RIGHT(AC9,1)="M", VALUE(LEFT(AC9,LEN(AC9)-1))*1000000, VALUE(AC9) ) ))/10000 -> 71.458
B10: Date | C10: Closing Price | D10: Weekly Returns | F10: Closing Price | G10: Weekly Returns | I10: Levered Raw Beta | J10: =J35 -> 1.2661066 | AA10: 44208 | AB10: 5639 | AC10: 591.44K | AD10: =(IF(RIGHT(AC10,1)="K", VALUE(LEFT(AC10,LEN(AC10)-1))*1000, IF(RIGHT(AC10,1)="M", VALUE(LEFT(AC10,LEN(AC10)-1))*1000000, VALUE(AC10) ) ))/10000 -> 59.144
B11: 45928 | C11: 12019 | F11: 24894.25 | I11: Raw Beta Weight | J11: 0.75 | AA11: 44209 | AB11: 5650.75 | AC11: 423.24K | AD11: =(IF(RIGHT(AC11,1)="K", VALUE(LEFT(AC11,LEN(AC11)-1))*1000, IF(RIGHT(AC11,1)="M", VALUE(LEFT(AC11,LEN(AC11)-1))*1000000, VALUE(AC11) ) ))/10000 -> 42.324
B12: 45921 | C12: 12070 | D12: =C12/C11-1 -> 0.0042432815 | F12: 24654.7 | G12: =F12/F11-1 -> -0.009622704 | AA12: 44210 | AB12: 5582.35 | AC12: 464.20K | AD12: =(IF(RIGHT(AC12,1)="K", VALUE(LEFT(AC12,LEN(AC12)-1))*1000, IF(RIGHT(AC12,1)="M", VALUE(LEFT(AC12,LEN(AC12)-1))*1000000, VALUE(AC12) ) ))/10000 -> 46.42
B13: 45914 | C13: 12508 | D13: =C13/C12-1 -> 0.036288318 | F13: 25327.05 | G13: =F13/F12-1 -> 0.027270662 | I13: Market Beta | J13: 1 | AA13: 44211 | AB13: 5452.25 | AC13: 589.87K | AD13: =(IF(RIGHT(AC13,1)="K", VALUE(LEFT(AC13,LEN(AC13)-1))*1000, IF(RIGHT(AC13,1)="M", VALUE(LEFT(AC13,LEN(AC13)-1))*1000000, VALUE(AC13) ) ))/10000 -> 58.987
